.class public Demon
.super java/lang/Object
.method public static draw1()V
.limit stack 10
.limit locals 0
sipush 18254
sipush 1008
invokestatic OS/Memory.poke(II)V
sipush 18286
sipush 16112
invokestatic OS/Memory.poke(II)V
sipush 18318
sipush 6272
ineg
invokestatic OS/Memory.poke(II)V
sipush 18350
sipush 29696
ineg
invokestatic OS/Memory.poke(II)V
sipush 18351
iconst_3
invokestatic OS/Memory.poke(II)V
sipush 18382
sipush 4096
invokestatic OS/Memory.poke(II)V
sipush 18383
bipush 7
invokestatic OS/Memory.poke(II)V
sipush 18414
sipush 4096
invokestatic OS/Memory.poke(II)V
sipush 18415
bipush 6
invokestatic OS/Memory.poke(II)V
sipush 18446
sipush 12288
invokestatic OS/Memory.poke(II)V
sipush 18447
bipush 12
invokestatic OS/Memory.poke(II)V
sipush 18448
sipush 1024
invokestatic OS/Memory.poke(II)V
sipush 18478
sipush 4096
ineg
invokestatic OS/Memory.poke(II)V
sipush 18479
bipush 24
invokestatic OS/Memory.poke(II)V
sipush 18480
sipush 1024
invokestatic OS/Memory.poke(II)V
sipush 18510
sipush 4096
ineg
invokestatic OS/Memory.poke(II)V
sipush 18511
bipush 61
invokestatic OS/Memory.poke(II)V
sipush 18512
sipush 1024
invokestatic OS/Memory.poke(II)V
sipush 18542
sipush 4096
ineg
invokestatic OS/Memory.poke(II)V
sipush 18543
sipush 8191
invokestatic OS/Memory.poke(II)V
sipush 18544
sipush 3072
invokestatic OS/Memory.poke(II)V
sipush 18574
sipush 4096
ineg
invokestatic OS/Memory.poke(II)V
sipush 18575
sipush 3585
ineg
invokestatic OS/Memory.poke(II)V
sipush 18576
sipush 3073
invokestatic OS/Memory.poke(II)V
sipush 18606
sipush 4096
ineg
invokestatic OS/Memory.poke(II)V
sipush 18607
bipush 127
invokestatic OS/Memory.poke(II)V
sipush 18608
sipush 7171
invokestatic OS/Memory.poke(II)V
sipush 18638
sipush 14336
invokestatic OS/Memory.poke(II)V
sipush 18640
sipush 29703
invokestatic OS/Memory.poke(II)V
sipush 18670
sipush 30720
invokestatic OS/Memory.poke(II)V
sipush 18672
sipush 15332
ineg
invokestatic OS/Memory.poke(II)V
sipush 18702
sipush 4096
ineg
invokestatic OS/Memory.poke(II)V
sipush 18703
bipush 63
invokestatic OS/Memory.poke(II)V
sipush 18704
sipush 13264
ineg
invokestatic OS/Memory.poke(II)V
sipush 18705
bipush 7
invokestatic OS/Memory.poke(II)V
sipush 18734
sipush 8192
invokestatic OS/Memory.poke(II)V
sipush 18736
sipush 10128
ineg
invokestatic OS/Memory.poke(II)V
sipush 18737
iconst_4
invokestatic OS/Memory.poke(II)V
sipush 18766
sipush 8192
ineg
invokestatic OS/Memory.poke(II)V
sipush 18767
bipush 48
invokestatic OS/Memory.poke(II)V
sipush 18768
sipush 6336
invokestatic OS/Memory.poke(II)V
sipush 18769
iconst_5
invokestatic OS/Memory.poke(II)V
sipush 18798
sipush 16000
ineg
invokestatic OS/Memory.poke(II)V
sipush 18799
bipush 31
invokestatic OS/Memory.poke(II)V
sipush 18800
sipush 28800
invokestatic OS/Memory.poke(II)V
sipush 18801
bipush 59
ineg
invokestatic OS/Memory.poke(II)V
sipush 18802
sipush 1023
invokestatic OS/Memory.poke(II)V
sipush 18829
bipush 32
invokestatic OS/Memory.poke(II)V
sipush 18830
sipush 15488
ineg
invokestatic OS/Memory.poke(II)V
sipush 18831
bipush 63
invokestatic OS/Memory.poke(II)V
sipush 18832
sipush 29056
invokestatic OS/Memory.poke(II)V
sipush 18833
iconst_3
ineg
invokestatic OS/Memory.poke(II)V
sipush 18834
iconst_1
ineg
invokestatic OS/Memory.poke(II)V
sipush 18859
sipush 2048
invokestatic OS/Memory.poke(II)V
sipush 18861
bipush 96
invokestatic OS/Memory.poke(II)V
sipush 18862
sipush 14592
ineg
invokestatic OS/Memory.poke(II)V
sipush 18863
iconst_1
invokestatic OS/Memory.poke(II)V
sipush 18864
sipush 16646
invokestatic OS/Memory.poke(II)V
sipush 18865
sipush 4095
invokestatic OS/Memory.poke(II)V
sipush 18866
sipush 2048
ineg
invokestatic OS/Memory.poke(II)V
sipush 18867
bipush 7
invokestatic OS/Memory.poke(II)V
sipush 18891
sipush 3072
invokestatic OS/Memory.poke(II)V
sipush 18893
bipush 96
invokestatic OS/Memory.poke(II)V
sipush 18894
sipush 13056
ineg
invokestatic OS/Memory.poke(II)V
sipush 18896
sipush 25092
invokestatic OS/Memory.poke(II)V
sipush 18897
sipush 254
invokestatic OS/Memory.poke(II)V
sipush 18898
sipush 16384
ineg
invokestatic OS/Memory.poke(II)V
sipush 18899
bipush 63
invokestatic OS/Memory.poke(II)V
sipush 18923
sipush 3072
invokestatic OS/Memory.poke(II)V
sipush 18925
sipush 224
invokestatic OS/Memory.poke(II)V
sipush 18926
sipush 18691
invokestatic OS/Memory.poke(II)V
sipush 18928
sipush 26126
invokestatic OS/Memory.poke(II)V
sipush 18929
sipush 8161
ineg
invokestatic OS/Memory.poke(II)V
sipush 18930
iconst_1
invokestatic OS/Memory.poke(II)V
sipush 18931
sipush 510
invokestatic OS/Memory.poke(II)V
sipush 18955
sipush 3072
invokestatic OS/Memory.poke(II)V
sipush 18957
sipush 6304
ineg
invokestatic OS/Memory.poke(II)V
sipush 18958
sipush 22847
invokestatic OS/Memory.poke(II)V
sipush 18960
sipush 28190
invokestatic OS/Memory.poke(II)V
sipush 18961
sipush 993
ineg
invokestatic OS/Memory.poke(II)V
sipush 18962
sipush 8191
invokestatic OS/Memory.poke(II)V
sipush 18963
sipush 2016
invokestatic OS/Memory.poke(II)V
sipush 18987
sipush 3072
invokestatic OS/Memory.poke(II)V
sipush 18988
sipush 1024
ineg
invokestatic OS/Memory.poke(II)V
sipush 18989
sipush 225
ineg
invokestatic OS/Memory.poke(II)V
sipush 18990
sipush 20991
invokestatic OS/Memory.poke(II)V
sipush 18991
bipush 12
invokestatic OS/Memory.poke(II)V
sipush 18992
sipush 30751
invokestatic OS/Memory.poke(II)V
sipush 18993
sipush 2047
invokestatic OS/Memory.poke(II)V
sipush 18994
iconst_1
ineg
invokestatic OS/Memory.poke(II)V
sipush 18995
sipush 7937
invokestatic OS/Memory.poke(II)V
sipush 19019
sipush 7168
invokestatic OS/Memory.poke(II)V
sipush 19020
sipush 1536
invokestatic OS/Memory.poke(II)V
sipush 19021
sipush 15904
invokestatic OS/Memory.poke(II)V
sipush 19022
sipush 3712
ineg
invokestatic OS/Memory.poke(II)V
sipush 19023
sipush 255
invokestatic OS/Memory.poke(II)V
sipush 19024
sipush 8141
ineg
invokestatic OS/Memory.poke(II)V
sipush 19025
sipush 257
ineg
invokestatic OS/Memory.poke(II)V
sipush 19026
sipush 8079
invokestatic OS/Memory.poke(II)V
sipush 19027
sipush 30783
invokestatic OS/Memory.poke(II)V
sipush 19051
sipush 5120
invokestatic OS/Memory.poke(II)V
sipush 19052
sipush 1920
invokestatic OS/Memory.poke(II)V
sipush 19053
sipush 23584
invokestatic OS/Memory.poke(II)V
sipush 19054
sipush 28288
ineg
invokestatic OS/Memory.poke(II)V
sipush 19055
sipush 32289
ineg
invokestatic OS/Memory.poke(II)V
sipush 19056
sipush 24625
invokestatic OS/Memory.poke(II)V
sipush 19057
sipush 1024
ineg
invokestatic OS/Memory.poke(II)V
sipush 19058
sipush 14385
invokestatic OS/Memory.poke(II)V
sipush 19059
sipush 24321
ineg
invokestatic OS/Memory.poke(II)V
sipush 19060
iconst_3
invokestatic OS/Memory.poke(II)V
sipush 19083
sipush 13312
invokestatic OS/Memory.poke(II)V
sipush 19084
sipush 960
invokestatic OS/Memory.poke(II)V
sipush 19085
sipush 19552
invokestatic OS/Memory.poke(II)V
sipush 19086
sipush 11360
ineg
invokestatic OS/Memory.poke(II)V
sipush 19087
sipush 6269
ineg
invokestatic OS/Memory.poke(II)V
sipush 19088
sipush 16335
ineg
invokestatic OS/Memory.poke(II)V
sipush 19089
sipush 4095
invokestatic OS/Memory.poke(II)V
sipush 19090
bipush 16
invokestatic OS/Memory.poke(II)V
sipush 19091
sipush 8188
invokestatic OS/Memory.poke(II)V
sipush 19092
bipush 6
invokestatic OS/Memory.poke(II)V
sipush 19115
sipush 25600
invokestatic OS/Memory.poke(II)V
sipush 19116
sipush 992
invokestatic OS/Memory.poke(II)V
sipush 19117
sipush 3696
invokestatic OS/Memory.poke(II)V
sipush 19118
sipush 10320
ineg
invokestatic OS/Memory.poke(II)V
sipush 19119
sipush 253
ineg
invokestatic OS/Memory.poke(II)V
sipush 19120
sipush 32719
ineg
invokestatic OS/Memory.poke(II)V
sipush 19121
sipush 391
ineg
invokestatic OS/Memory.poke(II)V
sipush 19122
bipush 127
invokestatic OS/Memory.poke(II)V
sipush 19123
sipush 32224
invokestatic OS/Memory.poke(II)V
sipush 19124
bipush 8
invokestatic OS/Memory.poke(II)V
sipush 19147
sipush 15360
ineg
invokestatic OS/Memory.poke(II)V
sipush 19148
sipush 499
invokestatic OS/Memory.poke(II)V
sipush 19149
sipush 18384
invokestatic OS/Memory.poke(II)V
sipush 19150
sipush 8272
ineg
invokestatic OS/Memory.poke(II)V
sipush 19151
sipush 505
ineg
invokestatic OS/Memory.poke(II)V
sipush 19152
sipush 32735
ineg
invokestatic OS/Memory.poke(II)V
sipush 19153
sipush 1089
ineg
invokestatic OS/Memory.poke(II)V
sipush 19154
sipush 1023
invokestatic OS/Memory.poke(II)V
sipush 19155
sipush 256
ineg
invokestatic OS/Memory.poke(II)V
sipush 19156
bipush 25
invokestatic OS/Memory.poke(II)V
sipush 19179
sipush 31744
ineg
invokestatic OS/Memory.poke(II)V
sipush 19180
sipush 511
invokestatic OS/Memory.poke(II)V
sipush 19181
sipush 14352
invokestatic OS/Memory.poke(II)V
sipush 19182
sipush 8416
ineg
invokestatic OS/Memory.poke(II)V
sipush 19183
sipush 30723
invokestatic OS/Memory.poke(II)V
sipush 19184
sipush 32720
ineg
invokestatic OS/Memory.poke(II)V
sipush 19185
sipush 32537
ineg
invokestatic OS/Memory.poke(II)V
sipush 19186
sipush 3583
invokestatic OS/Memory.poke(II)V
sipush 19187
sipush 7680
invokestatic OS/Memory.poke(II)V
sipush 19188
bipush 35
invokestatic OS/Memory.poke(II)V
sipush 19211
sipush 31744
ineg
invokestatic OS/Memory.poke(II)V
sipush 19212
sipush 254
invokestatic OS/Memory.poke(II)V
sipush 19213
sipush 3096
invokestatic OS/Memory.poke(II)V
sipush 19214
sipush 16192
ineg
invokestatic OS/Memory.poke(II)V
sipush 19215
sipush 26625
invokestatic OS/Memory.poke(II)V
sipush 19216
sipush 32744
ineg
invokestatic OS/Memory.poke(II)V
sipush 19217
sipush 927
invokestatic OS/Memory.poke(II)V
sipush 19218
sipush 4092
invokestatic OS/Memory.poke(II)V
sipush 19219
sipush 22528
invokestatic OS/Memory.poke(II)V
sipush 19220
sipush 199
invokestatic OS/Memory.poke(II)V
sipush 19243
sipush 31744
ineg
invokestatic OS/Memory.poke(II)V
sipush 19244
sipush 32545
ineg
invokestatic OS/Memory.poke(II)V
sipush 19245
bipush 13
invokestatic OS/Memory.poke(II)V
sipush 19246
sipush 16368
ineg
invokestatic OS/Memory.poke(II)V
sipush 19247
sipush 3072
invokestatic OS/Memory.poke(II)V
sipush 19248
bipush 28
invokestatic OS/Memory.poke(II)V
sipush 19249
sipush 3815
invokestatic OS/Memory.poke(II)V
sipush 19250
sipush 16352
invokestatic OS/Memory.poke(II)V
sipush 19251
sipush 20479
ineg
invokestatic OS/Memory.poke(II)V
sipush 19252
sipush 414
invokestatic OS/Memory.poke(II)V
sipush 19275
sipush 1024
invokestatic OS/Memory.poke(II)V
sipush 19276
sipush 32615
ineg
invokestatic OS/Memory.poke(II)V
sipush 19277
bipush 20
invokestatic OS/Memory.poke(II)V
sipush 19278
sipush 15888
ineg
invokestatic OS/Memory.poke(II)V
sipush 19279
sipush 1024
invokestatic OS/Memory.poke(II)V
sipush 19280
bipush 14
invokestatic OS/Memory.poke(II)V
sipush 19281
sipush 8079
invokestatic OS/Memory.poke(II)V
sipush 19282
sipush 32640
invokestatic OS/Memory.poke(II)V
sipush 19283
sipush 16370
ineg
invokestatic OS/Memory.poke(II)V
sipush 19284
sipush 789
invokestatic OS/Memory.poke(II)V
sipush 19307
sipush 1024
invokestatic OS/Memory.poke(II)V
sipush 19308
sipush 20464
ineg
invokestatic OS/Memory.poke(II)V
sipush 19309
bipush 52
invokestatic OS/Memory.poke(II)V
sipush 19310
sipush 14496
ineg
invokestatic OS/Memory.poke(II)V
sipush 19311
iconst_3
invokestatic OS/Memory.poke(II)V
sipush 19312
iconst_3
invokestatic OS/Memory.poke(II)V
sipush 19313
sipush 15887
invokestatic OS/Memory.poke(II)V
sipush 19314
sipush 32512
invokestatic OS/Memory.poke(II)V
sipush 19315
sipush 16384
sipush 16384
iadd
invokestatic OS/Memory.poke(II)V
sipush 19316
sipush 1591
invokestatic OS/Memory.poke(II)V
sipush 19339
sipush 3072
invokestatic OS/Memory.poke(II)V
sipush 19340
sipush 28688
invokestatic OS/Memory.poke(II)V
sipush 19341
bipush 53
invokestatic OS/Memory.poke(II)V
sipush 19342
sipush 31680
ineg
invokestatic OS/Memory.poke(II)V
sipush 19343
sipush 16353
ineg
invokestatic OS/Memory.poke(II)V
sipush 19344
iconst_1
invokestatic OS/Memory.poke(II)V
sipush 19345
sipush 2017
ineg
invokestatic OS/Memory.poke(II)V
sipush 19346
sipush 1024
ineg
invokestatic OS/Memory.poke(II)V
sipush 19347
bipush 15
invokestatic OS/Memory.poke(II)V
sipush 19348
sipush 3188
invokestatic OS/Memory.poke(II)V
sipush 19371
sipush 2048
invokestatic OS/Memory.poke(II)V
sipush 19372
sipush 256
ineg
invokestatic OS/Memory.poke(II)V
sipush 19373
sipush 245
invokestatic OS/Memory.poke(II)V
sipush 19374
sipush 29248
ineg
invokestatic OS/Memory.poke(II)V
sipush 19375
sipush 28799
invokestatic OS/Memory.poke(II)V
sipush 19376
sipush 16384
sipush 16384
iadd
invokestatic OS/Memory.poke(II)V
sipush 19377
sipush 4065
ineg
invokestatic OS/Memory.poke(II)V
sipush 19378
sipush 4093
ineg
invokestatic OS/Memory.poke(II)V
sipush 19379
iconst_1
invokestatic OS/Memory.poke(II)V
sipush 19380
sipush 6344
invokestatic OS/Memory.poke(II)V
sipush 19403
sipush 6144
invokestatic OS/Memory.poke(II)V
sipush 19404
sipush 128
ineg
invokestatic OS/Memory.poke(II)V
sipush 19405
sipush 1013
invokestatic OS/Memory.poke(II)V
sipush 19406
sipush 2432
invokestatic OS/Memory.poke(II)V
sipush 19407
sipush 8146
invokestatic OS/Memory.poke(II)V
sipush 19408
sipush 16384
sipush 16384
iadd
invokestatic OS/Memory.poke(II)V
sipush 19409
sipush 16321
ineg
invokestatic OS/Memory.poke(II)V
sipush 19410
sipush 8177
ineg
invokestatic OS/Memory.poke(II)V
sipush 19411
bipush 127
invokestatic OS/Memory.poke(II)V
sipush 19412
sipush 12440
invokestatic OS/Memory.poke(II)V
sipush 19435
sipush 14336
invokestatic OS/Memory.poke(II)V
sipush 19436
sipush 32384
ineg
invokestatic OS/Memory.poke(II)V
sipush 19437
sipush 1941
invokestatic OS/Memory.poke(II)V
sipush 19438
sipush 2497
invokestatic OS/Memory.poke(II)V
sipush 19439
bipush 18
invokestatic OS/Memory.poke(II)V
sipush 19440
sipush 16384
ineg
invokestatic OS/Memory.poke(II)V
sipush 19441
sipush 32705
ineg
invokestatic OS/Memory.poke(II)V
sipush 19442
sipush 16321
ineg
invokestatic OS/Memory.poke(II)V
sipush 19443
sipush 965
invokestatic OS/Memory.poke(II)V
sipush 19444
sipush 25496
invokestatic OS/Memory.poke(II)V
sipush 19467
sipush 4096
ineg
invokestatic OS/Memory.poke(II)V
sipush 19468
sipush 227
invokestatic OS/Memory.poke(II)V
sipush 19469
sipush 12087
invokestatic OS/Memory.poke(II)V
sipush 19470
sipush 6337
invokestatic OS/Memory.poke(II)V
sipush 19471
bipush 22
invokestatic OS/Memory.poke(II)V
sipush 19472
sipush 1024
ineg
invokestatic OS/Memory.poke(II)V
sipush 19473
sipush 255
invokestatic OS/Memory.poke(II)V
sipush 19474
sipush 32641
ineg
invokestatic OS/Memory.poke(II)V
sipush 19475
bipush 31
invokestatic OS/Memory.poke(II)V
sipush 19476
sipush 17280
invokestatic OS/Memory.poke(II)V
sipush 19499
sipush 16384
ineg
invokestatic OS/Memory.poke(II)V
sipush 19500
bipush 127
invokestatic OS/Memory.poke(II)V
sipush 19501
sipush 12094
invokestatic OS/Memory.poke(II)V
sipush 19502
sipush 6385
invokestatic OS/Memory.poke(II)V
sipush 19503
bipush 28
invokestatic OS/Memory.poke(II)V
sipush 19504
sipush 15488
ineg
invokestatic OS/Memory.poke(II)V
sipush 19505
sipush 500
invokestatic OS/Memory.poke(II)V
sipush 19506
sipush 1022
invokestatic OS/Memory.poke(II)V
sipush 19507
sipush 758
invokestatic OS/Memory.poke(II)V
sipush 19508
sipush 15104
ineg
invokestatic OS/Memory.poke(II)V
sipush 19532
bipush 60
invokestatic OS/Memory.poke(II)V
sipush 19533
sipush 11902
invokestatic OS/Memory.poke(II)V
sipush 19534
sipush 6643
invokestatic OS/Memory.poke(II)V
sipush 19535
bipush 12
invokestatic OS/Memory.poke(II)V
sipush 19536
sipush 31936
invokestatic OS/Memory.poke(II)V
sipush 19537
sipush 1008
invokestatic OS/Memory.poke(II)V
sipush 19538
sipush 1754
invokestatic OS/Memory.poke(II)V
sipush 19539
sipush 3564
invokestatic OS/Memory.poke(II)V
sipush 19540
sipush 29184
ineg
invokestatic OS/Memory.poke(II)V
sipush 19565
sipush 14300
invokestatic OS/Memory.poke(II)V
sipush 19566
sipush 4070
invokestatic OS/Memory.poke(II)V
sipush 19567
iconst_4
invokestatic OS/Memory.poke(II)V
sipush 19568
sipush 1888
invokestatic OS/Memory.poke(II)V
sipush 19569
sipush 2032
invokestatic OS/Memory.poke(II)V
sipush 19570
sipush 3508
invokestatic OS/Memory.poke(II)V
sipush 19571
sipush 456
invokestatic OS/Memory.poke(II)V
sipush 19572
sipush 25600
ineg
invokestatic OS/Memory.poke(II)V
sipush 19573
iconst_1
invokestatic OS/Memory.poke(II)V
sipush 19597
bipush 28
invokestatic OS/Memory.poke(II)V
sipush 19598
sipush 2016
invokestatic OS/Memory.poke(II)V
sipush 19599
sipush 4084
invokestatic OS/Memory.poke(II)V
sipush 19600
sipush 15952
ineg
invokestatic OS/Memory.poke(II)V
sipush 19601
sipush 4048
invokestatic OS/Memory.poke(II)V
sipush 19602
sipush 7788
invokestatic OS/Memory.poke(II)V
sipush 19603
sipush 1016
invokestatic OS/Memory.poke(II)V
sipush 19604
sipush 15360
invokestatic OS/Memory.poke(II)V
sipush 19605
iconst_1
invokestatic OS/Memory.poke(II)V
sipush 19629
sipush 31748
ineg
invokestatic OS/Memory.poke(II)V
sipush 19630
sipush 15872
invokestatic OS/Memory.poke(II)V
sipush 19631
sipush 16380
invokestatic OS/Memory.poke(II)V
sipush 19632
sipush 16136
ineg
invokestatic OS/Memory.poke(II)V
sipush 19633
sipush 7632
invokestatic OS/Memory.poke(II)V
sipush 19634
sipush 15944
invokestatic OS/Memory.poke(II)V
sipush 19635
sipush 4080
invokestatic OS/Memory.poke(II)V
sipush 19636
sipush 30720
invokestatic OS/Memory.poke(II)V
sipush 19637
iconst_2
invokestatic OS/Memory.poke(II)V
sipush 19661
sipush 24580
ineg
invokestatic OS/Memory.poke(II)V
sipush 19662
sipush 16179
invokestatic OS/Memory.poke(II)V
sipush 19663
sipush 10248
ineg
invokestatic OS/Memory.poke(II)V
sipush 19664
sipush 16260
ineg
invokestatic OS/Memory.poke(II)V
sipush 19665
sipush 6928
invokestatic OS/Memory.poke(II)V
sipush 19666
sipush 30928
invokestatic OS/Memory.poke(II)V
sipush 19667
sipush 29296
invokestatic OS/Memory.poke(II)V
sipush 19668
sipush 12288
ineg
invokestatic OS/Memory.poke(II)V
sipush 19669
bipush 6
invokestatic OS/Memory.poke(II)V
sipush 19693
sipush 16388
ineg
invokestatic OS/Memory.poke(II)V
sipush 19694
sipush 11263
invokestatic OS/Memory.poke(II)V
sipush 19695
bipush 8
ineg
invokestatic OS/Memory.poke(II)V
sipush 19696
sipush 16363
ineg
invokestatic OS/Memory.poke(II)V
sipush 19697
sipush 16128
invokestatic OS/Memory.poke(II)V
sipush 19698
sipush 11808
ineg
invokestatic OS/Memory.poke(II)V
sipush 19699
sipush 6944
ineg
invokestatic OS/Memory.poke(II)V
sipush 19700
sipush 16384
sipush 16384
iadd
invokestatic OS/Memory.poke(II)V
sipush 19701
bipush 12
invokestatic OS/Memory.poke(II)V
sipush 19725
sipush 6200
invokestatic OS/Memory.poke(II)V
sipush 19726
sipush 3199
invokestatic OS/Memory.poke(II)V
sipush 19727
sipush 32624
invokestatic OS/Memory.poke(II)V
sipush 19728
sipush 8161
ineg
invokestatic OS/Memory.poke(II)V
sipush 19729
sipush 32512
invokestatic OS/Memory.poke(II)V
sipush 19730
sipush 9152
invokestatic OS/Memory.poke(II)V
sipush 19731
sipush 11713
invokestatic OS/Memory.poke(II)V
sipush 19732
sipush 8192
ineg
invokestatic OS/Memory.poke(II)V
sipush 19733
bipush 28
invokestatic OS/Memory.poke(II)V
sipush 19757
sipush 14520
invokestatic OS/Memory.poke(II)V
sipush 19758
sipush 1596
invokestatic OS/Memory.poke(II)V
sipush 19759
sipush 14096
ineg
invokestatic OS/Memory.poke(II)V
sipush 19760
sipush 24547
ineg
invokestatic OS/Memory.poke(II)V
sipush 19761
sipush 512
ineg
invokestatic OS/Memory.poke(II)V
sipush 19762
sipush 18048
invokestatic OS/Memory.poke(II)V
sipush 19763
sipush 6531
invokestatic OS/Memory.poke(II)V
sipush 19764
sipush 16384
ineg
invokestatic OS/Memory.poke(II)V
sipush 19765
bipush 49
invokestatic OS/Memory.poke(II)V
sipush 19789
sipush 3256
invokestatic OS/Memory.poke(II)V
sipush 19790
sipush 1604
invokestatic OS/Memory.poke(II)V
sipush 19791
sipush 18482
invokestatic OS/Memory.poke(II)V
sipush 19792
sipush 20355
ineg
invokestatic OS/Memory.poke(II)V
sipush 19793
sipush 4095
ineg
invokestatic OS/Memory.poke(II)V
sipush 19794
sipush 31616
ineg
invokestatic OS/Memory.poke(II)V
sipush 19795
sipush 4935
invokestatic OS/Memory.poke(II)V
sipush 19796
sipush 16380
ineg
invokestatic OS/Memory.poke(II)V
sipush 19797
bipush 35
invokestatic OS/Memory.poke(II)V
sipush 19821
sipush 10160
invokestatic OS/Memory.poke(II)V
sipush 19822
sipush 1612
invokestatic OS/Memory.poke(II)V
sipush 19823
bipush 26
invokestatic OS/Memory.poke(II)V
sipush 19824
sipush 15308
invokestatic OS/Memory.poke(II)V
sipush 19825
sipush 6143
ineg
invokestatic OS/Memory.poke(II)V
sipush 19826
sipush 31487
ineg
invokestatic OS/Memory.poke(II)V
sipush 19827
sipush 2547
ineg
invokestatic OS/Memory.poke(II)V
sipush 19828
bipush 28
invokestatic OS/Memory.poke(II)V
sipush 19829
bipush 34
invokestatic OS/Memory.poke(II)V
sipush 19853
sipush 9208
invokestatic OS/Memory.poke(II)V
sipush 19854
sipush 888
invokestatic OS/Memory.poke(II)V
sipush 19855
sipush 283
invokestatic OS/Memory.poke(II)V
sipush 19856
sipush 16008
invokestatic OS/Memory.poke(II)V
sipush 19857
sipush 6143
ineg
invokestatic OS/Memory.poke(II)V
sipush 19858
sipush 3331
invokestatic OS/Memory.poke(II)V
sipush 19859
sipush 27675
invokestatic OS/Memory.poke(II)V
sipush 19860
sipush 8240
invokestatic OS/Memory.poke(II)V
sipush 19861
bipush 70
invokestatic OS/Memory.poke(II)V
sipush 19885
sipush 8200
invokestatic OS/Memory.poke(II)V
sipush 19886
sipush 496
invokestatic OS/Memory.poke(II)V
sipush 19887
sipush 283
invokestatic OS/Memory.poke(II)V
sipush 19888
sipush 7808
invokestatic OS/Memory.poke(II)V
sipush 19889
sipush 18433
invokestatic OS/Memory.poke(II)V
sipush 19890
sipush 2563
invokestatic OS/Memory.poke(II)V
sipush 19891
sipush 10178
ineg
invokestatic OS/Memory.poke(II)V
sipush 19892
bipush 96
invokestatic OS/Memory.poke(II)V
sipush 19893
sipush 204
invokestatic OS/Memory.poke(II)V
sipush 19917
sipush 12296
invokestatic OS/Memory.poke(II)V
sipush 19918
sipush 15360
invokestatic OS/Memory.poke(II)V
sipush 19919
sipush 8167
ineg
invokestatic OS/Memory.poke(II)V
sipush 19920
sipush 3712
invokestatic OS/Memory.poke(II)V
sipush 19921
sipush 2047
ineg
invokestatic OS/Memory.poke(II)V
sipush 19922
sipush 6662
invokestatic OS/Memory.poke(II)V
sipush 19923
sipush 3972
ineg
invokestatic OS/Memory.poke(II)V
sipush 19924
sipush 481
invokestatic OS/Memory.poke(II)V
sipush 19925
sipush 412
invokestatic OS/Memory.poke(II)V
sipush 19949
bipush 8
invokestatic OS/Memory.poke(II)V
sipush 19950
sipush 1920
invokestatic OS/Memory.poke(II)V
sipush 19951
sipush 32743
ineg
invokestatic OS/Memory.poke(II)V
sipush 19952
sipush 14690
ineg
invokestatic OS/Memory.poke(II)V
sipush 19953
sipush 24575
ineg
invokestatic OS/Memory.poke(II)V
sipush 19954
sipush 5645
invokestatic OS/Memory.poke(II)V
sipush 19955
sipush 20420
ineg
invokestatic OS/Memory.poke(II)V
sipush 19956
sipush 2019
invokestatic OS/Memory.poke(II)V
sipush 19957
sipush 792
invokestatic OS/Memory.poke(II)V
sipush 19981
bipush 24
invokestatic OS/Memory.poke(II)V
sipush 19983
sipush 16425
invokestatic OS/Memory.poke(II)V
sipush 19984
sipush 27036
invokestatic OS/Memory.poke(II)V
sipush 19986
sipush 7195
invokestatic OS/Memory.poke(II)V
sipush 19987
sipush 8072
ineg
invokestatic OS/Memory.poke(II)V
sipush 19988
sipush 16359
invokestatic OS/Memory.poke(II)V
sipush 19989
sipush 1648
invokestatic OS/Memory.poke(II)V
sipush 20013
sipush 13280
ineg
invokestatic OS/Memory.poke(II)V
sipush 20014
sipush 16384
sipush 16384
iadd
invokestatic OS/Memory.poke(II)V
sipush 20015
sipush 28729
invokestatic OS/Memory.poke(II)V
sipush 20016
sipush 31104
invokestatic OS/Memory.poke(II)V
sipush 20018
sipush 14362
invokestatic OS/Memory.poke(II)V
sipush 20019
sipush 16280
ineg
invokestatic OS/Memory.poke(II)V
sipush 20020
sipush 15575
invokestatic OS/Memory.poke(II)V
sipush 20021
sipush 3552
invokestatic OS/Memory.poke(II)V
sipush 20045
sipush 19552
invokestatic OS/Memory.poke(II)V
sipush 20046
sipush 16384
ineg
invokestatic OS/Memory.poke(II)V
sipush 20047
bipush 57
invokestatic OS/Memory.poke(II)V
sipush 20048
sipush 15616
ineg
invokestatic OS/Memory.poke(II)V
sipush 20050
sipush 14396
invokestatic OS/Memory.poke(II)V
sipush 20051
sipush 32536
ineg
invokestatic OS/Memory.poke(II)V
sipush 20052
sipush 31134
invokestatic OS/Memory.poke(II)V
sipush 20053
sipush 6592
invokestatic OS/Memory.poke(II)V
sipush 20077
bipush 64
invokestatic OS/Memory.poke(II)V
sipush 20078
sipush 16272
ineg
invokestatic OS/Memory.poke(II)V
sipush 20079
bipush 113
invokestatic OS/Memory.poke(II)V
sipush 20080
sipush 13312
ineg
invokestatic OS/Memory.poke(II)V
sipush 20081
iconst_1
invokestatic OS/Memory.poke(II)V
sipush 20082
sipush 28796
invokestatic OS/Memory.poke(II)V
sipush 20083
sipush 32320
ineg
invokestatic OS/Memory.poke(II)V
sipush 20084
sipush 7399
ineg
invokestatic OS/Memory.poke(II)V
sipush 20085
sipush 5000
invokestatic OS/Memory.poke(II)V
sipush 20109
sipush 448
invokestatic OS/Memory.poke(II)V
sipush 20110
sipush 3842
ineg
invokestatic OS/Memory.poke(II)V
sipush 20111
sipush 272
invokestatic OS/Memory.poke(II)V
sipush 20113
bipush 6
invokestatic OS/Memory.poke(II)V
sipush 20114
sipush 28920
invokestatic OS/Memory.poke(II)V
sipush 20115
sipush 960
invokestatic OS/Memory.poke(II)V
sipush 20116
sipush 32229
ineg
invokestatic OS/Memory.poke(II)V
sipush 20117
sipush 13201
invokestatic OS/Memory.poke(II)V
sipush 20141
sipush 384
invokestatic OS/Memory.poke(II)V
sipush 20142
sipush 30864
invokestatic OS/Memory.poke(II)V
sipush 20143
sipush 7920
ineg
invokestatic OS/Memory.poke(II)V
sipush 20145
bipush 28
invokestatic OS/Memory.poke(II)V
sipush 20146
sipush 24752
invokestatic OS/Memory.poke(II)V
sipush 20147
sipush 640
invokestatic OS/Memory.poke(II)V
sipush 20148
sipush 534
invokestatic OS/Memory.poke(II)V
sipush 20149
sipush 8966
invokestatic OS/Memory.poke(II)V
sipush 20170
sipush 960
invokestatic OS/Memory.poke(II)V
sipush 20173
sipush 128
ineg
invokestatic OS/Memory.poke(II)V
sipush 20174
sipush 15544
invokestatic OS/Memory.poke(II)V
sipush 20175
sipush 9008
invokestatic OS/Memory.poke(II)V
sipush 20177
bipush 56
invokestatic OS/Memory.poke(II)V
sipush 20178
sipush 15968
ineg
invokestatic OS/Memory.poke(II)V
sipush 20179
sipush 1920
invokestatic OS/Memory.poke(II)V
sipush 20180
sipush 1589
invokestatic OS/Memory.poke(II)V
sipush 20181
sipush 8972
invokestatic OS/Memory.poke(II)V
sipush 20202
sipush 3168
invokestatic OS/Memory.poke(II)V
sipush 20204
sipush 768
invokestatic OS/Memory.poke(II)V
sipush 20205
sipush 11906
ineg
invokestatic OS/Memory.poke(II)V
sipush 20206
sipush 31775
invokestatic OS/Memory.poke(II)V
sipush 20207
sipush 1568
invokestatic OS/Memory.poke(II)V
sipush 20208
sipush 18432
invokestatic OS/Memory.poke(II)V
sipush 20209
bipush 112
invokestatic OS/Memory.poke(II)V
sipush 20210
sipush 15520
ineg
invokestatic OS/Memory.poke(II)V
sipush 20211
sipush 1920
invokestatic OS/Memory.poke(II)V
sipush 20212
sipush 1068
invokestatic OS/Memory.poke(II)V
sipush 20213
sipush 9752
invokestatic OS/Memory.poke(II)V
sipush 20234
sipush 6176
invokestatic OS/Memory.poke(II)V
sipush 20236
sipush 14592
ineg
invokestatic OS/Memory.poke(II)V
sipush 20237
sipush 5091
invokestatic OS/Memory.poke(II)V
sipush 20238
sipush 32265
invokestatic OS/Memory.poke(II)V
sipush 20239
sipush 3104
invokestatic OS/Memory.poke(II)V
sipush 20240
sipush 16384
invokestatic OS/Memory.poke(II)V
sipush 20241
sipush 448
invokestatic OS/Memory.poke(II)V
sipush 20242
sipush 29216
ineg
invokestatic OS/Memory.poke(II)V
sipush 20243
sipush 3585
invokestatic OS/Memory.poke(II)V
sipush 20244
sipush 3180
invokestatic OS/Memory.poke(II)V
sipush 20245
sipush 17424
invokestatic OS/Memory.poke(II)V
sipush 20266
sipush 11824
invokestatic OS/Memory.poke(II)V
sipush 20268
sipush 4352
ineg
invokestatic OS/Memory.poke(II)V
sipush 20269
sipush 8208
ineg
invokestatic OS/Memory.poke(II)V
sipush 20270
sipush 32285
invokestatic OS/Memory.poke(II)V
sipush 20271
sipush 15456
invokestatic OS/Memory.poke(II)V
sipush 20272
bipush 64
invokestatic OS/Memory.poke(II)V
sipush 20273
sipush 928
invokestatic OS/Memory.poke(II)V
sipush 20274
sipush 26113
ineg
invokestatic OS/Memory.poke(II)V
sipush 20275
sipush 3585
invokestatic OS/Memory.poke(II)V
sipush 20276
sipush 6236
invokestatic OS/Memory.poke(II)V
sipush 20277
sipush 19504
invokestatic OS/Memory.poke(II)V
sipush 20298
sipush 400
ineg
invokestatic OS/Memory.poke(II)V
sipush 20299
bipush 7
invokestatic OS/Memory.poke(II)V
sipush 20300
sipush 512
ineg
invokestatic OS/Memory.poke(II)V
sipush 20301
bipush 100
ineg
invokestatic OS/Memory.poke(II)V
sipush 20302
sipush 483
ineg
invokestatic OS/Memory.poke(II)V
sipush 20303
sipush 6272
invokestatic OS/Memory.poke(II)V
sipush 20304
sipush 1632
invokestatic OS/Memory.poke(II)V
sipush 20305
sipush 29760
ineg
invokestatic OS/Memory.poke(II)V
sipush 20306
sipush 28173
ineg
invokestatic OS/Memory.poke(II)V
sipush 20307
sipush 5123
invokestatic OS/Memory.poke(II)V
sipush 20308
sipush 6384
invokestatic OS/Memory.poke(II)V
sipush 20309
sipush 18464
invokestatic OS/Memory.poke(II)V
sipush 20330
sipush 304
ineg
invokestatic OS/Memory.poke(II)V
sipush 20331
iconst_4
invokestatic OS/Memory.poke(II)V
sipush 20332
sipush 1120
invokestatic OS/Memory.poke(II)V
sipush 20333
bipush 25
ineg
invokestatic OS/Memory.poke(II)V
sipush 20334
sipush 481
ineg
invokestatic OS/Memory.poke(II)V
sipush 20335
sipush 4224
invokestatic OS/Memory.poke(II)V
sipush 20336
sipush 3072
invokestatic OS/Memory.poke(II)V
sipush 20337
sipush 14464
ineg
invokestatic OS/Memory.poke(II)V
sipush 20338
sipush 4576
invokestatic OS/Memory.poke(II)V
sipush 20339
sipush 15363
invokestatic OS/Memory.poke(II)V
sipush 20340
sipush 12720
invokestatic OS/Memory.poke(II)V
sipush 20341
sipush 10144
ineg
invokestatic OS/Memory.poke(II)V
sipush 20362
sipush 32656
invokestatic OS/Memory.poke(II)V
sipush 20363
bipush 8
invokestatic OS/Memory.poke(II)V
sipush 20364
sipush 28736
ineg
invokestatic OS/Memory.poke(II)V
sipush 20365
sipush 16333
ineg
invokestatic OS/Memory.poke(II)V
sipush 20366
sipush 2532
ineg
invokestatic OS/Memory.poke(II)V
sipush 20367
sipush 28672
invokestatic OS/Memory.poke(II)V
sipush 20369
sipush 256
ineg
invokestatic OS/Memory.poke(II)V
sipush 20370
sipush 12737
invokestatic OS/Memory.poke(II)V
sipush 20371
sipush 10243
invokestatic OS/Memory.poke(II)V
sipush 20372
sipush 12640
invokestatic OS/Memory.poke(II)V
sipush 20373
sipush 28480
ineg
invokestatic OS/Memory.poke(II)V
sipush 20394
sipush 8080
invokestatic OS/Memory.poke(II)V
sipush 20395
bipush 24
invokestatic OS/Memory.poke(II)V
sipush 20396
sipush 7296
ineg
invokestatic OS/Memory.poke(II)V
sipush 20397
sipush 32645
ineg
invokestatic OS/Memory.poke(II)V
sipush 20398
sipush 226
ineg
invokestatic OS/Memory.poke(II)V
sipush 20399
sipush 8161
ineg
invokestatic OS/Memory.poke(II)V
sipush 20401
sipush 1024
ineg
invokestatic OS/Memory.poke(II)V
sipush 20402
sipush 8513
invokestatic OS/Memory.poke(II)V
sipush 20403
sipush 30723
invokestatic OS/Memory.poke(II)V
sipush 20404
sipush 9024
invokestatic OS/Memory.poke(II)V
sipush 20405
sipush 20096
ineg
invokestatic OS/Memory.poke(II)V
sipush 20426
sipush 8080
invokestatic OS/Memory.poke(II)V
sipush 20427
bipush 48
invokestatic OS/Memory.poke(II)V
sipush 20428
sipush 512
ineg
invokestatic OS/Memory.poke(II)V
sipush 20429
sipush 255
invokestatic OS/Memory.poke(II)V
sipush 20430
sipush 12541
ineg
invokestatic OS/Memory.poke(II)V
sipush 20431
sipush 16381
ineg
invokestatic OS/Memory.poke(II)V
sipush 20432
bipush 15
invokestatic OS/Memory.poke(II)V
sipush 20433
sipush 5120
ineg
invokestatic OS/Memory.poke(II)V
sipush 20434
sipush 8643
invokestatic OS/Memory.poke(II)V
sipush 20435
sipush 20486
invokestatic OS/Memory.poke(II)V
sipush 20436
sipush 26304
invokestatic OS/Memory.poke(II)V
sipush 20437
sipush 7936
ineg
invokestatic OS/Memory.poke(II)V
sipush 20458
sipush 5400
invokestatic OS/Memory.poke(II)V
sipush 20459
bipush 32
invokestatic OS/Memory.poke(II)V
sipush 20460
sipush 16384
sipush 16384
iadd
invokestatic OS/Memory.poke(II)V
sipush 20461
sipush 239
invokestatic OS/Memory.poke(II)V
sipush 20462
sipush 15424
ineg
invokestatic OS/Memory.poke(II)V
sipush 20463
sipush 16381
ineg
invokestatic OS/Memory.poke(II)V
sipush 20464
bipush 15
invokestatic OS/Memory.poke(II)V
sipush 20465
sipush 29696
ineg
invokestatic OS/Memory.poke(II)V
sipush 20466
sipush 24963
invokestatic OS/Memory.poke(II)V
sipush 20467
sipush 28678
invokestatic OS/Memory.poke(II)V
sipush 20468
sipush 17792
invokestatic OS/Memory.poke(II)V
sipush 20469
sipush 7424
ineg
invokestatic OS/Memory.poke(II)V
sipush 20490
sipush 27788
ineg
invokestatic OS/Memory.poke(II)V
sipush 20491
bipush 35
invokestatic OS/Memory.poke(II)V
sipush 20492
sipush 16384
sipush 16384
iadd
invokestatic OS/Memory.poke(II)V
sipush 20493
sipush 480
invokestatic OS/Memory.poke(II)V
sipush 20494
sipush 15392
ineg
invokestatic OS/Memory.poke(II)V
sipush 20495
sipush 16353
ineg
invokestatic OS/Memory.poke(II)V
sipush 20496
sipush 1023
invokestatic OS/Memory.poke(II)V
sipush 20497
sipush 2048
invokestatic OS/Memory.poke(II)V
sipush 20498
sipush 16775
invokestatic OS/Memory.poke(II)V
sipush 20499
sipush 24582
invokestatic OS/Memory.poke(II)V
sipush 20500
sipush 13056
ineg
invokestatic OS/Memory.poke(II)V
sipush 20501
sipush 15616
ineg
invokestatic OS/Memory.poke(II)V
sipush 20522
sipush 10506
ineg
invokestatic OS/Memory.poke(II)V
sipush 20523
bipush 55
invokestatic OS/Memory.poke(II)V
sipush 20524
sipush 16384
ineg
invokestatic OS/Memory.poke(II)V
sipush 20525
sipush 480
invokestatic OS/Memory.poke(II)V
sipush 20526
sipush 15376
ineg
invokestatic OS/Memory.poke(II)V
sipush 20527
sipush 32642
ineg
invokestatic OS/Memory.poke(II)V
sipush 20528
bipush 127
invokestatic OS/Memory.poke(II)V
sipush 20529
sipush 2048
invokestatic OS/Memory.poke(II)V
sipush 20530
sipush 16114
ineg
invokestatic OS/Memory.poke(II)V
sipush 20531
sipush 8180
ineg
invokestatic OS/Memory.poke(II)V
sipush 20532
sipush 29184
ineg
invokestatic OS/Memory.poke(II)V
sipush 20533
sipush 14848
ineg
invokestatic OS/Memory.poke(II)V
sipush 20554
sipush 2062
ineg
invokestatic OS/Memory.poke(II)V
sipush 20555
bipush 31
invokestatic OS/Memory.poke(II)V
sipush 20556
sipush 8192
ineg
invokestatic OS/Memory.poke(II)V
sipush 20557
sipush 6432
ineg
invokestatic OS/Memory.poke(II)V
sipush 20558
sipush 25599
invokestatic OS/Memory.poke(II)V
sipush 20559
sipush 32706
ineg
invokestatic OS/Memory.poke(II)V
sipush 20560
sipush 8127
invokestatic OS/Memory.poke(II)V
sipush 20561
sipush 2048
invokestatic OS/Memory.poke(II)V
sipush 20562
sipush 32484
ineg
invokestatic OS/Memory.poke(II)V
sipush 20563
sipush 16372
ineg
invokestatic OS/Memory.poke(II)V
sipush 20564
sipush 25088
ineg
invokestatic OS/Memory.poke(II)V
sipush 20565
sipush 12799
ineg
invokestatic OS/Memory.poke(II)V
sipush 20586
sipush 4110
ineg
invokestatic OS/Memory.poke(II)V
sipush 20587
bipush 31
invokestatic OS/Memory.poke(II)V
sipush 20588
sipush 12288
invokestatic OS/Memory.poke(II)V
sipush 20589
sipush 832
ineg
invokestatic OS/Memory.poke(II)V
sipush 20590
sipush 1887
invokestatic OS/Memory.poke(II)V
sipush 20591
bipush 118
invokestatic OS/Memory.poke(II)V
sipush 20592
iconst_2
ineg
invokestatic OS/Memory.poke(II)V
sipush 20594
sipush 32648
ineg
invokestatic OS/Memory.poke(II)V
sipush 20595
sipush 16244
ineg
invokestatic OS/Memory.poke(II)V
sipush 20596
sipush 27647
ineg
invokestatic OS/Memory.poke(II)V
sipush 20597
sipush 1023
ineg
invokestatic OS/Memory.poke(II)V
sipush 20618
sipush 6046
ineg
invokestatic OS/Memory.poke(II)V
sipush 20619
bipush 29
invokestatic OS/Memory.poke(II)V
sipush 20620
sipush 20480
invokestatic OS/Memory.poke(II)V
sipush 20621
sipush 32576
ineg
invokestatic OS/Memory.poke(II)V
sipush 20622
sipush 1523
invokestatic OS/Memory.poke(II)V
sipush 20623
sipush 4086
invokestatic OS/Memory.poke(II)V
sipush 20624
sipush 2050
ineg
invokestatic OS/Memory.poke(II)V
sipush 20625
bipush 7
invokestatic OS/Memory.poke(II)V
sipush 20626
sipush 32528
ineg
invokestatic OS/Memory.poke(II)V
sipush 20627
sipush 16116
ineg
invokestatic OS/Memory.poke(II)V
sipush 20628
sipush 17391
ineg
invokestatic OS/Memory.poke(II)V
sipush 20629
sipush 2047
ineg
invokestatic OS/Memory.poke(II)V
sipush 20650
sipush 32766
invokestatic OS/Memory.poke(II)V
sipush 20651
bipush 23
invokestatic OS/Memory.poke(II)V
sipush 20652
sipush 4096
invokestatic OS/Memory.poke(II)V
sipush 20653
sipush 480
invokestatic OS/Memory.poke(II)V
sipush 20654
bipush 30
invokestatic OS/Memory.poke(II)V
sipush 20655
sipush 500
invokestatic OS/Memory.poke(II)V
sipush 20656
sipush 8176
invokestatic OS/Memory.poke(II)V
sipush 20657
sipush 248
invokestatic OS/Memory.poke(II)V
sipush 20658
sipush 31776
ineg
invokestatic OS/Memory.poke(II)V
sipush 20659
sipush 32372
ineg
invokestatic OS/Memory.poke(II)V
sipush 20660
sipush 18381
ineg
invokestatic OS/Memory.poke(II)V
sipush 20661
sipush 4093
ineg
invokestatic OS/Memory.poke(II)V
sipush 20662
iconst_1
invokestatic OS/Memory.poke(II)V
sipush 20682
sipush 32200
invokestatic OS/Memory.poke(II)V
sipush 20683
bipush 53
invokestatic OS/Memory.poke(II)V
sipush 20684
sipush 12288
invokestatic OS/Memory.poke(II)V
sipush 20685
sipush 31776
ineg
invokestatic OS/Memory.poke(II)V
sipush 20686
bipush 31
invokestatic OS/Memory.poke(II)V
sipush 20687
sipush 996
invokestatic OS/Memory.poke(II)V
sipush 20688
bipush 32
ineg
invokestatic OS/Memory.poke(II)V
sipush 20690
sipush 31232
ineg
invokestatic OS/Memory.poke(II)V
sipush 20691
sipush 31848
ineg
invokestatic OS/Memory.poke(II)V
sipush 20692
sipush 12402
invokestatic OS/Memory.poke(II)V
sipush 20693
sipush 8189
ineg
invokestatic OS/Memory.poke(II)V
sipush 20694
iconst_1
invokestatic OS/Memory.poke(II)V
sipush 20714
sipush 2248
invokestatic OS/Memory.poke(II)V
sipush 20715
bipush 103
invokestatic OS/Memory.poke(II)V
sipush 20716
sipush 20480
invokestatic OS/Memory.poke(II)V
sipush 20717
sipush 32705
invokestatic OS/Memory.poke(II)V
sipush 20718
bipush 30
invokestatic OS/Memory.poke(II)V
sipush 20719
sipush 4018
invokestatic OS/Memory.poke(II)V
sipush 20720
sipush 256
ineg
invokestatic OS/Memory.poke(II)V
sipush 20721
bipush 7
invokestatic OS/Memory.poke(II)V
sipush 20722
sipush 29696
ineg
invokestatic OS/Memory.poke(II)V
sipush 20723
sipush 792
invokestatic OS/Memory.poke(II)V
sipush 20724
sipush 12311
invokestatic OS/Memory.poke(II)V
sipush 20725
sipush 8185
ineg
invokestatic OS/Memory.poke(II)V
sipush 20726
iconst_1
invokestatic OS/Memory.poke(II)V
sipush 20746
sipush 6088
invokestatic OS/Memory.poke(II)V
sipush 20747
sipush 198
invokestatic OS/Memory.poke(II)V
sipush 20748
sipush 20480
invokestatic OS/Memory.poke(II)V
sipush 20749
sipush 4033
invokestatic OS/Memory.poke(II)V
sipush 20751
sipush 8082
invokestatic OS/Memory.poke(II)V
sipush 20752
sipush 4096
ineg
invokestatic OS/Memory.poke(II)V
sipush 20753
sipush 12351
invokestatic OS/Memory.poke(II)V
sipush 20754
sipush 29696
ineg
invokestatic OS/Memory.poke(II)V
sipush 20755
sipush 792
invokestatic OS/Memory.poke(II)V
sipush 20756
sipush 8247
invokestatic OS/Memory.poke(II)V
sipush 20757
sipush 16378
ineg
invokestatic OS/Memory.poke(II)V
sipush 20758
iconst_3
invokestatic OS/Memory.poke(II)V
sipush 20778
sipush 32712
invokestatic OS/Memory.poke(II)V
sipush 20779
sipush 192
invokestatic OS/Memory.poke(II)V
sipush 20780
sipush 12288
ineg
invokestatic OS/Memory.poke(II)V
sipush 20781
sipush 4033
invokestatic OS/Memory.poke(II)V
sipush 20783
sipush 16256
invokestatic OS/Memory.poke(II)V
sipush 20784
sipush 4096
ineg
invokestatic OS/Memory.poke(II)V
sipush 20785
sipush 8179
invokestatic OS/Memory.poke(II)V
sipush 20786
sipush 28608
ineg
invokestatic OS/Memory.poke(II)V
sipush 20787
sipush 3864
invokestatic OS/Memory.poke(II)V
sipush 20788
sipush 24695
invokestatic OS/Memory.poke(II)V
sipush 20789
sipush 32756
ineg
invokestatic OS/Memory.poke(II)V
sipush 20790
iconst_3
invokestatic OS/Memory.poke(II)V
sipush 20810
sipush 1944
invokestatic OS/Memory.poke(II)V
sipush 20811
sipush 448
invokestatic OS/Memory.poke(II)V
sipush 20812
sipush 4096
invokestatic OS/Memory.poke(II)V
sipush 20813
sipush 32704
invokestatic OS/Memory.poke(II)V
sipush 20815
sipush 16256
invokestatic OS/Memory.poke(II)V
sipush 20816
sipush 16384
sipush 16384
iadd
invokestatic OS/Memory.poke(II)V
sipush 20817
sipush 8065
invokestatic OS/Memory.poke(II)V
sipush 20818
sipush 28512
ineg
invokestatic OS/Memory.poke(II)V
sipush 20819
sipush 3353
invokestatic OS/Memory.poke(II)V
sipush 20820
sipush 16502
invokestatic OS/Memory.poke(II)V
sipush 20821
sipush 32756
ineg
invokestatic OS/Memory.poke(II)V
sipush 20822
iconst_3
invokestatic OS/Memory.poke(II)V
sipush 20842
sipush 3856
invokestatic OS/Memory.poke(II)V
sipush 20843
sipush 384
invokestatic OS/Memory.poke(II)V
sipush 20844
sipush 4096
invokestatic OS/Memory.poke(II)V
sipush 20845
bipush 64
ineg
invokestatic OS/Memory.poke(II)V
sipush 20846
iconst_3
invokestatic OS/Memory.poke(II)V
sipush 20847
sipush 32704
invokestatic OS/Memory.poke(II)V
sipush 20848
sipush 16384
ineg
invokestatic OS/Memory.poke(II)V
sipush 20849
sipush 1923
invokestatic OS/Memory.poke(II)V
sipush 20850
sipush 4992
invokestatic OS/Memory.poke(II)V
sipush 20851
sipush 2457
invokestatic OS/Memory.poke(II)V
sipush 20852
sipush 16218
ineg
invokestatic OS/Memory.poke(II)V
sipush 20853
sipush 32744
ineg
invokestatic OS/Memory.poke(II)V
sipush 20854
iconst_3
invokestatic OS/Memory.poke(II)V
sipush 20874
sipush 4080
invokestatic OS/Memory.poke(II)V
sipush 20875
sipush 896
invokestatic OS/Memory.poke(II)V
sipush 20876
sipush 28672
ineg
invokestatic OS/Memory.poke(II)V
sipush 20877
sipush 4032
invokestatic OS/Memory.poke(II)V
sipush 20879
sipush 3136
ineg
invokestatic OS/Memory.poke(II)V
sipush 20880
sipush 4095
ineg
invokestatic OS/Memory.poke(II)V
sipush 20881
sipush 7047
invokestatic OS/Memory.poke(II)V
sipush 20882
sipush 16320
invokestatic OS/Memory.poke(II)V
sipush 20883
sipush 6297
invokestatic OS/Memory.poke(II)V
sipush 20884
sipush 32474
ineg
invokestatic OS/Memory.poke(II)V
sipush 20885
bipush 24
invokestatic OS/Memory.poke(II)V
sipush 20886
iconst_3
invokestatic OS/Memory.poke(II)V
sipush 20906
sipush 29696
ineg
invokestatic OS/Memory.poke(II)V
sipush 20907
sipush 1795
invokestatic OS/Memory.poke(II)V
sipush 20908
sipush 28672
ineg
invokestatic OS/Memory.poke(II)V
sipush 20909
sipush 1986
invokestatic OS/Memory.poke(II)V
sipush 20910
bipush 6
invokestatic OS/Memory.poke(II)V
sipush 20911
sipush 7568
ineg
invokestatic OS/Memory.poke(II)V
sipush 20912
sipush 1023
ineg
invokestatic OS/Memory.poke(II)V
sipush 20913
sipush 3855
invokestatic OS/Memory.poke(II)V
sipush 20914
sipush 17216
ineg
invokestatic OS/Memory.poke(II)V
sipush 20915
sipush 4249
invokestatic OS/Memory.poke(II)V
sipush 20916
sipush 32442
ineg
invokestatic OS/Memory.poke(II)V
sipush 20917
bipush 16
invokestatic OS/Memory.poke(II)V
sipush 20918
iconst_3
invokestatic OS/Memory.poke(II)V
sipush 20938
sipush 2048
ineg
invokestatic OS/Memory.poke(II)V
sipush 20939
sipush 3871
invokestatic OS/Memory.poke(II)V
sipush 20940
sipush 20480
ineg
invokestatic OS/Memory.poke(II)V
sipush 20941
sipush 16342
invokestatic OS/Memory.poke(II)V
sipush 20942
sipush 15362
invokestatic OS/Memory.poke(II)V
sipush 20943
sipush 16369
ineg
invokestatic OS/Memory.poke(II)V
sipush 20944
iconst_3
invokestatic OS/Memory.poke(II)V
sipush 20945
sipush 3855
invokestatic OS/Memory.poke(II)V
sipush 20946
sipush 12736
invokestatic OS/Memory.poke(II)V
sipush 20947
sipush 4315
invokestatic OS/Memory.poke(II)V
sipush 20948
sipush 32186
ineg
invokestatic OS/Memory.poke(II)V
sipush 20949
bipush 49
invokestatic OS/Memory.poke(II)V
sipush 20950
iconst_2
invokestatic OS/Memory.poke(II)V
sipush 20970
sipush 4096
ineg
invokestatic OS/Memory.poke(II)V
sipush 20971
sipush 7939
invokestatic OS/Memory.poke(II)V
sipush 20972
sipush 4096
ineg
invokestatic OS/Memory.poke(II)V
sipush 20973
bipush 35
ineg
invokestatic OS/Memory.poke(II)V
sipush 20974
sipush 2241
ineg
invokestatic OS/Memory.poke(II)V
sipush 20975
sipush 16384
ineg
invokestatic OS/Memory.poke(II)V
sipush 20976
iconst_3
invokestatic OS/Memory.poke(II)V
sipush 20977
sipush 7692
invokestatic OS/Memory.poke(II)V
sipush 20978
sipush 256
invokestatic OS/Memory.poke(II)V
sipush 20979
sipush 4187
invokestatic OS/Memory.poke(II)V
sipush 20980
sipush 1732
invokestatic OS/Memory.poke(II)V
sipush 20981
bipush 33
invokestatic OS/Memory.poke(II)V
sipush 20982
iconst_2
invokestatic OS/Memory.poke(II)V
sipush 21002
sipush 4096
ineg
invokestatic OS/Memory.poke(II)V
sipush 21003
sipush 30471
invokestatic OS/Memory.poke(II)V
sipush 21004
sipush 4096
invokestatic OS/Memory.poke(II)V
sipush 21005
sipush 128
ineg
invokestatic OS/Memory.poke(II)V
sipush 21006
sipush 8191
invokestatic OS/Memory.poke(II)V
sipush 21007
sipush 16384
ineg
invokestatic OS/Memory.poke(II)V
sipush 21008
bipush 6
invokestatic OS/Memory.poke(II)V
sipush 21009
sipush 7183
invokestatic OS/Memory.poke(II)V
sipush 21010
sipush 896
invokestatic OS/Memory.poke(II)V
sipush 21011
sipush 12377
invokestatic OS/Memory.poke(II)V
sipush 21012
sipush 3276
invokestatic OS/Memory.poke(II)V
sipush 21013
bipush 33
invokestatic OS/Memory.poke(II)V
sipush 21014
iconst_4
invokestatic OS/Memory.poke(II)V
sipush 21034
sipush 8192
ineg
invokestatic OS/Memory.poke(II)V
sipush 21035
sipush 12017
ineg
invokestatic OS/Memory.poke(II)V
sipush 21036
sipush 6147
invokestatic OS/Memory.poke(II)V
sipush 21037
sipush 7936
invokestatic OS/Memory.poke(II)V
sipush 21038
sipush 16392
invokestatic OS/Memory.poke(II)V
sipush 21040
sipush 16378
ineg
invokestatic OS/Memory.poke(II)V
sipush 21041
sipush 14351
invokestatic OS/Memory.poke(II)V
sipush 21042
sipush 1792
invokestatic OS/Memory.poke(II)V
sipush 21043
sipush 8265
invokestatic OS/Memory.poke(II)V
sipush 21044
sipush 2188
invokestatic OS/Memory.poke(II)V
sipush 21045
bipush 34
invokestatic OS/Memory.poke(II)V
sipush 21066
sipush 8192
ineg
invokestatic OS/Memory.poke(II)V
sipush 21067
sipush 24577
invokestatic OS/Memory.poke(II)V
sipush 21068
sipush 6159
invokestatic OS/Memory.poke(II)V
sipush 21069
sipush 32640
invokestatic OS/Memory.poke(II)V
sipush 21070
sipush 460
invokestatic OS/Memory.poke(II)V
sipush 21072
sipush 16369
ineg
invokestatic OS/Memory.poke(II)V
sipush 21073
sipush 4081
ineg
invokestatic OS/Memory.poke(II)V
sipush 21074
sipush 1024
invokestatic OS/Memory.poke(II)V
sipush 21075
sipush 8265
invokestatic OS/Memory.poke(II)V
sipush 21076
sipush 6284
invokestatic OS/Memory.poke(II)V
sipush 21077
bipush 66
invokestatic OS/Memory.poke(II)V
sipush 21098
sipush 16384
sipush 16384
iadd
invokestatic OS/Memory.poke(II)V
sipush 21099
sipush 24577
invokestatic OS/Memory.poke(II)V
sipush 21100
sipush 6171
invokestatic OS/Memory.poke(II)V
sipush 21101
sipush 128
ineg
invokestatic OS/Memory.poke(II)V
sipush 21102
bipush 8
invokestatic OS/Memory.poke(II)V
sipush 21104
bipush 62
invokestatic OS/Memory.poke(II)V
sipush 21105
sipush 8181
ineg
invokestatic OS/Memory.poke(II)V
sipush 21106
sipush 1024
invokestatic OS/Memory.poke(II)V
sipush 21107
sipush 24653
invokestatic OS/Memory.poke(II)V
sipush 21108
sipush 12428
invokestatic OS/Memory.poke(II)V
sipush 21109
bipush 70
invokestatic OS/Memory.poke(II)V
sipush 21131
sipush 32765
ineg
invokestatic OS/Memory.poke(II)V
sipush 21132
sipush 31934
invokestatic OS/Memory.poke(II)V
sipush 21133
sipush 128
ineg
invokestatic OS/Memory.poke(II)V
sipush 21134
sipush 1033
invokestatic OS/Memory.poke(II)V
sipush 21136
bipush 126
invokestatic OS/Memory.poke(II)V
sipush 21137
sipush 16372
ineg
invokestatic OS/Memory.poke(II)V
sipush 21138
sipush 3073
invokestatic OS/Memory.poke(II)V
sipush 21139
sipush 16431
invokestatic OS/Memory.poke(II)V
sipush 21140
sipush 8588
invokestatic OS/Memory.poke(II)V
sipush 21141
bipush 68
invokestatic OS/Memory.poke(II)V
sipush 21163
sipush 32754
ineg
invokestatic OS/Memory.poke(II)V
sipush 21164
sipush 24172
invokestatic OS/Memory.poke(II)V
sipush 21165
sipush 128
ineg
invokestatic OS/Memory.poke(II)V
sipush 21166
sipush 1151
invokestatic OS/Memory.poke(II)V
sipush 21168
sipush 254
invokestatic OS/Memory.poke(II)V
sipush 21169
sipush 32753
ineg
invokestatic OS/Memory.poke(II)V
sipush 21170
sipush 2048
invokestatic OS/Memory.poke(II)V
sipush 21171
sipush 16425
invokestatic OS/Memory.poke(II)V
sipush 21172
sipush 24844
invokestatic OS/Memory.poke(II)V
sipush 21173
bipush 76
invokestatic OS/Memory.poke(II)V
sipush 21195
sipush 32708
ineg
invokestatic OS/Memory.poke(II)V
sipush 21196
sipush 32760
invokestatic OS/Memory.poke(II)V
sipush 21197
sipush 32512
invokestatic OS/Memory.poke(II)V
sipush 21198
sipush 1136
invokestatic OS/Memory.poke(II)V
sipush 21200
sipush 170
invokestatic OS/Memory.poke(II)V
sipush 21201
bipush 15
invokestatic OS/Memory.poke(II)V
sipush 21202
sipush 2049
invokestatic OS/Memory.poke(II)V
sipush 21203
sipush 16429
invokestatic OS/Memory.poke(II)V
sipush 21204
sipush 16652
invokestatic OS/Memory.poke(II)V
sipush 21205
bipush 72
invokestatic OS/Memory.poke(II)V
sipush 21227
bipush 24
invokestatic OS/Memory.poke(II)V
sipush 21228
sipush 16296
invokestatic OS/Memory.poke(II)V
sipush 21229
sipush 7680
invokestatic OS/Memory.poke(II)V
sipush 21230
bipush 15
invokestatic OS/Memory.poke(II)V
sipush 21231
sipush 16384
sipush 16384
iadd
invokestatic OS/Memory.poke(II)V
sipush 21232
sipush 437
invokestatic OS/Memory.poke(II)V
sipush 21233
bipush 8
invokestatic OS/Memory.poke(II)V
sipush 21234
sipush 2051
invokestatic OS/Memory.poke(II)V
sipush 21235
sipush 16323
ineg
invokestatic OS/Memory.poke(II)V
sipush 21236
sipush 32504
ineg
invokestatic OS/Memory.poke(II)V
sipush 21237
sipush 136
invokestatic OS/Memory.poke(II)V
sipush 21259
bipush 112
invokestatic OS/Memory.poke(II)V
sipush 21260
sipush 16168
invokestatic OS/Memory.poke(II)V
sipush 21261
sipush 512
ineg
invokestatic OS/Memory.poke(II)V
sipush 21262
iconst_3
invokestatic OS/Memory.poke(II)V
sipush 21263
sipush 16384
sipush 16384
iadd
invokestatic OS/Memory.poke(II)V
sipush 21264
sipush 304
invokestatic OS/Memory.poke(II)V
sipush 21265
bipush 8
invokestatic OS/Memory.poke(II)V
sipush 21266
sipush 2050
invokestatic OS/Memory.poke(II)V
sipush 21267
sipush 32715
ineg
invokestatic OS/Memory.poke(II)V
sipush 21268
sipush 32504
ineg
invokestatic OS/Memory.poke(II)V
sipush 21269
sipush 153
invokestatic OS/Memory.poke(II)V
sipush 21291
sipush 192
invokestatic OS/Memory.poke(II)V
sipush 21292
sipush 3872
invokestatic OS/Memory.poke(II)V
sipush 21293
sipush 3584
invokestatic OS/Memory.poke(II)V
sipush 21294
bipush 60
invokestatic OS/Memory.poke(II)V
sipush 21295
sipush 24704
invokestatic OS/Memory.poke(II)V
sipush 21296
sipush 768
invokestatic OS/Memory.poke(II)V
sipush 21297
bipush 12
invokestatic OS/Memory.poke(II)V
sipush 21298
sipush 2054
invokestatic OS/Memory.poke(II)V
sipush 21299
sipush 32713
ineg
invokestatic OS/Memory.poke(II)V
sipush 21300
sipush 264
invokestatic OS/Memory.poke(II)V
sipush 21301
sipush 145
invokestatic OS/Memory.poke(II)V
sipush 21323
sipush 128
invokestatic OS/Memory.poke(II)V
sipush 21324
sipush 29152
ineg
invokestatic OS/Memory.poke(II)V
sipush 21325
sipush 512
ineg
invokestatic OS/Memory.poke(II)V
sipush 21326
sipush 1025
invokestatic OS/Memory.poke(II)V
sipush 21327
sipush 12288
invokestatic OS/Memory.poke(II)V
sipush 21328
sipush 768
invokestatic OS/Memory.poke(II)V
sipush 21329
bipush 62
invokestatic OS/Memory.poke(II)V
sipush 21330
sipush 2054
invokestatic OS/Memory.poke(II)V
sipush 21331
sipush 32713
ineg
invokestatic OS/Memory.poke(II)V
sipush 21332
sipush 264
invokestatic OS/Memory.poke(II)V
sipush 21333
sipush 179
invokestatic OS/Memory.poke(II)V
sipush 21355
sipush 384
invokestatic OS/Memory.poke(II)V
sipush 21356
sipush 29696
ineg
invokestatic OS/Memory.poke(II)V
sipush 21357
sipush 506
ineg
invokestatic OS/Memory.poke(II)V
sipush 21358
sipush 1565
invokestatic OS/Memory.poke(II)V
sipush 21359
sipush 6144
invokestatic OS/Memory.poke(II)V
sipush 21360
sipush 896
invokestatic OS/Memory.poke(II)V
sipush 21361
sipush 252
invokestatic OS/Memory.poke(II)V
sipush 21362
sipush 2054
invokestatic OS/Memory.poke(II)V
sipush 21363
sipush 32713
ineg
invokestatic OS/Memory.poke(II)V
sipush 21364
sipush 264
invokestatic OS/Memory.poke(II)V
sipush 21365
sipush 162
invokestatic OS/Memory.poke(II)V
sipush 21387
sipush 768
invokestatic OS/Memory.poke(II)V
sipush 21388
sipush 29696
ineg
invokestatic OS/Memory.poke(II)V
sipush 21389
sipush 4605
ineg
invokestatic OS/Memory.poke(II)V
sipush 21390
sipush 769
invokestatic OS/Memory.poke(II)V
sipush 21391
sipush 1056
invokestatic OS/Memory.poke(II)V
sipush 21392
sipush 1920
invokestatic OS/Memory.poke(II)V
sipush 21393
sipush 2044
invokestatic OS/Memory.poke(II)V
sipush 21394
sipush 30714
ineg
invokestatic OS/Memory.poke(II)V
sipush 21395
sipush 32737
ineg
invokestatic OS/Memory.poke(II)V
sipush 21396
sipush 264
invokestatic OS/Memory.poke(II)V
sipush 21397
sipush 164
invokestatic OS/Memory.poke(II)V
sipush 21419
sipush 768
invokestatic OS/Memory.poke(II)V
sipush 21420
sipush 2048
invokestatic OS/Memory.poke(II)V
sipush 21421
sipush 256
ineg
invokestatic OS/Memory.poke(II)V
sipush 21422
sipush 32521
ineg
invokestatic OS/Memory.poke(II)V
sipush 21423
sipush 768
invokestatic OS/Memory.poke(II)V
sipush 21424
sipush 1920
invokestatic OS/Memory.poke(II)V
sipush 21425
sipush 28668
invokestatic OS/Memory.poke(II)V
sipush 21426
sipush 30714
ineg
invokestatic OS/Memory.poke(II)V
sipush 21427
sipush 32737
ineg
invokestatic OS/Memory.poke(II)V
sipush 21428
sipush 520
invokestatic OS/Memory.poke(II)V
sipush 21429
sipush 484
invokestatic OS/Memory.poke(II)V
sipush 21451
sipush 1536
invokestatic OS/Memory.poke(II)V
sipush 21452
sipush 2048
invokestatic OS/Memory.poke(II)V
sipush 21453
bipush 124
ineg
invokestatic OS/Memory.poke(II)V
sipush 21454
sipush 26879
invokestatic OS/Memory.poke(II)V
sipush 21455
sipush 192
invokestatic OS/Memory.poke(II)V
sipush 21456
sipush 3072
invokestatic OS/Memory.poke(II)V
sipush 21457
bipush 36
ineg
invokestatic OS/Memory.poke(II)V
sipush 21458
sipush 30714
ineg
invokestatic OS/Memory.poke(II)V
sipush 21459
sipush 32737
ineg
invokestatic OS/Memory.poke(II)V
sipush 21460
sipush 793
invokestatic OS/Memory.poke(II)V
sipush 21461
sipush 328
invokestatic OS/Memory.poke(II)V
sipush 21483
sipush 1536
invokestatic OS/Memory.poke(II)V
sipush 21485
sipush 8070
invokestatic OS/Memory.poke(II)V
sipush 21486
bipush 31
invokestatic OS/Memory.poke(II)V
sipush 21487
bipush 51
invokestatic OS/Memory.poke(II)V
sipush 21488
sipush 7168
invokestatic OS/Memory.poke(II)V
sipush 21489
sipush 28788
ineg
invokestatic OS/Memory.poke(II)V
sipush 21490
sipush 30713
ineg
invokestatic OS/Memory.poke(II)V
sipush 21491
bipush 15
invokestatic OS/Memory.poke(II)V
sipush 21492
sipush 793
invokestatic OS/Memory.poke(II)V
sipush 21493
sipush 328
invokestatic OS/Memory.poke(II)V
sipush 21515
sipush 1024
invokestatic OS/Memory.poke(II)V
sipush 21517
bipush 106
ineg
invokestatic OS/Memory.poke(II)V
sipush 21518
sipush 2017
ineg
invokestatic OS/Memory.poke(II)V
sipush 21519
bipush 31
invokestatic OS/Memory.poke(II)V
sipush 21520
sipush 7168
invokestatic OS/Memory.poke(II)V
sipush 21521
sipush 236
invokestatic OS/Memory.poke(II)V
sipush 21522
sipush 29690
ineg
invokestatic OS/Memory.poke(II)V
sipush 21523
bipush 15
invokestatic OS/Memory.poke(II)V
sipush 21524
sipush 793
invokestatic OS/Memory.poke(II)V
sipush 21525
sipush 392
invokestatic OS/Memory.poke(II)V
sipush 21547
sipush 3072
invokestatic OS/Memory.poke(II)V
sipush 21549
sipush 22640
ineg
invokestatic OS/Memory.poke(II)V
sipush 21550
sipush 2289
ineg
invokestatic OS/Memory.poke(II)V
sipush 21551
iconst_3
invokestatic OS/Memory.poke(II)V
sipush 21552
sipush 15360
invokestatic OS/Memory.poke(II)V
sipush 21553
bipush 52
invokestatic OS/Memory.poke(II)V
sipush 21554
sipush 29684
ineg
invokestatic OS/Memory.poke(II)V
sipush 21555
bipush 7
invokestatic OS/Memory.poke(II)V
sipush 21556
sipush 537
invokestatic OS/Memory.poke(II)V
sipush 21557
sipush 400
invokestatic OS/Memory.poke(II)V
sipush 21579
sipush 2048
invokestatic OS/Memory.poke(II)V
sipush 21581
sipush 7232
ineg
invokestatic OS/Memory.poke(II)V
sipush 21582
sipush 32759
invokestatic OS/Memory.poke(II)V
sipush 21584
sipush 14336
invokestatic OS/Memory.poke(II)V
sipush 21585
sipush 4048
invokestatic OS/Memory.poke(II)V
sipush 21586
sipush 31744
ineg
invokestatic OS/Memory.poke(II)V
sipush 21587
iconst_3
invokestatic OS/Memory.poke(II)V
sipush 21588
sipush 537
invokestatic OS/Memory.poke(II)V
sipush 21589
sipush 912
invokestatic OS/Memory.poke(II)V
sipush 21611
sipush 6144
invokestatic OS/Memory.poke(II)V
sipush 21613
sipush 15424
ineg
invokestatic OS/Memory.poke(II)V
sipush 21614
sipush 8191
invokestatic OS/Memory.poke(II)V
sipush 21616
sipush 15360
invokestatic OS/Memory.poke(II)V
sipush 21617
sipush 12144
invokestatic OS/Memory.poke(II)V
sipush 21618
sipush 31232
ineg
invokestatic OS/Memory.poke(II)V
sipush 21619
iconst_3
invokestatic OS/Memory.poke(II)V
sipush 21620
sipush 538
invokestatic OS/Memory.poke(II)V
sipush 21621
sipush 816
invokestatic OS/Memory.poke(II)V
sipush 21643
sipush 12288
invokestatic OS/Memory.poke(II)V
sipush 21645
sipush 15904
ineg
invokestatic OS/Memory.poke(II)V
sipush 21646
sipush 1039
invokestatic OS/Memory.poke(II)V
sipush 21648
sipush 15872
invokestatic OS/Memory.poke(II)V
sipush 21649
sipush 32752
invokestatic OS/Memory.poke(II)V
sipush 21650
sipush 15616
ineg
invokestatic OS/Memory.poke(II)V
sipush 21651
iconst_1
invokestatic OS/Memory.poke(II)V
sipush 21652
sipush 538
invokestatic OS/Memory.poke(II)V
sipush 21653
sipush 800
invokestatic OS/Memory.poke(II)V
sipush 21675
sipush 28672
invokestatic OS/Memory.poke(II)V
sipush 21677
sipush 32288
ineg
invokestatic OS/Memory.poke(II)V
sipush 21678
sipush 1551
invokestatic OS/Memory.poke(II)V
sipush 21680
sipush 11776
invokestatic OS/Memory.poke(II)V
sipush 21681
sipush 128
ineg
invokestatic OS/Memory.poke(II)V
sipush 21682
sipush 16000
ineg
invokestatic OS/Memory.poke(II)V
sipush 21684
sipush 794
invokestatic OS/Memory.poke(II)V
sipush 21685
sipush 864
invokestatic OS/Memory.poke(II)V
sipush 21707
sipush 16384
ineg
invokestatic OS/Memory.poke(II)V
sipush 21708
iconst_1
invokestatic OS/Memory.poke(II)V
sipush 21709
sipush 224
invokestatic OS/Memory.poke(II)V
sipush 21710
sipush 7167
invokestatic OS/Memory.poke(II)V
sipush 21712
sipush 10112
invokestatic OS/Memory.poke(II)V
sipush 21713
sipush 16352
invokestatic OS/Memory.poke(II)V
sipush 21714
sipush 16528
invokestatic OS/Memory.poke(II)V
sipush 21716
sipush 274
invokestatic OS/Memory.poke(II)V
sipush 21717
sipush 832
invokestatic OS/Memory.poke(II)V
sipush 21739
sipush 16384
sipush 16384
iadd
invokestatic OS/Memory.poke(II)V
sipush 21740
bipush 7
invokestatic OS/Memory.poke(II)V
sipush 21741
sipush 240
invokestatic OS/Memory.poke(II)V
sipush 21742
sipush 4578
ineg
invokestatic OS/Memory.poke(II)V
sipush 21744
sipush 8704
invokestatic OS/Memory.poke(II)V
sipush 21745
sipush 8224
ineg
invokestatic OS/Memory.poke(II)V
sipush 21746
bipush 112
invokestatic OS/Memory.poke(II)V
sipush 21748
sipush 274
invokestatic OS/Memory.poke(II)V
sipush 21749
sipush 1600
invokestatic OS/Memory.poke(II)V
sipush 21771
sipush 16384
ineg
invokestatic OS/Memory.poke(II)V
sipush 21772
iconst_3
invokestatic OS/Memory.poke(II)V
sipush 21773
bipush 112
invokestatic OS/Memory.poke(II)V
sipush 21774
sipush 3076
ineg
invokestatic OS/Memory.poke(II)V
sipush 21775
iconst_3
invokestatic OS/Memory.poke(II)V
sipush 21776
sipush 12688
invokestatic OS/Memory.poke(II)V
sipush 21777
sipush 24160
invokestatic OS/Memory.poke(II)V
sipush 21778
bipush 112
invokestatic OS/Memory.poke(II)V
sipush 21780
sipush 406
invokestatic OS/Memory.poke(II)V
sipush 21781
sipush 1728
invokestatic OS/Memory.poke(II)V
sipush 21803
sipush 16384
ineg
invokestatic OS/Memory.poke(II)V
sipush 21804
bipush 15
invokestatic OS/Memory.poke(II)V
sipush 21805
bipush 60
invokestatic OS/Memory.poke(II)V
sipush 21806
sipush 16392
ineg
invokestatic OS/Memory.poke(II)V
sipush 21807
bipush 24
invokestatic OS/Memory.poke(II)V
sipush 21808
sipush 6348
invokestatic OS/Memory.poke(II)V
sipush 21809
sipush 24256
invokestatic OS/Memory.poke(II)V
sipush 21810
bipush 48
invokestatic OS/Memory.poke(II)V
sipush 21812
sipush 404
invokestatic OS/Memory.poke(II)V
sipush 21813
sipush 1920
invokestatic OS/Memory.poke(II)V
sipush 21835
sipush 16384
sipush 16384
iadd
invokestatic OS/Memory.poke(II)V
sipush 21836
sipush 4095
invokestatic OS/Memory.poke(II)V
sipush 21837
bipush 28
invokestatic OS/Memory.poke(II)V
sipush 21838
bipush 16
ineg
invokestatic OS/Memory.poke(II)V
sipush 21839
iconst_5
invokestatic OS/Memory.poke(II)V
sipush 21840
sipush 3168
invokestatic OS/Memory.poke(II)V
sipush 21841
sipush 29056
invokestatic OS/Memory.poke(II)V
sipush 21842
bipush 33
invokestatic OS/Memory.poke(II)V
sipush 21844
sipush 404
invokestatic OS/Memory.poke(II)V
sipush 21845
sipush 1920
invokestatic OS/Memory.poke(II)V
sipush 21867
sipush 16384
sipush 16384
iadd
invokestatic OS/Memory.poke(II)V
sipush 21868
sipush 8191
invokestatic OS/Memory.poke(II)V
sipush 21869
bipush 15
invokestatic OS/Memory.poke(II)V
sipush 21870
sipush 1056
ineg
invokestatic OS/Memory.poke(II)V
sipush 21871
sipush 499
invokestatic OS/Memory.poke(II)V
sipush 21872
sipush 13336
invokestatic OS/Memory.poke(II)V
sipush 21873
bipush 8
ineg
invokestatic OS/Memory.poke(II)V
sipush 21874
bipush 15
ineg
invokestatic OS/Memory.poke(II)V
sipush 21876
sipush 404
invokestatic OS/Memory.poke(II)V
sipush 21877
sipush 1792
invokestatic OS/Memory.poke(II)V
sipush 21900
sipush 15287
invokestatic OS/Memory.poke(II)V
sipush 21901
iconst_1
invokestatic OS/Memory.poke(II)V
sipush 21902
sipush 384
ineg
invokestatic OS/Memory.poke(II)V
sipush 21903
sipush 32760
invokestatic OS/Memory.poke(II)V
sipush 21904
sipush 5127
invokestatic OS/Memory.poke(II)V
sipush 21905
sipush 16464
ineg
invokestatic OS/Memory.poke(II)V
sipush 21906
bipush 32
ineg
invokestatic OS/Memory.poke(II)V
sipush 21907
iconst_3
invokestatic OS/Memory.poke(II)V
sipush 21908
sipush 404
invokestatic OS/Memory.poke(II)V
sipush 21909
sipush 1792
invokestatic OS/Memory.poke(II)V
sipush 21932
sipush 22654
ineg
invokestatic OS/Memory.poke(II)V
sipush 21934
sipush 512
ineg
invokestatic OS/Memory.poke(II)V
sipush 21935
iconst_1
ineg
invokestatic OS/Memory.poke(II)V
sipush 21936
sipush 1536
invokestatic OS/Memory.poke(II)V
sipush 21937
sipush 28576
ineg
invokestatic OS/Memory.poke(II)V
sipush 21938
sipush 15852
invokestatic OS/Memory.poke(II)V
sipush 21939
bipush 7
invokestatic OS/Memory.poke(II)V
sipush 21940
sipush 412
invokestatic OS/Memory.poke(II)V
sipush 21941
sipush 3840
invokestatic OS/Memory.poke(II)V
sipush 21964
sipush 7412
ineg
invokestatic OS/Memory.poke(II)V
sipush 21966
sipush 2048
ineg
invokestatic OS/Memory.poke(II)V
sipush 21967
sipush 2047
invokestatic OS/Memory.poke(II)V
sipush 21968
sipush 512
invokestatic OS/Memory.poke(II)V
sipush 21969
sipush 32704
invokestatic OS/Memory.poke(II)V
sipush 21970
sipush 28662
invokestatic OS/Memory.poke(II)V
sipush 21971
bipush 15
invokestatic OS/Memory.poke(II)V
sipush 21972
sipush 216
invokestatic OS/Memory.poke(II)V
sipush 21973
sipush 3840
invokestatic OS/Memory.poke(II)V
sipush 21996
sipush 1560
invokestatic OS/Memory.poke(II)V
sipush 21998
sipush 8192
ineg
invokestatic OS/Memory.poke(II)V
sipush 21999
iconst_1
invokestatic OS/Memory.poke(II)V
sipush 22000
sipush 512
invokestatic OS/Memory.poke(II)V
sipush 22001
sipush 2048
invokestatic OS/Memory.poke(II)V
sipush 22002
sipush 19251
invokestatic OS/Memory.poke(II)V
sipush 22003
bipush 12
invokestatic OS/Memory.poke(II)V
sipush 22004
sipush 248
invokestatic OS/Memory.poke(II)V
sipush 22005
sipush 3584
invokestatic OS/Memory.poke(II)V
sipush 22028
sipush 3184
invokestatic OS/Memory.poke(II)V
sipush 22030
sipush 16384
sipush 16384
iadd
invokestatic OS/Memory.poke(II)V
sipush 22031
bipush 31
invokestatic OS/Memory.poke(II)V
sipush 22032
sipush 768
invokestatic OS/Memory.poke(II)V
sipush 22033
sipush 29184
ineg
invokestatic OS/Memory.poke(II)V
sipush 22034
sipush 20025
invokestatic OS/Memory.poke(II)V
sipush 22035
bipush 60
invokestatic OS/Memory.poke(II)V
sipush 22036
bipush 120
invokestatic OS/Memory.poke(II)V
sipush 22037
sipush 3072
invokestatic OS/Memory.poke(II)V
sipush 22060
sipush 3008
invokestatic OS/Memory.poke(II)V
sipush 22063
sipush 254
invokestatic OS/Memory.poke(II)V
sipush 22064
sipush 384
invokestatic OS/Memory.poke(II)V
sipush 22065
sipush 7424
ineg
invokestatic OS/Memory.poke(II)V
sipush 22066
sipush 30657
ineg
invokestatic OS/Memory.poke(II)V
sipush 22067
bipush 60
invokestatic OS/Memory.poke(II)V
sipush 22068
bipush 120
invokestatic OS/Memory.poke(II)V
sipush 22069
sipush 3072
invokestatic OS/Memory.poke(II)V
sipush 22092
sipush 7680
invokestatic OS/Memory.poke(II)V
sipush 22095
sipush 8048
invokestatic OS/Memory.poke(II)V
sipush 22096
sipush 192
invokestatic OS/Memory.poke(II)V
sipush 22097
bipush 64
ineg
invokestatic OS/Memory.poke(II)V
sipush 22098
sipush 32705
ineg
invokestatic OS/Memory.poke(II)V
sipush 22099
bipush 60
invokestatic OS/Memory.poke(II)V
sipush 22100
bipush 120
invokestatic OS/Memory.poke(II)V
sipush 22101
sipush 3072
invokestatic OS/Memory.poke(II)V
sipush 22124
sipush 31744
invokestatic OS/Memory.poke(II)V
sipush 22127
sipush 4032
invokestatic OS/Memory.poke(II)V
sipush 22128
sipush 254
invokestatic OS/Memory.poke(II)V
sipush 22129
sipush 4096
ineg
invokestatic OS/Memory.poke(II)V
sipush 22130
bipush 63
invokestatic OS/Memory.poke(II)V
sipush 22131
bipush 62
invokestatic OS/Memory.poke(II)V
sipush 22132
bipush 120
invokestatic OS/Memory.poke(II)V
sipush 22133
sipush 2048
invokestatic OS/Memory.poke(II)V
sipush 22156
sipush 2048
ineg
invokestatic OS/Memory.poke(II)V
sipush 22159
sipush 3648
ineg
invokestatic OS/Memory.poke(II)V
sipush 22160
sipush 3711
invokestatic OS/Memory.poke(II)V
sipush 22161
bipush 64
ineg
invokestatic OS/Memory.poke(II)V
sipush 22162
bipush 6
invokestatic OS/Memory.poke(II)V
sipush 22163
bipush 91
invokestatic OS/Memory.poke(II)V
sipush 22164
bipush 48
invokestatic OS/Memory.poke(II)V
sipush 22165
sipush 2048
invokestatic OS/Memory.poke(II)V
sipush 22188
sipush 16384
sipush 16384
iadd
invokestatic OS/Memory.poke(II)V
sipush 22189
iconst_1
invokestatic OS/Memory.poke(II)V
sipush 22191
sipush 384
invokestatic OS/Memory.poke(II)V
sipush 22192
sipush 510
invokestatic OS/Memory.poke(II)V
sipush 22193
sipush 32256
invokestatic OS/Memory.poke(II)V
sipush 22195
bipush 121
invokestatic OS/Memory.poke(II)V
sipush 22196
bipush 56
invokestatic OS/Memory.poke(II)V
sipush 22197
sipush 2048
invokestatic OS/Memory.poke(II)V
sipush 22221
iconst_1
invokestatic OS/Memory.poke(II)V
sipush 22223
sipush 960
invokestatic OS/Memory.poke(II)V
sipush 22224
sipush 252
invokestatic OS/Memory.poke(II)V
sipush 22225
sipush 31104
invokestatic OS/Memory.poke(II)V
sipush 22227
sipush 492
invokestatic OS/Memory.poke(II)V
sipush 22228
bipush 56
invokestatic OS/Memory.poke(II)V
sipush 22255
sipush 2044
invokestatic OS/Memory.poke(II)V
sipush 22256
sipush 252
invokestatic OS/Memory.poke(II)V
sipush 22257
sipush 30720
invokestatic OS/Memory.poke(II)V
sipush 22259
sipush 428
invokestatic OS/Memory.poke(II)V
sipush 22260
bipush 56
invokestatic OS/Memory.poke(II)V
sipush 22287
sipush 2047
invokestatic OS/Memory.poke(II)V
sipush 22288
sipush 1758
invokestatic OS/Memory.poke(II)V
sipush 22289
sipush 15872
invokestatic OS/Memory.poke(II)V
sipush 22291
sipush 228
invokestatic OS/Memory.poke(II)V
sipush 22292
bipush 56
invokestatic OS/Memory.poke(II)V
sipush 22318
sipush 8192
ineg
invokestatic OS/Memory.poke(II)V
sipush 22319
sipush 24577
ineg
invokestatic OS/Memory.poke(II)V
sipush 22320
sipush 479
invokestatic OS/Memory.poke(II)V
sipush 22321
sipush 1024
ineg
invokestatic OS/Memory.poke(II)V
sipush 22322
sipush 1023
invokestatic OS/Memory.poke(II)V
sipush 22323
sipush 192
invokestatic OS/Memory.poke(II)V
sipush 22324
bipush 48
invokestatic OS/Memory.poke(II)V
sipush 22325
bipush 6
invokestatic OS/Memory.poke(II)V
sipush 22350
sipush 14336
invokestatic OS/Memory.poke(II)V
sipush 22351
sipush 16456
ineg
invokestatic OS/Memory.poke(II)V
sipush 22352
bipush 63
invokestatic OS/Memory.poke(II)V
sipush 22353
sipush 3584
invokestatic OS/Memory.poke(II)V
sipush 22354
sipush 896
invokestatic OS/Memory.poke(II)V
sipush 22355
sipush 224
invokestatic OS/Memory.poke(II)V
sipush 22356
bipush 16
invokestatic OS/Memory.poke(II)V
sipush 22357
bipush 60
invokestatic OS/Memory.poke(II)V
sipush 22382
sipush 24832
ineg
invokestatic OS/Memory.poke(II)V
sipush 22383
sipush 393
ineg
invokestatic OS/Memory.poke(II)V
sipush 22384
bipush 127
invokestatic OS/Memory.poke(II)V
sipush 22385
sipush 1792
invokestatic OS/Memory.poke(II)V
sipush 22386
sipush 3584
invokestatic OS/Memory.poke(II)V
sipush 22387
sipush 128
invokestatic OS/Memory.poke(II)V
sipush 22388
bipush 16
invokestatic OS/Memory.poke(II)V
sipush 22389
sipush 1020
invokestatic OS/Memory.poke(II)V
sipush 22414
sipush 32192
invokestatic OS/Memory.poke(II)V
sipush 22415
sipush 232
ineg
invokestatic OS/Memory.poke(II)V
sipush 22416
sipush 32673
ineg
invokestatic OS/Memory.poke(II)V
sipush 22417
sipush 1792
invokestatic OS/Memory.poke(II)V
sipush 22418
sipush 31744
invokestatic OS/Memory.poke(II)V
sipush 22419
sipush 128
invokestatic OS/Memory.poke(II)V
sipush 22420
bipush 16
invokestatic OS/Memory.poke(II)V
sipush 22421
sipush 32304
invokestatic OS/Memory.poke(II)V
sipush 22446
sipush 3952
invokestatic OS/Memory.poke(II)V
sipush 22447
bipush 50
ineg
invokestatic OS/Memory.poke(II)V
sipush 22448
sipush 32641
ineg
invokestatic OS/Memory.poke(II)V
sipush 22449
sipush 1536
invokestatic OS/Memory.poke(II)V
sipush 22450
sipush 14336
invokestatic OS/Memory.poke(II)V
sipush 22451
sipush 224
invokestatic OS/Memory.poke(II)V
sipush 22452
sipush 1024
ineg
invokestatic OS/Memory.poke(II)V
sipush 22453
sipush 29823
invokestatic OS/Memory.poke(II)V
sipush 22478
sipush 32290
ineg
invokestatic OS/Memory.poke(II)V
sipush 22479
sipush 697
ineg
invokestatic OS/Memory.poke(II)V
sipush 22480
sipush 28433
ineg
invokestatic OS/Memory.poke(II)V
sipush 22481
sipush 1920
invokestatic OS/Memory.poke(II)V
sipush 22482
sipush 4096
ineg
invokestatic OS/Memory.poke(II)V
sipush 22483
sipush 448
invokestatic OS/Memory.poke(II)V
sipush 22484
sipush 768
invokestatic OS/Memory.poke(II)V
sipush 22485
sipush 8184
ineg
invokestatic OS/Memory.poke(II)V
sipush 22510
bipush 14
invokestatic OS/Memory.poke(II)V
sipush 22511
sipush 7584
ineg
invokestatic OS/Memory.poke(II)V
sipush 22512
sipush 28545
ineg
invokestatic OS/Memory.poke(II)V
sipush 22513
sipush 896
invokestatic OS/Memory.poke(II)V
sipush 22514
sipush 28672
invokestatic OS/Memory.poke(II)V
sipush 22515
sipush 385
invokestatic OS/Memory.poke(II)V
sipush 22516
sipush 384
invokestatic OS/Memory.poke(II)V
sipush 22517
sipush 12288
invokestatic OS/Memory.poke(II)V
sipush 22542
bipush 7
invokestatic OS/Memory.poke(II)V
sipush 22543
sipush 3616
ineg
invokestatic OS/Memory.poke(II)V
sipush 22544
sipush 8255
invokestatic OS/Memory.poke(II)V
sipush 22545
sipush 768
invokestatic OS/Memory.poke(II)V
sipush 22546
sipush 4096
ineg
invokestatic OS/Memory.poke(II)V
sipush 22547
sipush 387
invokestatic OS/Memory.poke(II)V
sipush 22548
sipush 15488
invokestatic OS/Memory.poke(II)V
sipush 22549
sipush 6192
invokestatic OS/Memory.poke(II)V
sipush 22573
sipush 16384
sipush 16384
iadd
invokestatic OS/Memory.poke(II)V
sipush 22574
iconst_1
invokestatic OS/Memory.poke(II)V
sipush 22575
sipush 976
ineg
invokestatic OS/Memory.poke(II)V
sipush 22576
sipush 8065
ineg
invokestatic OS/Memory.poke(II)V
sipush 22577
sipush 384
invokestatic OS/Memory.poke(II)V
sipush 22578
sipush 24576
invokestatic OS/Memory.poke(II)V
sipush 22579
sipush 897
invokestatic OS/Memory.poke(II)V
sipush 22580
sipush 1920
ineg
invokestatic OS/Memory.poke(II)V
sipush 22581
sipush 3103
invokestatic OS/Memory.poke(II)V
sipush 22605
sipush 16384
ineg
invokestatic OS/Memory.poke(II)V
sipush 22607
sipush 15360
ineg
invokestatic OS/Memory.poke(II)V
sipush 22608
sipush 32513
ineg
invokestatic OS/Memory.poke(II)V
sipush 22609
sipush 385
invokestatic OS/Memory.poke(II)V
sipush 22610
sipush 8192
ineg
invokestatic OS/Memory.poke(II)V
sipush 22611
sipush 897
invokestatic OS/Memory.poke(II)V
sipush 22612
sipush 14464
invokestatic OS/Memory.poke(II)V
sipush 22613
sipush 1052
invokestatic OS/Memory.poke(II)V
sipush 22637
sipush 28672
invokestatic OS/Memory.poke(II)V
sipush 22638
iconst_4
invokestatic OS/Memory.poke(II)V
sipush 22639
sipush 13312
ineg
invokestatic OS/Memory.poke(II)V
sipush 22640
sipush 1151
invokestatic OS/Memory.poke(II)V
sipush 22641
sipush 192
invokestatic OS/Memory.poke(II)V
sipush 22642
sipush 16384
ineg
invokestatic OS/Memory.poke(II)V
sipush 22643
sipush 1667
invokestatic OS/Memory.poke(II)V
sipush 22644
sipush 6272
invokestatic OS/Memory.poke(II)V
sipush 22645
sipush 792
invokestatic OS/Memory.poke(II)V
sipush 22669
sipush 7168
invokestatic OS/Memory.poke(II)V
sipush 22670
bipush 6
invokestatic OS/Memory.poke(II)V
sipush 22671
sipush 7168
ineg
invokestatic OS/Memory.poke(II)V
sipush 22672
sipush 1663
invokestatic OS/Memory.poke(II)V
sipush 22673
bipush 96
invokestatic OS/Memory.poke(II)V
sipush 22674
sipush 8192
ineg
invokestatic OS/Memory.poke(II)V
sipush 22675
sipush 1167
invokestatic OS/Memory.poke(II)V
sipush 22676
sipush 6272
invokestatic OS/Memory.poke(II)V
sipush 22677
sipush 488
invokestatic OS/Memory.poke(II)V
sipush 22701
sipush 9728
invokestatic OS/Memory.poke(II)V
sipush 22702
iconst_3
invokestatic OS/Memory.poke(II)V
sipush 22703
sipush 8192
invokestatic OS/Memory.poke(II)V
sipush 22704
sipush 1791
invokestatic OS/Memory.poke(II)V
sipush 22705
sipush 480
invokestatic OS/Memory.poke(II)V
sipush 22706
sipush 16384
ineg
invokestatic OS/Memory.poke(II)V
sipush 22707
sipush 3215
invokestatic OS/Memory.poke(II)V
sipush 22708
sipush 6528
invokestatic OS/Memory.poke(II)V
sipush 22709
bipush 124
invokestatic OS/Memory.poke(II)V
sipush 22733
sipush 7936
ineg
invokestatic OS/Memory.poke(II)V
sipush 22734
sipush 193
invokestatic OS/Memory.poke(II)V
sipush 22735
sipush 14336
invokestatic OS/Memory.poke(II)V
sipush 22736
sipush 191
invokestatic OS/Memory.poke(II)V
sipush 22737
sipush 4080
invokestatic OS/Memory.poke(II)V
sipush 22738
sipush 16384
sipush 16384
iadd
invokestatic OS/Memory.poke(II)V
sipush 22739
sipush 2055
invokestatic OS/Memory.poke(II)V
sipush 22740
sipush 6400
invokestatic OS/Memory.poke(II)V
sipush 22741
bipush 28
invokestatic OS/Memory.poke(II)V
sipush 22765
sipush 2304
invokestatic OS/Memory.poke(II)V
sipush 22766
sipush 192
invokestatic OS/Memory.poke(II)V
sipush 22767
sipush 1024
ineg
invokestatic OS/Memory.poke(II)V
sipush 22768
sipush 385
invokestatic OS/Memory.poke(II)V
sipush 22769
sipush 16380
invokestatic OS/Memory.poke(II)V
sipush 22771
sipush 6151
invokestatic OS/Memory.poke(II)V
sipush 22772
sipush 12544
invokestatic OS/Memory.poke(II)V
sipush 22797
sipush 3840
invokestatic OS/Memory.poke(II)V
sipush 22799
sipush 128
ineg
invokestatic OS/Memory.poke(II)V
sipush 22800
sipush 768
invokestatic OS/Memory.poke(II)V
sipush 22801
bipush 116
ineg
invokestatic OS/Memory.poke(II)V
sipush 22802
iconst_3
invokestatic OS/Memory.poke(II)V
sipush 22803
sipush 4126
invokestatic OS/Memory.poke(II)V
sipush 22804
sipush 25344
invokestatic OS/Memory.poke(II)V
sipush 22829
sipush 30976
ineg
invokestatic OS/Memory.poke(II)V
sipush 22831
sipush 2046
invokestatic OS/Memory.poke(II)V
sipush 22832
sipush 512
invokestatic OS/Memory.poke(II)V
sipush 22833
sipush 9216
ineg
invokestatic OS/Memory.poke(II)V
sipush 22834
bipush 7
invokestatic OS/Memory.poke(II)V
sipush 22835
sipush 12414
invokestatic OS/Memory.poke(II)V
sipush 22836
sipush 14848
ineg
invokestatic OS/Memory.poke(II)V
sipush 22837
iconst_3
invokestatic OS/Memory.poke(II)V
sipush 22861
sipush 32512
ineg
invokestatic OS/Memory.poke(II)V
sipush 22862
sipush 2047
ineg
invokestatic OS/Memory.poke(II)V
sipush 22863
iconst_1
invokestatic OS/Memory.poke(II)V
sipush 22864
sipush 20992
invokestatic OS/Memory.poke(II)V
sipush 22865
sipush 11264
ineg
invokestatic OS/Memory.poke(II)V
sipush 22866
bipush 7
invokestatic OS/Memory.poke(II)V
sipush 22867
sipush 24696
invokestatic OS/Memory.poke(II)V
sipush 22868
sipush 7168
invokestatic OS/Memory.poke(II)V
sipush 22869
bipush 14
invokestatic OS/Memory.poke(II)V
sipush 22893
sipush 256
invokestatic OS/Memory.poke(II)V
sipush 22894
sipush 2047
invokestatic OS/Memory.poke(II)V
sipush 22896
sipush 29184
invokestatic OS/Memory.poke(II)V
sipush 22897
bipush 13
invokestatic OS/Memory.poke(II)V
sipush 22898
bipush 7
invokestatic OS/Memory.poke(II)V
sipush 22899
sipush 15376
ineg
invokestatic OS/Memory.poke(II)V
sipush 22900
sipush 12288
invokestatic OS/Memory.poke(II)V
sipush 22901
bipush 24
invokestatic OS/Memory.poke(II)V
sipush 22925
sipush 256
invokestatic OS/Memory.poke(II)V
sipush 22926
sipush 496
invokestatic OS/Memory.poke(II)V
sipush 22928
sipush 31232
ineg
invokestatic OS/Memory.poke(II)V
sipush 22929
sipush 32759
ineg
invokestatic OS/Memory.poke(II)V
sipush 22930
bipush 15
invokestatic OS/Memory.poke(II)V
sipush 22931
sipush 32576
ineg
invokestatic OS/Memory.poke(II)V
sipush 22932
sipush 24577
invokestatic OS/Memory.poke(II)V
sipush 22933
sipush 224
invokestatic OS/Memory.poke(II)V
sipush 22957
sipush 7424
invokestatic OS/Memory.poke(II)V
sipush 22958
sipush 1020
invokestatic OS/Memory.poke(II)V
sipush 22960
sipush 1024
invokestatic OS/Memory.poke(II)V
sipush 22961
sipush 16393
invokestatic OS/Memory.poke(II)V
sipush 22962
bipush 14
invokestatic OS/Memory.poke(II)V
sipush 22963
sipush 896
invokestatic OS/Memory.poke(II)V
sipush 22964
sipush 16381
ineg
invokestatic OS/Memory.poke(II)V
sipush 22965
sipush 960
invokestatic OS/Memory.poke(II)V
sipush 22989
sipush 7424
invokestatic OS/Memory.poke(II)V
sipush 22990
sipush 2008
invokestatic OS/Memory.poke(II)V
sipush 22992
sipush 1024
invokestatic OS/Memory.poke(II)V
sipush 22993
bipush 109
invokestatic OS/Memory.poke(II)V
sipush 22994
bipush 10
invokestatic OS/Memory.poke(II)V
sipush 22995
sipush 1792
invokestatic OS/Memory.poke(II)V
sipush 22996
sipush 32762
ineg
invokestatic OS/Memory.poke(II)V
sipush 22997
sipush 901
invokestatic OS/Memory.poke(II)V
sipush 23021
sipush 4864
invokestatic OS/Memory.poke(II)V
sipush 23022
sipush 2008
invokestatic OS/Memory.poke(II)V
sipush 23024
sipush 1024
invokestatic OS/Memory.poke(II)V
sipush 23025
bipush 76
invokestatic OS/Memory.poke(II)V
sipush 23026
bipush 10
invokestatic OS/Memory.poke(II)V
sipush 23027
sipush 3584
invokestatic OS/Memory.poke(II)V
sipush 23028
bipush 12
invokestatic OS/Memory.poke(II)V
sipush 23029
sipush 1951
invokestatic OS/Memory.poke(II)V
sipush 23053
sipush 3584
ineg
invokestatic OS/Memory.poke(II)V
sipush 23054
sipush 1806
invokestatic OS/Memory.poke(II)V
sipush 23056
sipush 7168
invokestatic OS/Memory.poke(II)V
sipush 23057
sipush 192
invokestatic OS/Memory.poke(II)V
sipush 23058
bipush 10
invokestatic OS/Memory.poke(II)V
sipush 23059
sipush 7168
invokestatic OS/Memory.poke(II)V
sipush 23060
bipush 24
invokestatic OS/Memory.poke(II)V
sipush 23061
sipush 1836
invokestatic OS/Memory.poke(II)V
sipush 23085
sipush 25088
invokestatic OS/Memory.poke(II)V
sipush 23086
sipush 1792
invokestatic OS/Memory.poke(II)V
sipush 23088
sipush 7168
invokestatic OS/Memory.poke(II)V
sipush 23089
sipush 1024
invokestatic OS/Memory.poke(II)V
sipush 23090
bipush 14
invokestatic OS/Memory.poke(II)V
sipush 23091
sipush 14336
invokestatic OS/Memory.poke(II)V
sipush 23092
bipush 112
invokestatic OS/Memory.poke(II)V
sipush 23093
sipush 1848
invokestatic OS/Memory.poke(II)V
sipush 23117
sipush 6656
invokestatic OS/Memory.poke(II)V
sipush 23118
sipush 1792
invokestatic OS/Memory.poke(II)V
sipush 23120
sipush 2048
ineg
invokestatic OS/Memory.poke(II)V
sipush 23121
sipush 4095
invokestatic OS/Memory.poke(II)V
sipush 23122
bipush 15
invokestatic OS/Memory.poke(II)V
sipush 23123
sipush 28672
invokestatic OS/Memory.poke(II)V
sipush 23124
sipush 192
invokestatic OS/Memory.poke(II)V
sipush 23125
sipush 1584
invokestatic OS/Memory.poke(II)V
sipush 23149
sipush 3584
invokestatic OS/Memory.poke(II)V
sipush 23150
sipush 1920
invokestatic OS/Memory.poke(II)V
sipush 23153
sipush 2032
invokestatic OS/Memory.poke(II)V
sipush 23154
bipush 31
invokestatic OS/Memory.poke(II)V
sipush 23155
sipush 8192
ineg
invokestatic OS/Memory.poke(II)V
sipush 23156
sipush 384
invokestatic OS/Memory.poke(II)V
sipush 23157
sipush 1072
invokestatic OS/Memory.poke(II)V
sipush 23181
sipush 1536
invokestatic OS/Memory.poke(II)V
sipush 23182
sipush 1920
invokestatic OS/Memory.poke(II)V
sipush 23185
sipush 15392
ineg
invokestatic OS/Memory.poke(II)V
sipush 23186
bipush 28
invokestatic OS/Memory.poke(II)V
sipush 23187
sipush 16384
ineg
invokestatic OS/Memory.poke(II)V
sipush 23188
sipush 769
invokestatic OS/Memory.poke(II)V
sipush 23189
sipush 1072
invokestatic OS/Memory.poke(II)V
sipush 23213
sipush 1024
invokestatic OS/Memory.poke(II)V
sipush 23214
sipush 1792
invokestatic OS/Memory.poke(II)V
sipush 23217
sipush 25568
invokestatic OS/Memory.poke(II)V
sipush 23218
bipush 28
invokestatic OS/Memory.poke(II)V
sipush 23219
sipush 16384
sipush 16384
iadd
invokestatic OS/Memory.poke(II)V
sipush 23220
sipush 1539
invokestatic OS/Memory.poke(II)V
sipush 23221
sipush 1072
invokestatic OS/Memory.poke(II)V
sipush 23245
sipush 13312
ineg
invokestatic OS/Memory.poke(II)V
sipush 23246
sipush 1792
invokestatic OS/Memory.poke(II)V
sipush 23249
sipush 960
invokestatic OS/Memory.poke(II)V
sipush 23250
bipush 24
invokestatic OS/Memory.poke(II)V
sipush 23252
sipush 7175
invokestatic OS/Memory.poke(II)V
sipush 23253
sipush 1072
invokestatic OS/Memory.poke(II)V
sipush 23277
sipush 26624
ineg
invokestatic OS/Memory.poke(II)V
sipush 23278
sipush 1920
invokestatic OS/Memory.poke(II)V
sipush 23281
sipush 1984
invokestatic OS/Memory.poke(II)V
sipush 23282
bipush 28
invokestatic OS/Memory.poke(II)V
sipush 23284
sipush 14364
invokestatic OS/Memory.poke(II)V
sipush 23285
sipush 1592
invokestatic OS/Memory.poke(II)V
sipush 23309
sipush 28672
ineg
invokestatic OS/Memory.poke(II)V
sipush 23310
sipush 1792
invokestatic OS/Memory.poke(II)V
sipush 23313
sipush 960
invokestatic OS/Memory.poke(II)V
sipush 23314
bipush 16
invokestatic OS/Memory.poke(II)V
sipush 23316
sipush 4040
ineg
invokestatic OS/Memory.poke(II)V
sipush 23317
sipush 527
invokestatic OS/Memory.poke(II)V
sipush 23341
sipush 24576
ineg
invokestatic OS/Memory.poke(II)V
sipush 23342
sipush 769
invokestatic OS/Memory.poke(II)V
sipush 23345
sipush 960
invokestatic OS/Memory.poke(II)V
sipush 23346
bipush 20
invokestatic OS/Memory.poke(II)V
sipush 23348
sipush 16288
ineg
invokestatic OS/Memory.poke(II)V
sipush 23349
sipush 519
invokestatic OS/Memory.poke(II)V
sipush 23373
sipush 8192
invokestatic OS/Memory.poke(II)V
sipush 23374
sipush 768
invokestatic OS/Memory.poke(II)V
sipush 23377
sipush 448
invokestatic OS/Memory.poke(II)V
sipush 23378
bipush 20
invokestatic OS/Memory.poke(II)V
sipush 23380
sipush 448
invokestatic OS/Memory.poke(II)V
sipush 23381
sipush 768
invokestatic OS/Memory.poke(II)V
sipush 23405
sipush 8192
invokestatic OS/Memory.poke(II)V
sipush 23406
sipush 256
invokestatic OS/Memory.poke(II)V
sipush 23409
sipush 448
invokestatic OS/Memory.poke(II)V
sipush 23410
bipush 16
invokestatic OS/Memory.poke(II)V
sipush 23412
sipush 896
invokestatic OS/Memory.poke(II)V
sipush 23413
sipush 256
invokestatic OS/Memory.poke(II)V
sipush 23437
sipush 8192
invokestatic OS/Memory.poke(II)V
sipush 23438
sipush 384
invokestatic OS/Memory.poke(II)V
sipush 23441
sipush 192
invokestatic OS/Memory.poke(II)V
sipush 23442
bipush 16
invokestatic OS/Memory.poke(II)V
sipush 23444
sipush 1792
invokestatic OS/Memory.poke(II)V
sipush 23445
sipush 448
invokestatic OS/Memory.poke(II)V
sipush 23469
sipush 16384
invokestatic OS/Memory.poke(II)V
sipush 23470
sipush 128
invokestatic OS/Memory.poke(II)V
sipush 23473
sipush 192
invokestatic OS/Memory.poke(II)V
sipush 23474
bipush 24
invokestatic OS/Memory.poke(II)V
sipush 23476
sipush 31744
invokestatic OS/Memory.poke(II)V
sipush 23477
sipush 252
invokestatic OS/Memory.poke(II)V
sipush 23501
sipush 16384
invokestatic OS/Memory.poke(II)V
sipush 23502
sipush 192
invokestatic OS/Memory.poke(II)V
sipush 23505
sipush 192
invokestatic OS/Memory.poke(II)V
sipush 23506
bipush 8
invokestatic OS/Memory.poke(II)V
sipush 23508
sipush 2048
ineg
invokestatic OS/Memory.poke(II)V
sipush 23509
bipush 63
invokestatic OS/Memory.poke(II)V
sipush 23533
sipush 16384
invokestatic OS/Memory.poke(II)V
sipush 23534
sipush 192
invokestatic OS/Memory.poke(II)V
sipush 23537
sipush 128
invokestatic OS/Memory.poke(II)V
sipush 23538
bipush 12
invokestatic OS/Memory.poke(II)V
sipush 23540
sipush 16384
ineg
invokestatic OS/Memory.poke(II)V
sipush 23541
bipush 7
invokestatic OS/Memory.poke(II)V
sipush 23565
sipush 16384
invokestatic OS/Memory.poke(II)V
sipush 23566
sipush 192
invokestatic OS/Memory.poke(II)V
sipush 23569
sipush 640
invokestatic OS/Memory.poke(II)V
sipush 23570
iconst_4
invokestatic OS/Memory.poke(II)V
sipush 23597
sipush 16384
invokestatic OS/Memory.poke(II)V
sipush 23598
sipush 960
invokestatic OS/Memory.poke(II)V
sipush 23601
sipush 896
invokestatic OS/Memory.poke(II)V
sipush 23602
iconst_4
invokestatic OS/Memory.poke(II)V
sipush 23629
sipush 16384
invokestatic OS/Memory.poke(II)V
sipush 23630
sipush 1664
invokestatic OS/Memory.poke(II)V
sipush 23633
sipush 1984
invokestatic OS/Memory.poke(II)V
sipush 23634
iconst_4
invokestatic OS/Memory.poke(II)V
sipush 23661
sipush 16384
invokestatic OS/Memory.poke(II)V
sipush 23662
sipush 1920
invokestatic OS/Memory.poke(II)V
sipush 23665
sipush 3520
invokestatic OS/Memory.poke(II)V
sipush 23666
iconst_4
invokestatic OS/Memory.poke(II)V
sipush 23693
sipush 16384
invokestatic OS/Memory.poke(II)V
sipush 23694
sipush 3456
invokestatic OS/Memory.poke(II)V
sipush 23697
sipush 5056
invokestatic OS/Memory.poke(II)V
sipush 23698
bipush 6
invokestatic OS/Memory.poke(II)V
sipush 23725
sipush 16384
invokestatic OS/Memory.poke(II)V
sipush 23726
sipush 14720
invokestatic OS/Memory.poke(II)V
sipush 23729
sipush 2016
invokestatic OS/Memory.poke(II)V
sipush 23730
bipush 6
invokestatic OS/Memory.poke(II)V
sipush 23757
sipush 24576
invokestatic OS/Memory.poke(II)V
sipush 23758
sipush 26496
invokestatic OS/Memory.poke(II)V
sipush 23761
sipush 496
invokestatic OS/Memory.poke(II)V
sipush 23762
bipush 6
invokestatic OS/Memory.poke(II)V
sipush 23789
sipush 4096
ineg
invokestatic OS/Memory.poke(II)V
sipush 23790
sipush 8320
ineg
invokestatic OS/Memory.poke(II)V
sipush 23793
bipush 120
invokestatic OS/Memory.poke(II)V
sipush 23794
bipush 14
invokestatic OS/Memory.poke(II)V
sipush 23821
sipush 512
ineg
invokestatic OS/Memory.poke(II)V
sipush 23822
sipush 24704
ineg
invokestatic OS/Memory.poke(II)V
sipush 23825
bipush 62
invokestatic OS/Memory.poke(II)V
sipush 23826
bipush 13
invokestatic OS/Memory.poke(II)V
sipush 23853
sipush 16512
ineg
invokestatic OS/Memory.poke(II)V
sipush 23854
sipush 25344
ineg
invokestatic OS/Memory.poke(II)V
sipush 23856
sipush 8192
ineg
invokestatic OS/Memory.poke(II)V
sipush 23857
bipush 11
invokestatic OS/Memory.poke(II)V
sipush 23858
bipush 25
invokestatic OS/Memory.poke(II)V
sipush 23885
sipush 20488
ineg
invokestatic OS/Memory.poke(II)V
sipush 23886
sipush 28415
ineg
invokestatic OS/Memory.poke(II)V
sipush 23888
sipush 12288
invokestatic OS/Memory.poke(II)V
sipush 23889
bipush 6
invokestatic OS/Memory.poke(II)V
sipush 23890
bipush 55
invokestatic OS/Memory.poke(II)V
sipush 23917
sipush 1871
invokestatic OS/Memory.poke(II)V
sipush 23918
sipush 3327
ineg
invokestatic OS/Memory.poke(II)V
sipush 23920
sipush 4096
invokestatic OS/Memory.poke(II)V
sipush 23921
bipush 14
invokestatic OS/Memory.poke(II)V
sipush 23922
bipush 47
invokestatic OS/Memory.poke(II)V
sipush 23948
sipush 16384
ineg
invokestatic OS/Memory.poke(II)V
sipush 23949
bipush 7
invokestatic OS/Memory.poke(II)V
sipush 23950
sipush 25088
invokestatic OS/Memory.poke(II)V
sipush 23952
sipush 26624
ineg
invokestatic OS/Memory.poke(II)V
sipush 23953
sipush 32738
ineg
invokestatic OS/Memory.poke(II)V
sipush 23954
bipush 123
invokestatic OS/Memory.poke(II)V
sipush 23980
sipush 24576
invokestatic OS/Memory.poke(II)V
sipush 23981
iconst_4
invokestatic OS/Memory.poke(II)V
sipush 23982
sipush 8960
invokestatic OS/Memory.poke(II)V
sipush 23984
sipush 18432
ineg
invokestatic OS/Memory.poke(II)V
sipush 23985
sipush 28769
ineg
invokestatic OS/Memory.poke(II)V
sipush 23986
bipush 113
invokestatic OS/Memory.poke(II)V
sipush 24012
sipush 8192
invokestatic OS/Memory.poke(II)V
sipush 24013
sipush 1542
invokestatic OS/Memory.poke(II)V
sipush 24014
sipush 256
invokestatic OS/Memory.poke(II)V
sipush 24016
sipush 2048
ineg
invokestatic OS/Memory.poke(II)V
sipush 24017
sipush 1801
ineg
invokestatic OS/Memory.poke(II)V
sipush 24018
bipush 7
invokestatic OS/Memory.poke(II)V
sipush 24044
sipush 8192
invokestatic OS/Memory.poke(II)V
sipush 24045
sipush 25729
ineg
invokestatic OS/Memory.poke(II)V
sipush 24046
sipush 449
invokestatic OS/Memory.poke(II)V
sipush 24048
sipush 2048
invokestatic OS/Memory.poke(II)V
sipush 24049
sipush 15481
invokestatic OS/Memory.poke(II)V
sipush 24076
sipush 8192
ineg
invokestatic OS/Memory.poke(II)V
sipush 24077
sipush 11833
ineg
invokestatic OS/Memory.poke(II)V
sipush 24078
bipush 127
invokestatic OS/Memory.poke(II)V
sipush 24080
sipush 2048
invokestatic OS/Memory.poke(II)V
sipush 24081
sipush 3697
invokestatic OS/Memory.poke(II)V
sipush 24108
sipush 24576
invokestatic OS/Memory.poke(II)V
sipush 24109
sipush 3646
ineg
invokestatic OS/Memory.poke(II)V
sipush 24110
iconst_1
invokestatic OS/Memory.poke(II)V
sipush 24112
sipush 16384
sipush 16384
iadd
invokestatic OS/Memory.poke(II)V
sipush 24113
sipush 1881
invokestatic OS/Memory.poke(II)V
sipush 24141
sipush 12787
invokestatic OS/Memory.poke(II)V
sipush 24144
sipush 16384
sipush 16384
iadd
invokestatic OS/Memory.poke(II)V
sipush 24145
sipush 333
invokestatic OS/Memory.poke(II)V
sipush 24173
sipush 15679
invokestatic OS/Memory.poke(II)V
sipush 24176
sipush 16384
sipush 16384
iadd
invokestatic OS/Memory.poke(II)V
sipush 24177
sipush 327
invokestatic OS/Memory.poke(II)V
sipush 24205
sipush 1821
invokestatic OS/Memory.poke(II)V
sipush 24209
sipush 451
invokestatic OS/Memory.poke(II)V
return
.end method
.method public static draw6()V
.limit stack 10
.limit locals 0
sipush 18254
sipush 1008
invokestatic OS/Memory.poke(II)V
sipush 18286
sipush 16112
invokestatic OS/Memory.poke(II)V
sipush 18318
sipush 6272
ineg
invokestatic OS/Memory.poke(II)V
sipush 18350
sipush 29696
ineg
invokestatic OS/Memory.poke(II)V
sipush 18351
iconst_3
invokestatic OS/Memory.poke(II)V
sipush 18382
sipush 4096
invokestatic OS/Memory.poke(II)V
sipush 18383
bipush 7
invokestatic OS/Memory.poke(II)V
sipush 18414
sipush 4096
invokestatic OS/Memory.poke(II)V
sipush 18415
bipush 6
invokestatic OS/Memory.poke(II)V
sipush 18446
sipush 12288
invokestatic OS/Memory.poke(II)V
sipush 18447
bipush 12
invokestatic OS/Memory.poke(II)V
sipush 18448
sipush 1024
invokestatic OS/Memory.poke(II)V
sipush 18478
sipush 4096
ineg
invokestatic OS/Memory.poke(II)V
sipush 18479
bipush 24
invokestatic OS/Memory.poke(II)V
sipush 18480
sipush 1024
invokestatic OS/Memory.poke(II)V
sipush 18510
sipush 4096
ineg
invokestatic OS/Memory.poke(II)V
sipush 18511
bipush 61
invokestatic OS/Memory.poke(II)V
sipush 18512
sipush 1024
invokestatic OS/Memory.poke(II)V
sipush 18542
sipush 4096
ineg
invokestatic OS/Memory.poke(II)V
sipush 18543
sipush 8191
invokestatic OS/Memory.poke(II)V
sipush 18544
sipush 3072
invokestatic OS/Memory.poke(II)V
sipush 18574
sipush 4096
ineg
invokestatic OS/Memory.poke(II)V
sipush 18575
sipush 3585
ineg
invokestatic OS/Memory.poke(II)V
sipush 18576
sipush 3073
invokestatic OS/Memory.poke(II)V
sipush 18606
sipush 4096
ineg
invokestatic OS/Memory.poke(II)V
sipush 18607
bipush 127
invokestatic OS/Memory.poke(II)V
sipush 18608
sipush 7171
invokestatic OS/Memory.poke(II)V
sipush 18638
sipush 14336
invokestatic OS/Memory.poke(II)V
sipush 18640
sipush 29703
invokestatic OS/Memory.poke(II)V
sipush 18670
sipush 30720
invokestatic OS/Memory.poke(II)V
sipush 18672
sipush 15332
ineg
invokestatic OS/Memory.poke(II)V
sipush 18702
sipush 4096
ineg
invokestatic OS/Memory.poke(II)V
sipush 18703
bipush 63
invokestatic OS/Memory.poke(II)V
sipush 18704
sipush 13264
ineg
invokestatic OS/Memory.poke(II)V
sipush 18705
bipush 7
invokestatic OS/Memory.poke(II)V
sipush 18734
sipush 8192
invokestatic OS/Memory.poke(II)V
sipush 18736
sipush 10128
ineg
invokestatic OS/Memory.poke(II)V
sipush 18737
iconst_4
invokestatic OS/Memory.poke(II)V
sipush 18766
sipush 8192
ineg
invokestatic OS/Memory.poke(II)V
sipush 18767
bipush 48
invokestatic OS/Memory.poke(II)V
sipush 18768
sipush 6336
invokestatic OS/Memory.poke(II)V
sipush 18769
iconst_5
invokestatic OS/Memory.poke(II)V
sipush 18798
sipush 16384
ineg
invokestatic OS/Memory.poke(II)V
sipush 18799
bipush 31
invokestatic OS/Memory.poke(II)V
sipush 18800
sipush 28800
invokestatic OS/Memory.poke(II)V
sipush 18801
bipush 59
ineg
invokestatic OS/Memory.poke(II)V
sipush 18802
sipush 1023
invokestatic OS/Memory.poke(II)V
sipush 18830
sipush 16384
ineg
invokestatic OS/Memory.poke(II)V
sipush 18831
bipush 63
invokestatic OS/Memory.poke(II)V
sipush 18832
sipush 29056
invokestatic OS/Memory.poke(II)V
sipush 18833
iconst_3
ineg
invokestatic OS/Memory.poke(II)V
sipush 18834
iconst_1
ineg
invokestatic OS/Memory.poke(II)V
sipush 18862
sipush 16384
ineg
invokestatic OS/Memory.poke(II)V
sipush 18863
iconst_1
invokestatic OS/Memory.poke(II)V
sipush 18864
sipush 16640
invokestatic OS/Memory.poke(II)V
sipush 18865
sipush 4095
invokestatic OS/Memory.poke(II)V
sipush 18866
sipush 2048
ineg
invokestatic OS/Memory.poke(II)V
sipush 18867
bipush 7
invokestatic OS/Memory.poke(II)V
sipush 18894
sipush 16384
ineg
invokestatic OS/Memory.poke(II)V
sipush 18896
sipush 25088
invokestatic OS/Memory.poke(II)V
sipush 18897
sipush 254
invokestatic OS/Memory.poke(II)V
sipush 18898
sipush 16384
ineg
invokestatic OS/Memory.poke(II)V
sipush 18899
bipush 63
invokestatic OS/Memory.poke(II)V
sipush 18926
sipush 16384
invokestatic OS/Memory.poke(II)V
sipush 18928
sipush 26112
invokestatic OS/Memory.poke(II)V
sipush 18929
sipush 8161
ineg
invokestatic OS/Memory.poke(II)V
sipush 18930
iconst_1
invokestatic OS/Memory.poke(II)V
sipush 18931
sipush 510
invokestatic OS/Memory.poke(II)V
sipush 18958
sipush 16384
invokestatic OS/Memory.poke(II)V
sipush 18960
sipush 28160
invokestatic OS/Memory.poke(II)V
sipush 18961
sipush 993
ineg
invokestatic OS/Memory.poke(II)V
sipush 18962
sipush 8191
invokestatic OS/Memory.poke(II)V
sipush 18963
sipush 2016
invokestatic OS/Memory.poke(II)V
sipush 18990
sipush 16384
invokestatic OS/Memory.poke(II)V
sipush 18992
sipush 30720
invokestatic OS/Memory.poke(II)V
sipush 18993
sipush 2047
invokestatic OS/Memory.poke(II)V
sipush 18994
iconst_1
ineg
invokestatic OS/Memory.poke(II)V
sipush 18995
sipush 7937
invokestatic OS/Memory.poke(II)V
sipush 19022
sipush 16384
ineg
invokestatic OS/Memory.poke(II)V
sipush 19024
sipush 8192
ineg
invokestatic OS/Memory.poke(II)V
sipush 19025
sipush 257
ineg
invokestatic OS/Memory.poke(II)V
sipush 19026
sipush 8079
invokestatic OS/Memory.poke(II)V
sipush 19027
sipush 30783
invokestatic OS/Memory.poke(II)V
sipush 19054
sipush 16384
sipush 16384
iadd
invokestatic OS/Memory.poke(II)V
sipush 19056
sipush 24576
invokestatic OS/Memory.poke(II)V
sipush 19057
sipush 1024
ineg
invokestatic OS/Memory.poke(II)V
sipush 19058
sipush 14385
invokestatic OS/Memory.poke(II)V
sipush 19059
sipush 24321
ineg
invokestatic OS/Memory.poke(II)V
sipush 19060
iconst_3
invokestatic OS/Memory.poke(II)V
sipush 19086
sipush 16384
ineg
invokestatic OS/Memory.poke(II)V
sipush 19088
sipush 16384
ineg
invokestatic OS/Memory.poke(II)V
sipush 19089
sipush 4095
invokestatic OS/Memory.poke(II)V
sipush 19090
bipush 16
invokestatic OS/Memory.poke(II)V
sipush 19091
sipush 8188
invokestatic OS/Memory.poke(II)V
sipush 19092
bipush 6
invokestatic OS/Memory.poke(II)V
sipush 19118
sipush 16384
ineg
invokestatic OS/Memory.poke(II)V
sipush 19120
sipush 16384
sipush 16384
iadd
invokestatic OS/Memory.poke(II)V
sipush 19121
sipush 391
ineg
invokestatic OS/Memory.poke(II)V
sipush 19122
bipush 127
invokestatic OS/Memory.poke(II)V
sipush 19123
sipush 32224
invokestatic OS/Memory.poke(II)V
sipush 19124
bipush 8
invokestatic OS/Memory.poke(II)V
sipush 19150
sipush 16384
ineg
invokestatic OS/Memory.poke(II)V
sipush 19152
sipush 16384
sipush 16384
iadd
invokestatic OS/Memory.poke(II)V
sipush 19153
sipush 1089
ineg
invokestatic OS/Memory.poke(II)V
sipush 19154
sipush 1023
invokestatic OS/Memory.poke(II)V
sipush 19155
sipush 256
ineg
invokestatic OS/Memory.poke(II)V
sipush 19156
bipush 25
invokestatic OS/Memory.poke(II)V
sipush 19182
sipush 16384
ineg
invokestatic OS/Memory.poke(II)V
sipush 19184
sipush 16384
sipush 16384
iadd
invokestatic OS/Memory.poke(II)V
sipush 19185
sipush 32537
ineg
invokestatic OS/Memory.poke(II)V
sipush 19186
sipush 3583
invokestatic OS/Memory.poke(II)V
sipush 19187
sipush 7680
invokestatic OS/Memory.poke(II)V
sipush 19188
bipush 35
invokestatic OS/Memory.poke(II)V
sipush 19214
sipush 16384
ineg
invokestatic OS/Memory.poke(II)V
sipush 19216
sipush 16384
sipush 16384
iadd
invokestatic OS/Memory.poke(II)V
sipush 19217
sipush 927
invokestatic OS/Memory.poke(II)V
sipush 19218
sipush 4092
invokestatic OS/Memory.poke(II)V
sipush 19219
sipush 22528
invokestatic OS/Memory.poke(II)V
sipush 19220
sipush 199
invokestatic OS/Memory.poke(II)V
sipush 19246
sipush 16384
ineg
invokestatic OS/Memory.poke(II)V
sipush 19249
sipush 3815
invokestatic OS/Memory.poke(II)V
sipush 19250
sipush 16352
invokestatic OS/Memory.poke(II)V
sipush 19251
sipush 20479
ineg
invokestatic OS/Memory.poke(II)V
sipush 19252
sipush 414
invokestatic OS/Memory.poke(II)V
sipush 19278
sipush 16384
ineg
invokestatic OS/Memory.poke(II)V
sipush 19281
sipush 8079
invokestatic OS/Memory.poke(II)V
sipush 19282
sipush 32640
invokestatic OS/Memory.poke(II)V
sipush 19283
sipush 16370
ineg
invokestatic OS/Memory.poke(II)V
sipush 19284
sipush 789
invokestatic OS/Memory.poke(II)V
sipush 19310
sipush 4096
ineg
invokestatic OS/Memory.poke(II)V
sipush 19313
sipush 15887
invokestatic OS/Memory.poke(II)V
sipush 19314
sipush 32512
invokestatic OS/Memory.poke(II)V
sipush 19315
sipush 16384
sipush 16384
iadd
invokestatic OS/Memory.poke(II)V
sipush 19316
sipush 1591
invokestatic OS/Memory.poke(II)V
sipush 19342
sipush 2048
ineg
invokestatic OS/Memory.poke(II)V
sipush 19345
sipush 2017
ineg
invokestatic OS/Memory.poke(II)V
sipush 19346
sipush 1024
ineg
invokestatic OS/Memory.poke(II)V
sipush 19347
bipush 15
invokestatic OS/Memory.poke(II)V
sipush 19348
sipush 3188
invokestatic OS/Memory.poke(II)V
sipush 19373
bipush 112
invokestatic OS/Memory.poke(II)V
sipush 19374
sipush 26624
ineg
invokestatic OS/Memory.poke(II)V
sipush 19376
sipush 16384
sipush 16384
iadd
invokestatic OS/Memory.poke(II)V
sipush 19377
sipush 4065
ineg
invokestatic OS/Memory.poke(II)V
sipush 19378
sipush 4093
ineg
invokestatic OS/Memory.poke(II)V
sipush 19379
iconst_1
invokestatic OS/Memory.poke(II)V
sipush 19380
sipush 6344
invokestatic OS/Memory.poke(II)V
sipush 19405
sipush 1936
invokestatic OS/Memory.poke(II)V
sipush 19406
sipush 25600
ineg
invokestatic OS/Memory.poke(II)V
sipush 19408
sipush 16384
sipush 16384
iadd
invokestatic OS/Memory.poke(II)V
sipush 19409
sipush 16321
ineg
invokestatic OS/Memory.poke(II)V
sipush 19410
sipush 8177
ineg
invokestatic OS/Memory.poke(II)V
sipush 19411
bipush 127
invokestatic OS/Memory.poke(II)V
sipush 19412
sipush 12440
invokestatic OS/Memory.poke(II)V
sipush 19437
sipush 3632
invokestatic OS/Memory.poke(II)V
sipush 19438
sipush 11776
invokestatic OS/Memory.poke(II)V
sipush 19440
sipush 16384
ineg
invokestatic OS/Memory.poke(II)V
sipush 19441
sipush 32705
ineg
invokestatic OS/Memory.poke(II)V
sipush 19442
sipush 16321
ineg
invokestatic OS/Memory.poke(II)V
sipush 19443
sipush 965
invokestatic OS/Memory.poke(II)V
sipush 19444
sipush 25496
invokestatic OS/Memory.poke(II)V
sipush 19469
sipush 6768
invokestatic OS/Memory.poke(II)V
sipush 19470
sipush 10752
invokestatic OS/Memory.poke(II)V
sipush 19472
sipush 1024
ineg
invokestatic OS/Memory.poke(II)V
sipush 19473
sipush 255
invokestatic OS/Memory.poke(II)V
sipush 19474
sipush 32641
ineg
invokestatic OS/Memory.poke(II)V
sipush 19475
bipush 31
invokestatic OS/Memory.poke(II)V
sipush 19476
sipush 17280
invokestatic OS/Memory.poke(II)V
sipush 19501
sipush 4680
invokestatic OS/Memory.poke(II)V
sipush 19502
sipush 10496
invokestatic OS/Memory.poke(II)V
sipush 19503
bipush 29
invokestatic OS/Memory.poke(II)V
sipush 19504
sipush 15488
ineg
invokestatic OS/Memory.poke(II)V
sipush 19505
sipush 500
invokestatic OS/Memory.poke(II)V
sipush 19506
sipush 1022
invokestatic OS/Memory.poke(II)V
sipush 19507
sipush 758
invokestatic OS/Memory.poke(II)V
sipush 19508
sipush 15104
ineg
invokestatic OS/Memory.poke(II)V
sipush 19533
sipush 8776
invokestatic OS/Memory.poke(II)V
sipush 19534
sipush 10688
invokestatic OS/Memory.poke(II)V
sipush 19535
bipush 13
invokestatic OS/Memory.poke(II)V
sipush 19536
sipush 31936
invokestatic OS/Memory.poke(II)V
sipush 19537
sipush 1008
invokestatic OS/Memory.poke(II)V
sipush 19538
sipush 1754
invokestatic OS/Memory.poke(II)V
sipush 19539
sipush 3564
invokestatic OS/Memory.poke(II)V
sipush 19540
sipush 29184
ineg
invokestatic OS/Memory.poke(II)V
sipush 19565
sipush 32712
invokestatic OS/Memory.poke(II)V
sipush 19566
sipush 10304
invokestatic OS/Memory.poke(II)V
sipush 19567
bipush 6
invokestatic OS/Memory.poke(II)V
sipush 19568
sipush 1888
invokestatic OS/Memory.poke(II)V
sipush 19569
sipush 2032
invokestatic OS/Memory.poke(II)V
sipush 19570
sipush 3508
invokestatic OS/Memory.poke(II)V
sipush 19571
sipush 456
invokestatic OS/Memory.poke(II)V
sipush 19572
sipush 25600
ineg
invokestatic OS/Memory.poke(II)V
sipush 19573
iconst_1
invokestatic OS/Memory.poke(II)V
sipush 19597
sipush 13944
ineg
invokestatic OS/Memory.poke(II)V
sipush 19598
sipush 27680
invokestatic OS/Memory.poke(II)V
sipush 19599
sipush 4086
invokestatic OS/Memory.poke(II)V
sipush 19600
sipush 15952
ineg
invokestatic OS/Memory.poke(II)V
sipush 19601
sipush 4048
invokestatic OS/Memory.poke(II)V
sipush 19602
sipush 7788
invokestatic OS/Memory.poke(II)V
sipush 19603
sipush 1016
invokestatic OS/Memory.poke(II)V
sipush 19604
sipush 15360
invokestatic OS/Memory.poke(II)V
sipush 19605
iconst_1
invokestatic OS/Memory.poke(II)V
sipush 19629
sipush 13944
ineg
invokestatic OS/Memory.poke(II)V
sipush 19630
sipush 17535
invokestatic OS/Memory.poke(II)V
sipush 19631
sipush 16382
invokestatic OS/Memory.poke(II)V
sipush 19632
sipush 16136
ineg
invokestatic OS/Memory.poke(II)V
sipush 19633
sipush 7632
invokestatic OS/Memory.poke(II)V
sipush 19634
sipush 15944
invokestatic OS/Memory.poke(II)V
sipush 19635
sipush 4080
invokestatic OS/Memory.poke(II)V
sipush 19636
sipush 30720
invokestatic OS/Memory.poke(II)V
sipush 19637
iconst_2
invokestatic OS/Memory.poke(II)V
sipush 19661
sipush 7112
invokestatic OS/Memory.poke(II)V
sipush 19662
sipush 18397
invokestatic OS/Memory.poke(II)V
sipush 19663
sipush 10246
ineg
invokestatic OS/Memory.poke(II)V
sipush 19664
sipush 16260
ineg
invokestatic OS/Memory.poke(II)V
sipush 19665
sipush 6928
invokestatic OS/Memory.poke(II)V
sipush 19666
sipush 30928
invokestatic OS/Memory.poke(II)V
sipush 19667
sipush 29296
invokestatic OS/Memory.poke(II)V
sipush 19668
sipush 12288
ineg
invokestatic OS/Memory.poke(II)V
sipush 19669
bipush 6
invokestatic OS/Memory.poke(II)V
sipush 19693
sipush 13960
invokestatic OS/Memory.poke(II)V
sipush 19694
sipush 18373
invokestatic OS/Memory.poke(II)V
sipush 19695
bipush 6
ineg
invokestatic OS/Memory.poke(II)V
sipush 19696
sipush 16363
ineg
invokestatic OS/Memory.poke(II)V
sipush 19697
sipush 16128
invokestatic OS/Memory.poke(II)V
sipush 19698
sipush 11808
ineg
invokestatic OS/Memory.poke(II)V
sipush 19699
sipush 6944
ineg
invokestatic OS/Memory.poke(II)V
sipush 19700
sipush 16384
sipush 16384
iadd
invokestatic OS/Memory.poke(II)V
sipush 19701
bipush 12
invokestatic OS/Memory.poke(II)V
sipush 19725
sipush 27784
invokestatic OS/Memory.poke(II)V
sipush 19726
sipush 18423
invokestatic OS/Memory.poke(II)V
sipush 19727
sipush 32626
invokestatic OS/Memory.poke(II)V
sipush 19728
sipush 8161
ineg
invokestatic OS/Memory.poke(II)V
sipush 19729
sipush 32512
invokestatic OS/Memory.poke(II)V
sipush 19730
sipush 9152
invokestatic OS/Memory.poke(II)V
sipush 19731
sipush 11713
invokestatic OS/Memory.poke(II)V
sipush 19732
sipush 8192
ineg
invokestatic OS/Memory.poke(II)V
sipush 19733
bipush 28
invokestatic OS/Memory.poke(II)V
sipush 19757
sipush 22664
invokestatic OS/Memory.poke(II)V
sipush 19758
sipush 17819
invokestatic OS/Memory.poke(II)V
sipush 19759
sipush 14094
ineg
invokestatic OS/Memory.poke(II)V
sipush 19760
sipush 24547
ineg
invokestatic OS/Memory.poke(II)V
sipush 19761
sipush 512
ineg
invokestatic OS/Memory.poke(II)V
sipush 19762
sipush 18048
invokestatic OS/Memory.poke(II)V
sipush 19763
sipush 6531
invokestatic OS/Memory.poke(II)V
sipush 19764
sipush 16384
ineg
invokestatic OS/Memory.poke(II)V
sipush 19765
bipush 49
invokestatic OS/Memory.poke(II)V
sipush 19789
sipush 31928
invokestatic OS/Memory.poke(II)V
sipush 19790
sipush 18118
invokestatic OS/Memory.poke(II)V
sipush 19791
sipush 18482
invokestatic OS/Memory.poke(II)V
sipush 19792
sipush 20355
ineg
invokestatic OS/Memory.poke(II)V
sipush 19793
sipush 4095
ineg
invokestatic OS/Memory.poke(II)V
sipush 19794
sipush 31616
ineg
invokestatic OS/Memory.poke(II)V
sipush 19795
sipush 4935
invokestatic OS/Memory.poke(II)V
sipush 19796
sipush 16380
ineg
invokestatic OS/Memory.poke(II)V
sipush 19797
bipush 35
invokestatic OS/Memory.poke(II)V
sipush 19821
sipush 6224
ineg
invokestatic OS/Memory.poke(II)V
sipush 19822
sipush 18047
invokestatic OS/Memory.poke(II)V
sipush 19823
bipush 26
invokestatic OS/Memory.poke(II)V
sipush 19824
sipush 15308
invokestatic OS/Memory.poke(II)V
sipush 19825
sipush 6143
ineg
invokestatic OS/Memory.poke(II)V
sipush 19826
sipush 31487
ineg
invokestatic OS/Memory.poke(II)V
sipush 19827
sipush 2547
ineg
invokestatic OS/Memory.poke(II)V
sipush 19828
bipush 28
invokestatic OS/Memory.poke(II)V
sipush 19829
bipush 34
invokestatic OS/Memory.poke(II)V
sipush 19853
sipush 23560
ineg
invokestatic OS/Memory.poke(II)V
sipush 19854
sipush 18303
invokestatic OS/Memory.poke(II)V
sipush 19855
sipush 283
invokestatic OS/Memory.poke(II)V
sipush 19856
sipush 16008
invokestatic OS/Memory.poke(II)V
sipush 19857
sipush 6143
ineg
invokestatic OS/Memory.poke(II)V
sipush 19858
sipush 3331
invokestatic OS/Memory.poke(II)V
sipush 19859
sipush 27675
invokestatic OS/Memory.poke(II)V
sipush 19860
sipush 8240
invokestatic OS/Memory.poke(II)V
sipush 19861
bipush 70
invokestatic OS/Memory.poke(II)V
sipush 19885
sipush 24440
ineg
invokestatic OS/Memory.poke(II)V
sipush 19886
sipush 17904
invokestatic OS/Memory.poke(II)V
sipush 19887
sipush 283
invokestatic OS/Memory.poke(II)V
sipush 19888
sipush 7808
invokestatic OS/Memory.poke(II)V
sipush 19889
sipush 18433
invokestatic OS/Memory.poke(II)V
sipush 19890
sipush 2563
invokestatic OS/Memory.poke(II)V
sipush 19891
sipush 10178
ineg
invokestatic OS/Memory.poke(II)V
sipush 19892
bipush 96
invokestatic OS/Memory.poke(II)V
sipush 19893
sipush 204
invokestatic OS/Memory.poke(II)V
sipush 19917
sipush 20344
ineg
invokestatic OS/Memory.poke(II)V
sipush 19918
sipush 31760
invokestatic OS/Memory.poke(II)V
sipush 19919
sipush 8167
ineg
invokestatic OS/Memory.poke(II)V
sipush 19920
sipush 3712
invokestatic OS/Memory.poke(II)V
sipush 19921
sipush 2047
ineg
invokestatic OS/Memory.poke(II)V
sipush 19922
sipush 6662
invokestatic OS/Memory.poke(II)V
sipush 19923
sipush 3972
ineg
invokestatic OS/Memory.poke(II)V
sipush 19924
sipush 481
invokestatic OS/Memory.poke(II)V
sipush 19925
sipush 412
invokestatic OS/Memory.poke(II)V
sipush 19949
sipush 28536
ineg
invokestatic OS/Memory.poke(II)V
sipush 19950
sipush 18320
invokestatic OS/Memory.poke(II)V
sipush 19951
sipush 32743
ineg
invokestatic OS/Memory.poke(II)V
sipush 19952
sipush 14690
ineg
invokestatic OS/Memory.poke(II)V
sipush 19953
sipush 24575
ineg
invokestatic OS/Memory.poke(II)V
sipush 19954
sipush 5645
invokestatic OS/Memory.poke(II)V
sipush 19955
sipush 20420
ineg
invokestatic OS/Memory.poke(II)V
sipush 19956
sipush 2019
invokestatic OS/Memory.poke(II)V
sipush 19957
sipush 792
invokestatic OS/Memory.poke(II)V
sipush 19981
sipush 28520
ineg
invokestatic OS/Memory.poke(II)V
sipush 19982
sipush 17424
invokestatic OS/Memory.poke(II)V
sipush 19983
sipush 16425
invokestatic OS/Memory.poke(II)V
sipush 19984
sipush 27036
invokestatic OS/Memory.poke(II)V
sipush 19986
sipush 7195
invokestatic OS/Memory.poke(II)V
sipush 19987
sipush 8072
ineg
invokestatic OS/Memory.poke(II)V
sipush 19988
sipush 16359
invokestatic OS/Memory.poke(II)V
sipush 19989
sipush 1648
invokestatic OS/Memory.poke(II)V
sipush 20013
sipush 9056
ineg
invokestatic OS/Memory.poke(II)V
sipush 20014
sipush 15344
ineg
invokestatic OS/Memory.poke(II)V
sipush 20015
sipush 28729
invokestatic OS/Memory.poke(II)V
sipush 20016
sipush 31104
invokestatic OS/Memory.poke(II)V
sipush 20018
sipush 14362
invokestatic OS/Memory.poke(II)V
sipush 20019
sipush 16280
ineg
invokestatic OS/Memory.poke(II)V
sipush 20020
sipush 15575
invokestatic OS/Memory.poke(II)V
sipush 20021
sipush 3552
invokestatic OS/Memory.poke(II)V
sipush 20045
sipush 8992
ineg
invokestatic OS/Memory.poke(II)V
sipush 20046
sipush 15344
ineg
invokestatic OS/Memory.poke(II)V
sipush 20047
bipush 57
invokestatic OS/Memory.poke(II)V
sipush 20048
sipush 15616
ineg
invokestatic OS/Memory.poke(II)V
sipush 20050
sipush 14396
invokestatic OS/Memory.poke(II)V
sipush 20051
sipush 32536
ineg
invokestatic OS/Memory.poke(II)V
sipush 20052
sipush 31134
invokestatic OS/Memory.poke(II)V
sipush 20053
sipush 6592
invokestatic OS/Memory.poke(II)V
sipush 20077
sipush 30528
ineg
invokestatic OS/Memory.poke(II)V
sipush 20078
sipush 15248
ineg
invokestatic OS/Memory.poke(II)V
sipush 20079
bipush 113
invokestatic OS/Memory.poke(II)V
sipush 20080
sipush 13312
ineg
invokestatic OS/Memory.poke(II)V
sipush 20081
iconst_1
invokestatic OS/Memory.poke(II)V
sipush 20082
sipush 28796
invokestatic OS/Memory.poke(II)V
sipush 20083
sipush 32320
ineg
invokestatic OS/Memory.poke(II)V
sipush 20084
sipush 7399
ineg
invokestatic OS/Memory.poke(II)V
sipush 20085
sipush 5000
invokestatic OS/Memory.poke(II)V
sipush 20109
sipush 30272
ineg
invokestatic OS/Memory.poke(II)V
sipush 20110
sipush 2818
ineg
invokestatic OS/Memory.poke(II)V
sipush 20111
sipush 272
invokestatic OS/Memory.poke(II)V
sipush 20113
bipush 6
invokestatic OS/Memory.poke(II)V
sipush 20114
sipush 28920
invokestatic OS/Memory.poke(II)V
sipush 20115
sipush 960
invokestatic OS/Memory.poke(II)V
sipush 20116
sipush 32229
ineg
invokestatic OS/Memory.poke(II)V
sipush 20117
sipush 13201
invokestatic OS/Memory.poke(II)V
sipush 20141
sipush 30336
ineg
invokestatic OS/Memory.poke(II)V
sipush 20142
sipush 31888
invokestatic OS/Memory.poke(II)V
sipush 20143
sipush 7920
ineg
invokestatic OS/Memory.poke(II)V
sipush 20145
bipush 28
invokestatic OS/Memory.poke(II)V
sipush 20146
sipush 24752
invokestatic OS/Memory.poke(II)V
sipush 20147
sipush 640
invokestatic OS/Memory.poke(II)V
sipush 20148
sipush 534
invokestatic OS/Memory.poke(II)V
sipush 20149
sipush 8966
invokestatic OS/Memory.poke(II)V
sipush 20170
sipush 960
invokestatic OS/Memory.poke(II)V
sipush 20173
sipush 128
ineg
invokestatic OS/Memory.poke(II)V
sipush 20174
sipush 15544
invokestatic OS/Memory.poke(II)V
sipush 20175
sipush 9008
invokestatic OS/Memory.poke(II)V
sipush 20177
bipush 56
invokestatic OS/Memory.poke(II)V
sipush 20178
sipush 15968
ineg
invokestatic OS/Memory.poke(II)V
sipush 20179
sipush 1920
invokestatic OS/Memory.poke(II)V
sipush 20180
sipush 1589
invokestatic OS/Memory.poke(II)V
sipush 20181
sipush 8972
invokestatic OS/Memory.poke(II)V
sipush 20202
sipush 3168
invokestatic OS/Memory.poke(II)V
sipush 20204
sipush 768
invokestatic OS/Memory.poke(II)V
sipush 20205
sipush 9858
ineg
invokestatic OS/Memory.poke(II)V
sipush 20206
sipush 31775
invokestatic OS/Memory.poke(II)V
sipush 20207
sipush 1568
invokestatic OS/Memory.poke(II)V
sipush 20208
sipush 18432
invokestatic OS/Memory.poke(II)V
sipush 20209
bipush 112
invokestatic OS/Memory.poke(II)V
sipush 20210
sipush 15520
ineg
invokestatic OS/Memory.poke(II)V
sipush 20211
sipush 1920
invokestatic OS/Memory.poke(II)V
sipush 20212
sipush 1068
invokestatic OS/Memory.poke(II)V
sipush 20213
sipush 9752
invokestatic OS/Memory.poke(II)V
sipush 20234
sipush 6176
invokestatic OS/Memory.poke(II)V
sipush 20236
sipush 14592
ineg
invokestatic OS/Memory.poke(II)V
sipush 20237
sipush 25629
ineg
invokestatic OS/Memory.poke(II)V
sipush 20238
sipush 32281
invokestatic OS/Memory.poke(II)V
sipush 20239
sipush 3104
invokestatic OS/Memory.poke(II)V
sipush 20240
sipush 16384
invokestatic OS/Memory.poke(II)V
sipush 20241
sipush 448
invokestatic OS/Memory.poke(II)V
sipush 20242
sipush 29216
ineg
invokestatic OS/Memory.poke(II)V
sipush 20243
sipush 3585
invokestatic OS/Memory.poke(II)V
sipush 20244
sipush 3180
invokestatic OS/Memory.poke(II)V
sipush 20245
sipush 17424
invokestatic OS/Memory.poke(II)V
sipush 20266
sipush 11824
invokestatic OS/Memory.poke(II)V
sipush 20268
sipush 4352
ineg
invokestatic OS/Memory.poke(II)V
sipush 20269
sipush 8208
ineg
invokestatic OS/Memory.poke(II)V
sipush 20270
sipush 32285
invokestatic OS/Memory.poke(II)V
sipush 20271
sipush 15456
invokestatic OS/Memory.poke(II)V
sipush 20272
bipush 64
invokestatic OS/Memory.poke(II)V
sipush 20273
sipush 928
invokestatic OS/Memory.poke(II)V
sipush 20274
sipush 26113
ineg
invokestatic OS/Memory.poke(II)V
sipush 20275
sipush 3585
invokestatic OS/Memory.poke(II)V
sipush 20276
sipush 6236
invokestatic OS/Memory.poke(II)V
sipush 20277
sipush 19504
invokestatic OS/Memory.poke(II)V
sipush 20298
sipush 400
ineg
invokestatic OS/Memory.poke(II)V
sipush 20299
bipush 7
invokestatic OS/Memory.poke(II)V
sipush 20300
sipush 512
ineg
invokestatic OS/Memory.poke(II)V
sipush 20301
bipush 100
ineg
invokestatic OS/Memory.poke(II)V
sipush 20302
sipush 483
ineg
invokestatic OS/Memory.poke(II)V
sipush 20303
sipush 6272
invokestatic OS/Memory.poke(II)V
sipush 20304
sipush 1632
invokestatic OS/Memory.poke(II)V
sipush 20305
sipush 29760
ineg
invokestatic OS/Memory.poke(II)V
sipush 20306
sipush 28173
ineg
invokestatic OS/Memory.poke(II)V
sipush 20307
sipush 5123
invokestatic OS/Memory.poke(II)V
sipush 20308
sipush 6384
invokestatic OS/Memory.poke(II)V
sipush 20309
sipush 18464
invokestatic OS/Memory.poke(II)V
sipush 20330
sipush 304
ineg
invokestatic OS/Memory.poke(II)V
sipush 20331
iconst_4
invokestatic OS/Memory.poke(II)V
sipush 20332
sipush 1120
invokestatic OS/Memory.poke(II)V
sipush 20333
bipush 25
ineg
invokestatic OS/Memory.poke(II)V
sipush 20334
sipush 481
ineg
invokestatic OS/Memory.poke(II)V
sipush 20335
sipush 4224
invokestatic OS/Memory.poke(II)V
sipush 20336
sipush 3072
invokestatic OS/Memory.poke(II)V
sipush 20337
sipush 14464
ineg
invokestatic OS/Memory.poke(II)V
sipush 20338
sipush 4576
invokestatic OS/Memory.poke(II)V
sipush 20339
sipush 15363
invokestatic OS/Memory.poke(II)V
sipush 20340
sipush 12720
invokestatic OS/Memory.poke(II)V
sipush 20341
sipush 10144
ineg
invokestatic OS/Memory.poke(II)V
sipush 20362
sipush 32656
invokestatic OS/Memory.poke(II)V
sipush 20363
bipush 8
invokestatic OS/Memory.poke(II)V
sipush 20364
sipush 28736
ineg
invokestatic OS/Memory.poke(II)V
sipush 20365
sipush 14285
ineg
invokestatic OS/Memory.poke(II)V
sipush 20366
sipush 2532
ineg
invokestatic OS/Memory.poke(II)V
sipush 20367
sipush 28672
invokestatic OS/Memory.poke(II)V
sipush 20369
sipush 256
ineg
invokestatic OS/Memory.poke(II)V
sipush 20370
sipush 12737
invokestatic OS/Memory.poke(II)V
sipush 20371
sipush 10243
invokestatic OS/Memory.poke(II)V
sipush 20372
sipush 12640
invokestatic OS/Memory.poke(II)V
sipush 20373
sipush 28480
ineg
invokestatic OS/Memory.poke(II)V
sipush 20394
sipush 8080
invokestatic OS/Memory.poke(II)V
sipush 20395
bipush 24
invokestatic OS/Memory.poke(II)V
sipush 20396
sipush 7296
ineg
invokestatic OS/Memory.poke(II)V
sipush 20397
sipush 30597
ineg
invokestatic OS/Memory.poke(II)V
sipush 20398
sipush 226
ineg
invokestatic OS/Memory.poke(II)V
sipush 20399
sipush 8161
ineg
invokestatic OS/Memory.poke(II)V
sipush 20401
sipush 1024
ineg
invokestatic OS/Memory.poke(II)V
sipush 20402
sipush 8513
invokestatic OS/Memory.poke(II)V
sipush 20403
sipush 30723
invokestatic OS/Memory.poke(II)V
sipush 20404
sipush 9024
invokestatic OS/Memory.poke(II)V
sipush 20405
sipush 20096
ineg
invokestatic OS/Memory.poke(II)V
sipush 20426
sipush 8080
invokestatic OS/Memory.poke(II)V
sipush 20427
bipush 48
invokestatic OS/Memory.poke(II)V
sipush 20428
sipush 512
ineg
invokestatic OS/Memory.poke(II)V
sipush 20429
sipush 30465
ineg
invokestatic OS/Memory.poke(II)V
sipush 20430
sipush 12525
ineg
invokestatic OS/Memory.poke(II)V
sipush 20431
sipush 16381
ineg
invokestatic OS/Memory.poke(II)V
sipush 20432
bipush 15
invokestatic OS/Memory.poke(II)V
sipush 20433
sipush 5120
ineg
invokestatic OS/Memory.poke(II)V
sipush 20434
sipush 8643
invokestatic OS/Memory.poke(II)V
sipush 20435
sipush 20486
invokestatic OS/Memory.poke(II)V
sipush 20436
sipush 26304
invokestatic OS/Memory.poke(II)V
sipush 20437
sipush 7936
ineg
invokestatic OS/Memory.poke(II)V
sipush 20458
sipush 5400
invokestatic OS/Memory.poke(II)V
sipush 20459
bipush 32
invokestatic OS/Memory.poke(II)V
sipush 20460
sipush 16384
sipush 16384
iadd
invokestatic OS/Memory.poke(II)V
sipush 20461
sipush 30481
ineg
invokestatic OS/Memory.poke(II)V
sipush 20462
sipush 14384
ineg
invokestatic OS/Memory.poke(II)V
sipush 20463
sipush 16381
ineg
invokestatic OS/Memory.poke(II)V
sipush 20464
bipush 15
invokestatic OS/Memory.poke(II)V
sipush 20465
sipush 29696
ineg
invokestatic OS/Memory.poke(II)V
sipush 20466
sipush 24963
invokestatic OS/Memory.poke(II)V
sipush 20467
sipush 28678
invokestatic OS/Memory.poke(II)V
sipush 20468
sipush 17792
invokestatic OS/Memory.poke(II)V
sipush 20469
sipush 7424
ineg
invokestatic OS/Memory.poke(II)V
sipush 20490
sipush 27788
ineg
invokestatic OS/Memory.poke(II)V
sipush 20491
bipush 35
invokestatic OS/Memory.poke(II)V
sipush 20492
sipush 16384
sipush 16384
iadd
invokestatic OS/Memory.poke(II)V
sipush 20493
sipush 30240
ineg
invokestatic OS/Memory.poke(II)V
sipush 20494
sipush 14352
ineg
invokestatic OS/Memory.poke(II)V
sipush 20495
sipush 16353
ineg
invokestatic OS/Memory.poke(II)V
sipush 20496
sipush 1023
invokestatic OS/Memory.poke(II)V
sipush 20497
sipush 2048
invokestatic OS/Memory.poke(II)V
sipush 20498
sipush 16775
invokestatic OS/Memory.poke(II)V
sipush 20499
sipush 24582
invokestatic OS/Memory.poke(II)V
sipush 20500
sipush 13056
ineg
invokestatic OS/Memory.poke(II)V
sipush 20501
sipush 15616
ineg
invokestatic OS/Memory.poke(II)V
sipush 20522
sipush 10506
ineg
invokestatic OS/Memory.poke(II)V
sipush 20523
bipush 55
invokestatic OS/Memory.poke(II)V
sipush 20524
sipush 16384
ineg
invokestatic OS/Memory.poke(II)V
sipush 20525
sipush 30240
ineg
invokestatic OS/Memory.poke(II)V
sipush 20526
sipush 14352
ineg
invokestatic OS/Memory.poke(II)V
sipush 20527
sipush 32642
ineg
invokestatic OS/Memory.poke(II)V
sipush 20528
bipush 127
invokestatic OS/Memory.poke(II)V
sipush 20529
sipush 2048
invokestatic OS/Memory.poke(II)V
sipush 20530
sipush 16114
ineg
invokestatic OS/Memory.poke(II)V
sipush 20531
sipush 8180
ineg
invokestatic OS/Memory.poke(II)V
sipush 20532
sipush 29184
ineg
invokestatic OS/Memory.poke(II)V
sipush 20533
sipush 14848
ineg
invokestatic OS/Memory.poke(II)V
sipush 20554
sipush 2062
ineg
invokestatic OS/Memory.poke(II)V
sipush 20555
bipush 31
invokestatic OS/Memory.poke(II)V
sipush 20556
sipush 8192
ineg
invokestatic OS/Memory.poke(II)V
sipush 20557
sipush 4384
ineg
invokestatic OS/Memory.poke(II)V
sipush 20558
sipush 26623
invokestatic OS/Memory.poke(II)V
sipush 20559
sipush 32706
ineg
invokestatic OS/Memory.poke(II)V
sipush 20560
sipush 8127
invokestatic OS/Memory.poke(II)V
sipush 20561
sipush 2048
invokestatic OS/Memory.poke(II)V
sipush 20562
sipush 32484
ineg
invokestatic OS/Memory.poke(II)V
sipush 20563
sipush 16372
ineg
invokestatic OS/Memory.poke(II)V
sipush 20564
sipush 25088
ineg
invokestatic OS/Memory.poke(II)V
sipush 20565
sipush 12799
ineg
invokestatic OS/Memory.poke(II)V
sipush 20586
sipush 4110
ineg
invokestatic OS/Memory.poke(II)V
sipush 20587
bipush 31
invokestatic OS/Memory.poke(II)V
sipush 20588
sipush 12288
invokestatic OS/Memory.poke(II)V
sipush 20589
sipush 832
ineg
invokestatic OS/Memory.poke(II)V
sipush 20590
sipush 1887
invokestatic OS/Memory.poke(II)V
sipush 20591
bipush 118
invokestatic OS/Memory.poke(II)V
sipush 20592
iconst_2
ineg
invokestatic OS/Memory.poke(II)V
sipush 20594
sipush 32648
ineg
invokestatic OS/Memory.poke(II)V
sipush 20595
sipush 16244
ineg
invokestatic OS/Memory.poke(II)V
sipush 20596
sipush 27647
ineg
invokestatic OS/Memory.poke(II)V
sipush 20597
sipush 1023
ineg
invokestatic OS/Memory.poke(II)V
sipush 20618
sipush 6046
ineg
invokestatic OS/Memory.poke(II)V
sipush 20619
bipush 29
invokestatic OS/Memory.poke(II)V
sipush 20620
sipush 20480
invokestatic OS/Memory.poke(II)V
sipush 20621
sipush 16192
ineg
invokestatic OS/Memory.poke(II)V
sipush 20622
sipush 1531
invokestatic OS/Memory.poke(II)V
sipush 20623
sipush 4086
invokestatic OS/Memory.poke(II)V
sipush 20624
sipush 2050
ineg
invokestatic OS/Memory.poke(II)V
sipush 20625
bipush 7
invokestatic OS/Memory.poke(II)V
sipush 20626
sipush 32528
ineg
invokestatic OS/Memory.poke(II)V
sipush 20627
sipush 16116
ineg
invokestatic OS/Memory.poke(II)V
sipush 20628
sipush 17391
ineg
invokestatic OS/Memory.poke(II)V
sipush 20629
sipush 2047
ineg
invokestatic OS/Memory.poke(II)V
sipush 20650
sipush 32766
invokestatic OS/Memory.poke(II)V
sipush 20651
bipush 23
invokestatic OS/Memory.poke(II)V
sipush 20652
sipush 4096
invokestatic OS/Memory.poke(II)V
sipush 20653
sipush 16864
invokestatic OS/Memory.poke(II)V
sipush 20654
sipush 1054
invokestatic OS/Memory.poke(II)V
sipush 20655
sipush 500
invokestatic OS/Memory.poke(II)V
sipush 20656
sipush 8176
invokestatic OS/Memory.poke(II)V
sipush 20657
sipush 248
invokestatic OS/Memory.poke(II)V
sipush 20658
sipush 31776
ineg
invokestatic OS/Memory.poke(II)V
sipush 20659
sipush 32372
ineg
invokestatic OS/Memory.poke(II)V
sipush 20660
sipush 18381
ineg
invokestatic OS/Memory.poke(II)V
sipush 20661
sipush 4093
ineg
invokestatic OS/Memory.poke(II)V
sipush 20662
iconst_1
invokestatic OS/Memory.poke(II)V
sipush 20682
sipush 32200
invokestatic OS/Memory.poke(II)V
sipush 20683
bipush 53
invokestatic OS/Memory.poke(II)V
sipush 20684
sipush 12288
invokestatic OS/Memory.poke(II)V
sipush 20685
sipush 15392
ineg
invokestatic OS/Memory.poke(II)V
sipush 20686
sipush 1055
invokestatic OS/Memory.poke(II)V
sipush 20687
sipush 996
invokestatic OS/Memory.poke(II)V
sipush 20688
bipush 32
ineg
invokestatic OS/Memory.poke(II)V
sipush 20690
sipush 31232
ineg
invokestatic OS/Memory.poke(II)V
sipush 20691
sipush 31848
ineg
invokestatic OS/Memory.poke(II)V
sipush 20692
sipush 12402
invokestatic OS/Memory.poke(II)V
sipush 20693
sipush 8189
ineg
invokestatic OS/Memory.poke(II)V
sipush 20694
iconst_1
invokestatic OS/Memory.poke(II)V
sipush 20714
sipush 2248
invokestatic OS/Memory.poke(II)V
sipush 20715
bipush 103
invokestatic OS/Memory.poke(II)V
sipush 20716
sipush 20480
invokestatic OS/Memory.poke(II)V
sipush 20717
sipush 32705
invokestatic OS/Memory.poke(II)V
sipush 20718
sipush 1054
invokestatic OS/Memory.poke(II)V
sipush 20719
sipush 4018
invokestatic OS/Memory.poke(II)V
sipush 20720
sipush 256
ineg
invokestatic OS/Memory.poke(II)V
sipush 20721
bipush 7
invokestatic OS/Memory.poke(II)V
sipush 20722
sipush 29696
ineg
invokestatic OS/Memory.poke(II)V
sipush 20723
sipush 792
invokestatic OS/Memory.poke(II)V
sipush 20724
sipush 12311
invokestatic OS/Memory.poke(II)V
sipush 20725
sipush 8185
ineg
invokestatic OS/Memory.poke(II)V
sipush 20726
iconst_1
invokestatic OS/Memory.poke(II)V
sipush 20746
sipush 6088
invokestatic OS/Memory.poke(II)V
sipush 20747
sipush 198
invokestatic OS/Memory.poke(II)V
sipush 20748
sipush 20480
invokestatic OS/Memory.poke(II)V
sipush 20749
sipush 20417
invokestatic OS/Memory.poke(II)V
sipush 20750
sipush 1032
invokestatic OS/Memory.poke(II)V
sipush 20751
sipush 8082
invokestatic OS/Memory.poke(II)V
sipush 20752
sipush 4096
ineg
invokestatic OS/Memory.poke(II)V
sipush 20753
sipush 12351
invokestatic OS/Memory.poke(II)V
sipush 20754
sipush 29696
ineg
invokestatic OS/Memory.poke(II)V
sipush 20755
sipush 792
invokestatic OS/Memory.poke(II)V
sipush 20756
sipush 8247
invokestatic OS/Memory.poke(II)V
sipush 20757
sipush 16378
ineg
invokestatic OS/Memory.poke(II)V
sipush 20758
iconst_3
invokestatic OS/Memory.poke(II)V
sipush 20778
sipush 32712
invokestatic OS/Memory.poke(II)V
sipush 20779
sipush 192
invokestatic OS/Memory.poke(II)V
sipush 20780
sipush 12288
ineg
invokestatic OS/Memory.poke(II)V
sipush 20781
sipush 20417
invokestatic OS/Memory.poke(II)V
sipush 20782
sipush 1032
invokestatic OS/Memory.poke(II)V
sipush 20783
sipush 16256
invokestatic OS/Memory.poke(II)V
sipush 20784
sipush 4096
ineg
invokestatic OS/Memory.poke(II)V
sipush 20785
sipush 8179
invokestatic OS/Memory.poke(II)V
sipush 20786
sipush 28608
ineg
invokestatic OS/Memory.poke(II)V
sipush 20787
sipush 3864
invokestatic OS/Memory.poke(II)V
sipush 20788
sipush 24695
invokestatic OS/Memory.poke(II)V
sipush 20789
sipush 32756
ineg
invokestatic OS/Memory.poke(II)V
sipush 20790
iconst_3
invokestatic OS/Memory.poke(II)V
sipush 20810
sipush 1944
invokestatic OS/Memory.poke(II)V
sipush 20811
sipush 448
invokestatic OS/Memory.poke(II)V
sipush 20812
sipush 4096
invokestatic OS/Memory.poke(II)V
sipush 20813
sipush 32704
invokestatic OS/Memory.poke(II)V
sipush 20814
sipush 1032
invokestatic OS/Memory.poke(II)V
sipush 20815
sipush 16256
invokestatic OS/Memory.poke(II)V
sipush 20816
sipush 16384
sipush 16384
iadd
invokestatic OS/Memory.poke(II)V
sipush 20817
sipush 8065
invokestatic OS/Memory.poke(II)V
sipush 20818
sipush 28512
ineg
invokestatic OS/Memory.poke(II)V
sipush 20819
sipush 3353
invokestatic OS/Memory.poke(II)V
sipush 20820
sipush 16502
invokestatic OS/Memory.poke(II)V
sipush 20821
sipush 32756
ineg
invokestatic OS/Memory.poke(II)V
sipush 20822
iconst_3
invokestatic OS/Memory.poke(II)V
sipush 20842
sipush 3856
invokestatic OS/Memory.poke(II)V
sipush 20843
sipush 384
invokestatic OS/Memory.poke(II)V
sipush 20844
sipush 4096
invokestatic OS/Memory.poke(II)V
sipush 20845
bipush 64
ineg
invokestatic OS/Memory.poke(II)V
sipush 20846
sipush 1035
invokestatic OS/Memory.poke(II)V
sipush 20847
sipush 32704
invokestatic OS/Memory.poke(II)V
sipush 20848
sipush 16384
ineg
invokestatic OS/Memory.poke(II)V
sipush 20849
sipush 1923
invokestatic OS/Memory.poke(II)V
sipush 20850
sipush 4992
invokestatic OS/Memory.poke(II)V
sipush 20851
sipush 2457
invokestatic OS/Memory.poke(II)V
sipush 20852
sipush 16218
ineg
invokestatic OS/Memory.poke(II)V
sipush 20853
sipush 32744
ineg
invokestatic OS/Memory.poke(II)V
sipush 20854
iconst_3
invokestatic OS/Memory.poke(II)V
sipush 20874
sipush 4080
invokestatic OS/Memory.poke(II)V
sipush 20875
sipush 896
invokestatic OS/Memory.poke(II)V
sipush 20876
sipush 28672
ineg
invokestatic OS/Memory.poke(II)V
sipush 20877
sipush 4032
invokestatic OS/Memory.poke(II)V
sipush 20878
sipush 1032
invokestatic OS/Memory.poke(II)V
sipush 20879
sipush 3136
ineg
invokestatic OS/Memory.poke(II)V
sipush 20880
sipush 4095
ineg
invokestatic OS/Memory.poke(II)V
sipush 20881
sipush 7047
invokestatic OS/Memory.poke(II)V
sipush 20882
sipush 16320
invokestatic OS/Memory.poke(II)V
sipush 20883
sipush 6297
invokestatic OS/Memory.poke(II)V
sipush 20884
sipush 32474
ineg
invokestatic OS/Memory.poke(II)V
sipush 20885
bipush 24
invokestatic OS/Memory.poke(II)V
sipush 20886
iconst_3
invokestatic OS/Memory.poke(II)V
sipush 20906
sipush 29696
ineg
invokestatic OS/Memory.poke(II)V
sipush 20907
sipush 1795
invokestatic OS/Memory.poke(II)V
sipush 20908
sipush 28672
ineg
invokestatic OS/Memory.poke(II)V
sipush 20909
sipush 1986
invokestatic OS/Memory.poke(II)V
sipush 20910
sipush 1030
invokestatic OS/Memory.poke(II)V
sipush 20911
sipush 7568
ineg
invokestatic OS/Memory.poke(II)V
sipush 20912
sipush 1023
ineg
invokestatic OS/Memory.poke(II)V
sipush 20913
sipush 3855
invokestatic OS/Memory.poke(II)V
sipush 20914
sipush 17216
ineg
invokestatic OS/Memory.poke(II)V
sipush 20915
sipush 4249
invokestatic OS/Memory.poke(II)V
sipush 20916
sipush 32442
ineg
invokestatic OS/Memory.poke(II)V
sipush 20917
bipush 16
invokestatic OS/Memory.poke(II)V
sipush 20918
iconst_3
invokestatic OS/Memory.poke(II)V
sipush 20938
sipush 2048
ineg
invokestatic OS/Memory.poke(II)V
sipush 20939
sipush 3871
invokestatic OS/Memory.poke(II)V
sipush 20940
sipush 20480
ineg
invokestatic OS/Memory.poke(II)V
sipush 20941
sipush 16342
invokestatic OS/Memory.poke(II)V
sipush 20942
sipush 15362
invokestatic OS/Memory.poke(II)V
sipush 20943
sipush 16369
ineg
invokestatic OS/Memory.poke(II)V
sipush 20944
iconst_3
invokestatic OS/Memory.poke(II)V
sipush 20945
sipush 3855
invokestatic OS/Memory.poke(II)V
sipush 20946
sipush 12736
invokestatic OS/Memory.poke(II)V
sipush 20947
sipush 4315
invokestatic OS/Memory.poke(II)V
sipush 20948
sipush 32186
ineg
invokestatic OS/Memory.poke(II)V
sipush 20949
bipush 49
invokestatic OS/Memory.poke(II)V
sipush 20950
iconst_2
invokestatic OS/Memory.poke(II)V
sipush 20970
sipush 4096
ineg
invokestatic OS/Memory.poke(II)V
sipush 20971
sipush 7939
invokestatic OS/Memory.poke(II)V
sipush 20972
sipush 4096
ineg
invokestatic OS/Memory.poke(II)V
sipush 20973
bipush 35
ineg
invokestatic OS/Memory.poke(II)V
sipush 20974
sipush 2241
ineg
invokestatic OS/Memory.poke(II)V
sipush 20975
sipush 16384
ineg
invokestatic OS/Memory.poke(II)V
sipush 20976
iconst_3
invokestatic OS/Memory.poke(II)V
sipush 20977
sipush 7692
invokestatic OS/Memory.poke(II)V
sipush 20978
sipush 256
invokestatic OS/Memory.poke(II)V
sipush 20979
sipush 4187
invokestatic OS/Memory.poke(II)V
sipush 20980
sipush 1732
invokestatic OS/Memory.poke(II)V
sipush 20981
bipush 33
invokestatic OS/Memory.poke(II)V
sipush 20982
iconst_2
invokestatic OS/Memory.poke(II)V
sipush 21002
sipush 4096
ineg
invokestatic OS/Memory.poke(II)V
sipush 21003
sipush 30471
invokestatic OS/Memory.poke(II)V
sipush 21004
sipush 4096
invokestatic OS/Memory.poke(II)V
sipush 21005
sipush 128
ineg
invokestatic OS/Memory.poke(II)V
sipush 21006
sipush 8191
invokestatic OS/Memory.poke(II)V
sipush 21007
sipush 16384
ineg
invokestatic OS/Memory.poke(II)V
sipush 21008
bipush 6
invokestatic OS/Memory.poke(II)V
sipush 21009
sipush 7183
invokestatic OS/Memory.poke(II)V
sipush 21010
sipush 896
invokestatic OS/Memory.poke(II)V
sipush 21011
sipush 12377
invokestatic OS/Memory.poke(II)V
sipush 21012
sipush 3276
invokestatic OS/Memory.poke(II)V
sipush 21013
bipush 33
invokestatic OS/Memory.poke(II)V
sipush 21014
iconst_4
invokestatic OS/Memory.poke(II)V
sipush 21034
sipush 8192
ineg
invokestatic OS/Memory.poke(II)V
sipush 21035
sipush 12017
ineg
invokestatic OS/Memory.poke(II)V
sipush 21036
sipush 6147
invokestatic OS/Memory.poke(II)V
sipush 21037
sipush 7936
invokestatic OS/Memory.poke(II)V
sipush 21038
sipush 16392
invokestatic OS/Memory.poke(II)V
sipush 21040
sipush 16378
ineg
invokestatic OS/Memory.poke(II)V
sipush 21041
sipush 14351
invokestatic OS/Memory.poke(II)V
sipush 21042
sipush 1792
invokestatic OS/Memory.poke(II)V
sipush 21043
sipush 8265
invokestatic OS/Memory.poke(II)V
sipush 21044
sipush 2188
invokestatic OS/Memory.poke(II)V
sipush 21045
bipush 34
invokestatic OS/Memory.poke(II)V
sipush 21066
sipush 8192
ineg
invokestatic OS/Memory.poke(II)V
sipush 21067
sipush 24577
invokestatic OS/Memory.poke(II)V
sipush 21068
sipush 6159
invokestatic OS/Memory.poke(II)V
sipush 21069
sipush 32640
invokestatic OS/Memory.poke(II)V
sipush 21070
sipush 460
invokestatic OS/Memory.poke(II)V
sipush 21072
sipush 16369
ineg
invokestatic OS/Memory.poke(II)V
sipush 21073
sipush 4081
ineg
invokestatic OS/Memory.poke(II)V
sipush 21074
sipush 1024
invokestatic OS/Memory.poke(II)V
sipush 21075
sipush 8265
invokestatic OS/Memory.poke(II)V
sipush 21076
sipush 6284
invokestatic OS/Memory.poke(II)V
sipush 21077
bipush 66
invokestatic OS/Memory.poke(II)V
sipush 21098
sipush 16384
sipush 16384
iadd
invokestatic OS/Memory.poke(II)V
sipush 21099
sipush 24577
invokestatic OS/Memory.poke(II)V
sipush 21100
sipush 6171
invokestatic OS/Memory.poke(II)V
sipush 21101
sipush 128
ineg
invokestatic OS/Memory.poke(II)V
sipush 21102
bipush 8
invokestatic OS/Memory.poke(II)V
sipush 21104
bipush 62
invokestatic OS/Memory.poke(II)V
sipush 21105
sipush 8181
ineg
invokestatic OS/Memory.poke(II)V
sipush 21106
sipush 1024
invokestatic OS/Memory.poke(II)V
sipush 21107
sipush 24653
invokestatic OS/Memory.poke(II)V
sipush 21108
sipush 12428
invokestatic OS/Memory.poke(II)V
sipush 21109
bipush 70
invokestatic OS/Memory.poke(II)V
sipush 21131
sipush 32765
ineg
invokestatic OS/Memory.poke(II)V
sipush 21132
sipush 31934
invokestatic OS/Memory.poke(II)V
sipush 21133
sipush 128
ineg
invokestatic OS/Memory.poke(II)V
sipush 21134
sipush 1033
invokestatic OS/Memory.poke(II)V
sipush 21136
bipush 126
invokestatic OS/Memory.poke(II)V
sipush 21137
sipush 16372
ineg
invokestatic OS/Memory.poke(II)V
sipush 21138
sipush 3073
invokestatic OS/Memory.poke(II)V
sipush 21139
sipush 16431
invokestatic OS/Memory.poke(II)V
sipush 21140
sipush 8588
invokestatic OS/Memory.poke(II)V
sipush 21141
bipush 68
invokestatic OS/Memory.poke(II)V
sipush 21163
sipush 32754
ineg
invokestatic OS/Memory.poke(II)V
sipush 21164
sipush 24172
invokestatic OS/Memory.poke(II)V
sipush 21165
sipush 128
ineg
invokestatic OS/Memory.poke(II)V
sipush 21166
sipush 1151
invokestatic OS/Memory.poke(II)V
sipush 21168
sipush 254
invokestatic OS/Memory.poke(II)V
sipush 21169
sipush 32753
ineg
invokestatic OS/Memory.poke(II)V
sipush 21170
sipush 2048
invokestatic OS/Memory.poke(II)V
sipush 21171
sipush 16425
invokestatic OS/Memory.poke(II)V
sipush 21172
sipush 24844
invokestatic OS/Memory.poke(II)V
sipush 21173
bipush 76
invokestatic OS/Memory.poke(II)V
sipush 21195
sipush 32708
ineg
invokestatic OS/Memory.poke(II)V
sipush 21196
sipush 32760
invokestatic OS/Memory.poke(II)V
sipush 21197
sipush 32512
invokestatic OS/Memory.poke(II)V
sipush 21198
sipush 1136
invokestatic OS/Memory.poke(II)V
sipush 21200
sipush 170
invokestatic OS/Memory.poke(II)V
sipush 21201
bipush 15
invokestatic OS/Memory.poke(II)V
sipush 21202
sipush 2049
invokestatic OS/Memory.poke(II)V
sipush 21203
sipush 16429
invokestatic OS/Memory.poke(II)V
sipush 21204
sipush 16652
invokestatic OS/Memory.poke(II)V
sipush 21205
bipush 72
invokestatic OS/Memory.poke(II)V
sipush 21227
bipush 24
invokestatic OS/Memory.poke(II)V
sipush 21228
sipush 16296
invokestatic OS/Memory.poke(II)V
sipush 21229
sipush 7680
invokestatic OS/Memory.poke(II)V
sipush 21230
bipush 15
invokestatic OS/Memory.poke(II)V
sipush 21231
sipush 16384
sipush 16384
iadd
invokestatic OS/Memory.poke(II)V
sipush 21232
sipush 437
invokestatic OS/Memory.poke(II)V
sipush 21233
bipush 8
invokestatic OS/Memory.poke(II)V
sipush 21234
sipush 2051
invokestatic OS/Memory.poke(II)V
sipush 21235
sipush 16323
ineg
invokestatic OS/Memory.poke(II)V
sipush 21236
sipush 32504
ineg
invokestatic OS/Memory.poke(II)V
sipush 21237
sipush 136
invokestatic OS/Memory.poke(II)V
sipush 21259
bipush 112
invokestatic OS/Memory.poke(II)V
sipush 21260
sipush 16168
invokestatic OS/Memory.poke(II)V
sipush 21261
sipush 512
ineg
invokestatic OS/Memory.poke(II)V
sipush 21262
iconst_3
invokestatic OS/Memory.poke(II)V
sipush 21263
sipush 16384
sipush 16384
iadd
invokestatic OS/Memory.poke(II)V
sipush 21264
sipush 304
invokestatic OS/Memory.poke(II)V
sipush 21265
bipush 8
invokestatic OS/Memory.poke(II)V
sipush 21266
sipush 2050
invokestatic OS/Memory.poke(II)V
sipush 21267
sipush 32715
ineg
invokestatic OS/Memory.poke(II)V
sipush 21268
sipush 32504
ineg
invokestatic OS/Memory.poke(II)V
sipush 21269
sipush 153
invokestatic OS/Memory.poke(II)V
sipush 21291
sipush 192
invokestatic OS/Memory.poke(II)V
sipush 21292
sipush 3872
invokestatic OS/Memory.poke(II)V
sipush 21293
sipush 3584
invokestatic OS/Memory.poke(II)V
sipush 21294
bipush 60
invokestatic OS/Memory.poke(II)V
sipush 21295
sipush 24704
invokestatic OS/Memory.poke(II)V
sipush 21296
sipush 768
invokestatic OS/Memory.poke(II)V
sipush 21297
bipush 12
invokestatic OS/Memory.poke(II)V
sipush 21298
sipush 2054
invokestatic OS/Memory.poke(II)V
sipush 21299
sipush 32713
ineg
invokestatic OS/Memory.poke(II)V
sipush 21300
sipush 264
invokestatic OS/Memory.poke(II)V
sipush 21301
sipush 145
invokestatic OS/Memory.poke(II)V
sipush 21323
sipush 128
invokestatic OS/Memory.poke(II)V
sipush 21324
sipush 29152
ineg
invokestatic OS/Memory.poke(II)V
sipush 21325
sipush 512
ineg
invokestatic OS/Memory.poke(II)V
sipush 21326
sipush 1025
invokestatic OS/Memory.poke(II)V
sipush 21327
sipush 12288
invokestatic OS/Memory.poke(II)V
sipush 21328
sipush 768
invokestatic OS/Memory.poke(II)V
sipush 21329
bipush 62
invokestatic OS/Memory.poke(II)V
sipush 21330
sipush 2054
invokestatic OS/Memory.poke(II)V
sipush 21331
sipush 32713
ineg
invokestatic OS/Memory.poke(II)V
sipush 21332
sipush 264
invokestatic OS/Memory.poke(II)V
sipush 21333
sipush 179
invokestatic OS/Memory.poke(II)V
sipush 21355
sipush 384
invokestatic OS/Memory.poke(II)V
sipush 21356
sipush 29696
ineg
invokestatic OS/Memory.poke(II)V
sipush 21357
sipush 506
ineg
invokestatic OS/Memory.poke(II)V
sipush 21358
sipush 1565
invokestatic OS/Memory.poke(II)V
sipush 21359
sipush 6144
invokestatic OS/Memory.poke(II)V
sipush 21360
sipush 896
invokestatic OS/Memory.poke(II)V
sipush 21361
sipush 252
invokestatic OS/Memory.poke(II)V
sipush 21362
sipush 2054
invokestatic OS/Memory.poke(II)V
sipush 21363
sipush 32713
ineg
invokestatic OS/Memory.poke(II)V
sipush 21364
sipush 264
invokestatic OS/Memory.poke(II)V
sipush 21365
sipush 162
invokestatic OS/Memory.poke(II)V
sipush 21387
sipush 768
invokestatic OS/Memory.poke(II)V
sipush 21388
sipush 29696
ineg
invokestatic OS/Memory.poke(II)V
sipush 21389
sipush 4605
ineg
invokestatic OS/Memory.poke(II)V
sipush 21390
sipush 769
invokestatic OS/Memory.poke(II)V
sipush 21391
sipush 1056
invokestatic OS/Memory.poke(II)V
sipush 21392
sipush 1920
invokestatic OS/Memory.poke(II)V
sipush 21393
sipush 2044
invokestatic OS/Memory.poke(II)V
sipush 21394
sipush 30714
ineg
invokestatic OS/Memory.poke(II)V
sipush 21395
sipush 32737
ineg
invokestatic OS/Memory.poke(II)V
sipush 21396
sipush 264
invokestatic OS/Memory.poke(II)V
sipush 21397
sipush 164
invokestatic OS/Memory.poke(II)V
sipush 21419
sipush 768
invokestatic OS/Memory.poke(II)V
sipush 21420
sipush 2048
invokestatic OS/Memory.poke(II)V
sipush 21421
sipush 256
ineg
invokestatic OS/Memory.poke(II)V
sipush 21422
sipush 32521
ineg
invokestatic OS/Memory.poke(II)V
sipush 21423
sipush 768
invokestatic OS/Memory.poke(II)V
sipush 21424
sipush 1920
invokestatic OS/Memory.poke(II)V
sipush 21425
sipush 28668
invokestatic OS/Memory.poke(II)V
sipush 21426
sipush 30714
ineg
invokestatic OS/Memory.poke(II)V
sipush 21427
sipush 32737
ineg
invokestatic OS/Memory.poke(II)V
sipush 21428
sipush 520
invokestatic OS/Memory.poke(II)V
sipush 21429
sipush 484
invokestatic OS/Memory.poke(II)V
sipush 21451
sipush 1536
invokestatic OS/Memory.poke(II)V
sipush 21452
sipush 2048
invokestatic OS/Memory.poke(II)V
sipush 21453
bipush 124
ineg
invokestatic OS/Memory.poke(II)V
sipush 21454
sipush 26879
invokestatic OS/Memory.poke(II)V
sipush 21455
sipush 192
invokestatic OS/Memory.poke(II)V
sipush 21456
sipush 3072
invokestatic OS/Memory.poke(II)V
sipush 21457
bipush 36
ineg
invokestatic OS/Memory.poke(II)V
sipush 21458
sipush 30714
ineg
invokestatic OS/Memory.poke(II)V
sipush 21459
sipush 32737
ineg
invokestatic OS/Memory.poke(II)V
sipush 21460
sipush 793
invokestatic OS/Memory.poke(II)V
sipush 21461
sipush 328
invokestatic OS/Memory.poke(II)V
sipush 21483
sipush 1536
invokestatic OS/Memory.poke(II)V
sipush 21485
sipush 8070
invokestatic OS/Memory.poke(II)V
sipush 21486
bipush 31
invokestatic OS/Memory.poke(II)V
sipush 21487
bipush 51
invokestatic OS/Memory.poke(II)V
sipush 21488
sipush 7168
invokestatic OS/Memory.poke(II)V
sipush 21489
sipush 28788
ineg
invokestatic OS/Memory.poke(II)V
sipush 21490
sipush 30713
ineg
invokestatic OS/Memory.poke(II)V
sipush 21491
bipush 15
invokestatic OS/Memory.poke(II)V
sipush 21492
sipush 793
invokestatic OS/Memory.poke(II)V
sipush 21493
sipush 328
invokestatic OS/Memory.poke(II)V
sipush 21515
sipush 1024
invokestatic OS/Memory.poke(II)V
sipush 21517
bipush 106
ineg
invokestatic OS/Memory.poke(II)V
sipush 21518
sipush 2017
ineg
invokestatic OS/Memory.poke(II)V
sipush 21519
bipush 31
invokestatic OS/Memory.poke(II)V
sipush 21520
sipush 7168
invokestatic OS/Memory.poke(II)V
sipush 21521
sipush 236
invokestatic OS/Memory.poke(II)V
sipush 21522
sipush 29690
ineg
invokestatic OS/Memory.poke(II)V
sipush 21523
bipush 15
invokestatic OS/Memory.poke(II)V
sipush 21524
sipush 793
invokestatic OS/Memory.poke(II)V
sipush 21525
sipush 392
invokestatic OS/Memory.poke(II)V
sipush 21547
sipush 3072
invokestatic OS/Memory.poke(II)V
sipush 21549
sipush 22640
ineg
invokestatic OS/Memory.poke(II)V
sipush 21550
sipush 2289
ineg
invokestatic OS/Memory.poke(II)V
sipush 21551
iconst_3
invokestatic OS/Memory.poke(II)V
sipush 21552
sipush 15360
invokestatic OS/Memory.poke(II)V
sipush 21553
bipush 52
invokestatic OS/Memory.poke(II)V
sipush 21554
sipush 29684
ineg
invokestatic OS/Memory.poke(II)V
sipush 21555
bipush 7
invokestatic OS/Memory.poke(II)V
sipush 21556
sipush 537
invokestatic OS/Memory.poke(II)V
sipush 21557
sipush 400
invokestatic OS/Memory.poke(II)V
sipush 21579
sipush 2048
invokestatic OS/Memory.poke(II)V
sipush 21581
sipush 7232
ineg
invokestatic OS/Memory.poke(II)V
sipush 21582
sipush 32759
invokestatic OS/Memory.poke(II)V
sipush 21584
sipush 14336
invokestatic OS/Memory.poke(II)V
sipush 21585
sipush 4048
invokestatic OS/Memory.poke(II)V
sipush 21586
sipush 31744
ineg
invokestatic OS/Memory.poke(II)V
sipush 21587
iconst_3
invokestatic OS/Memory.poke(II)V
sipush 21588
sipush 537
invokestatic OS/Memory.poke(II)V
sipush 21589
sipush 912
invokestatic OS/Memory.poke(II)V
sipush 21611
sipush 6144
invokestatic OS/Memory.poke(II)V
sipush 21613
sipush 15424
ineg
invokestatic OS/Memory.poke(II)V
sipush 21614
sipush 8191
invokestatic OS/Memory.poke(II)V
sipush 21616
sipush 15360
invokestatic OS/Memory.poke(II)V
sipush 21617
sipush 12144
invokestatic OS/Memory.poke(II)V
sipush 21618
sipush 31232
ineg
invokestatic OS/Memory.poke(II)V
sipush 21619
iconst_3
invokestatic OS/Memory.poke(II)V
sipush 21620
sipush 538
invokestatic OS/Memory.poke(II)V
sipush 21621
sipush 816
invokestatic OS/Memory.poke(II)V
sipush 21643
sipush 12288
invokestatic OS/Memory.poke(II)V
sipush 21645
sipush 15904
ineg
invokestatic OS/Memory.poke(II)V
sipush 21646
sipush 1039
invokestatic OS/Memory.poke(II)V
sipush 21648
sipush 15872
invokestatic OS/Memory.poke(II)V
sipush 21649
sipush 32752
invokestatic OS/Memory.poke(II)V
sipush 21650
sipush 15616
ineg
invokestatic OS/Memory.poke(II)V
sipush 21651
iconst_1
invokestatic OS/Memory.poke(II)V
sipush 21652
sipush 538
invokestatic OS/Memory.poke(II)V
sipush 21653
sipush 800
invokestatic OS/Memory.poke(II)V
sipush 21675
sipush 28672
invokestatic OS/Memory.poke(II)V
sipush 21677
sipush 32288
ineg
invokestatic OS/Memory.poke(II)V
sipush 21678
sipush 1551
invokestatic OS/Memory.poke(II)V
sipush 21680
sipush 11776
invokestatic OS/Memory.poke(II)V
sipush 21681
sipush 128
ineg
invokestatic OS/Memory.poke(II)V
sipush 21682
sipush 16000
ineg
invokestatic OS/Memory.poke(II)V
sipush 21684
sipush 794
invokestatic OS/Memory.poke(II)V
sipush 21685
sipush 864
invokestatic OS/Memory.poke(II)V
sipush 21707
sipush 16384
ineg
invokestatic OS/Memory.poke(II)V
sipush 21708
iconst_1
invokestatic OS/Memory.poke(II)V
sipush 21709
sipush 224
invokestatic OS/Memory.poke(II)V
sipush 21710
sipush 7167
invokestatic OS/Memory.poke(II)V
sipush 21712
sipush 10112
invokestatic OS/Memory.poke(II)V
sipush 21713
sipush 16352
invokestatic OS/Memory.poke(II)V
sipush 21714
sipush 16528
invokestatic OS/Memory.poke(II)V
sipush 21716
sipush 274
invokestatic OS/Memory.poke(II)V
sipush 21717
sipush 832
invokestatic OS/Memory.poke(II)V
sipush 21739
sipush 16384
sipush 16384
iadd
invokestatic OS/Memory.poke(II)V
sipush 21740
bipush 7
invokestatic OS/Memory.poke(II)V
sipush 21741
sipush 240
invokestatic OS/Memory.poke(II)V
sipush 21742
sipush 4578
ineg
invokestatic OS/Memory.poke(II)V
sipush 21744
sipush 8704
invokestatic OS/Memory.poke(II)V
sipush 21745
sipush 8224
ineg
invokestatic OS/Memory.poke(II)V
sipush 21746
bipush 112
invokestatic OS/Memory.poke(II)V
sipush 21748
sipush 274
invokestatic OS/Memory.poke(II)V
sipush 21749
sipush 1600
invokestatic OS/Memory.poke(II)V
sipush 21771
sipush 16384
ineg
invokestatic OS/Memory.poke(II)V
sipush 21772
iconst_3
invokestatic OS/Memory.poke(II)V
sipush 21773
bipush 112
invokestatic OS/Memory.poke(II)V
sipush 21774
sipush 3076
ineg
invokestatic OS/Memory.poke(II)V
sipush 21775
iconst_3
invokestatic OS/Memory.poke(II)V
sipush 21776
sipush 12688
invokestatic OS/Memory.poke(II)V
sipush 21777
sipush 24160
invokestatic OS/Memory.poke(II)V
sipush 21778
bipush 112
invokestatic OS/Memory.poke(II)V
sipush 21780
sipush 406
invokestatic OS/Memory.poke(II)V
sipush 21781
sipush 1728
invokestatic OS/Memory.poke(II)V
sipush 21803
sipush 16384
ineg
invokestatic OS/Memory.poke(II)V
sipush 21804
bipush 15
invokestatic OS/Memory.poke(II)V
sipush 21805
bipush 60
invokestatic OS/Memory.poke(II)V
sipush 21806
sipush 16392
ineg
invokestatic OS/Memory.poke(II)V
sipush 21807
bipush 24
invokestatic OS/Memory.poke(II)V
sipush 21808
sipush 6348
invokestatic OS/Memory.poke(II)V
sipush 21809
sipush 24256
invokestatic OS/Memory.poke(II)V
sipush 21810
bipush 48
invokestatic OS/Memory.poke(II)V
sipush 21812
sipush 404
invokestatic OS/Memory.poke(II)V
sipush 21813
sipush 1920
invokestatic OS/Memory.poke(II)V
sipush 21835
sipush 16384
sipush 16384
iadd
invokestatic OS/Memory.poke(II)V
sipush 21836
sipush 4095
invokestatic OS/Memory.poke(II)V
sipush 21837
bipush 28
invokestatic OS/Memory.poke(II)V
sipush 21838
bipush 16
ineg
invokestatic OS/Memory.poke(II)V
sipush 21839
iconst_5
invokestatic OS/Memory.poke(II)V
sipush 21840
sipush 3168
invokestatic OS/Memory.poke(II)V
sipush 21841
sipush 29056
invokestatic OS/Memory.poke(II)V
sipush 21842
bipush 33
invokestatic OS/Memory.poke(II)V
sipush 21844
sipush 404
invokestatic OS/Memory.poke(II)V
sipush 21845
sipush 1920
invokestatic OS/Memory.poke(II)V
sipush 21867
sipush 16384
sipush 16384
iadd
invokestatic OS/Memory.poke(II)V
sipush 21868
sipush 8191
invokestatic OS/Memory.poke(II)V
sipush 21869
bipush 15
invokestatic OS/Memory.poke(II)V
sipush 21870
sipush 1056
ineg
invokestatic OS/Memory.poke(II)V
sipush 21871
sipush 499
invokestatic OS/Memory.poke(II)V
sipush 21872
sipush 13336
invokestatic OS/Memory.poke(II)V
sipush 21873
bipush 8
ineg
invokestatic OS/Memory.poke(II)V
sipush 21874
bipush 15
ineg
invokestatic OS/Memory.poke(II)V
sipush 21876
sipush 404
invokestatic OS/Memory.poke(II)V
sipush 21877
sipush 1792
invokestatic OS/Memory.poke(II)V
sipush 21900
sipush 15287
invokestatic OS/Memory.poke(II)V
sipush 21901
iconst_1
invokestatic OS/Memory.poke(II)V
sipush 21902
sipush 384
ineg
invokestatic OS/Memory.poke(II)V
sipush 21903
sipush 32760
invokestatic OS/Memory.poke(II)V
sipush 21904
sipush 5127
invokestatic OS/Memory.poke(II)V
sipush 21905
sipush 16464
ineg
invokestatic OS/Memory.poke(II)V
sipush 21906
bipush 32
ineg
invokestatic OS/Memory.poke(II)V
sipush 21907
iconst_3
invokestatic OS/Memory.poke(II)V
sipush 21908
sipush 404
invokestatic OS/Memory.poke(II)V
sipush 21909
sipush 1792
invokestatic OS/Memory.poke(II)V
sipush 21932
sipush 22654
ineg
invokestatic OS/Memory.poke(II)V
sipush 21934
sipush 512
ineg
invokestatic OS/Memory.poke(II)V
sipush 21935
iconst_1
ineg
invokestatic OS/Memory.poke(II)V
sipush 21936
sipush 1536
invokestatic OS/Memory.poke(II)V
sipush 21937
sipush 28576
ineg
invokestatic OS/Memory.poke(II)V
sipush 21938
sipush 15852
invokestatic OS/Memory.poke(II)V
sipush 21939
bipush 7
invokestatic OS/Memory.poke(II)V
sipush 21940
sipush 412
invokestatic OS/Memory.poke(II)V
sipush 21941
sipush 3840
invokestatic OS/Memory.poke(II)V
sipush 21964
sipush 7412
ineg
invokestatic OS/Memory.poke(II)V
sipush 21966
sipush 2048
ineg
invokestatic OS/Memory.poke(II)V
sipush 21967
sipush 2047
invokestatic OS/Memory.poke(II)V
sipush 21968
sipush 512
invokestatic OS/Memory.poke(II)V
sipush 21969
sipush 32704
invokestatic OS/Memory.poke(II)V
sipush 21970
sipush 28662
invokestatic OS/Memory.poke(II)V
sipush 21971
bipush 15
invokestatic OS/Memory.poke(II)V
sipush 21972
sipush 216
invokestatic OS/Memory.poke(II)V
sipush 21973
sipush 3840
invokestatic OS/Memory.poke(II)V
sipush 21996
sipush 1560
invokestatic OS/Memory.poke(II)V
sipush 21998
sipush 8192
ineg
invokestatic OS/Memory.poke(II)V
sipush 21999
iconst_1
invokestatic OS/Memory.poke(II)V
sipush 22000
sipush 512
invokestatic OS/Memory.poke(II)V
sipush 22001
sipush 2048
invokestatic OS/Memory.poke(II)V
sipush 22002
sipush 19251
invokestatic OS/Memory.poke(II)V
sipush 22003
bipush 12
invokestatic OS/Memory.poke(II)V
sipush 22004
sipush 248
invokestatic OS/Memory.poke(II)V
sipush 22005
sipush 3584
invokestatic OS/Memory.poke(II)V
sipush 22028
sipush 3184
invokestatic OS/Memory.poke(II)V
sipush 22030
sipush 16384
sipush 16384
iadd
invokestatic OS/Memory.poke(II)V
sipush 22031
bipush 31
invokestatic OS/Memory.poke(II)V
sipush 22032
sipush 768
invokestatic OS/Memory.poke(II)V
sipush 22033
sipush 29184
ineg
invokestatic OS/Memory.poke(II)V
sipush 22034
sipush 20025
invokestatic OS/Memory.poke(II)V
sipush 22035
bipush 60
invokestatic OS/Memory.poke(II)V
sipush 22036
bipush 120
invokestatic OS/Memory.poke(II)V
sipush 22037
sipush 3072
invokestatic OS/Memory.poke(II)V
sipush 22060
sipush 3008
invokestatic OS/Memory.poke(II)V
sipush 22063
sipush 254
invokestatic OS/Memory.poke(II)V
sipush 22064
sipush 384
invokestatic OS/Memory.poke(II)V
sipush 22065
sipush 7424
ineg
invokestatic OS/Memory.poke(II)V
sipush 22066
sipush 30657
ineg
invokestatic OS/Memory.poke(II)V
sipush 22067
bipush 60
invokestatic OS/Memory.poke(II)V
sipush 22068
bipush 120
invokestatic OS/Memory.poke(II)V
sipush 22069
sipush 3072
invokestatic OS/Memory.poke(II)V
sipush 22092
sipush 7680
invokestatic OS/Memory.poke(II)V
sipush 22095
sipush 8048
invokestatic OS/Memory.poke(II)V
sipush 22096
sipush 192
invokestatic OS/Memory.poke(II)V
sipush 22097
bipush 64
ineg
invokestatic OS/Memory.poke(II)V
sipush 22098
sipush 32705
ineg
invokestatic OS/Memory.poke(II)V
sipush 22099
bipush 60
invokestatic OS/Memory.poke(II)V
sipush 22100
bipush 120
invokestatic OS/Memory.poke(II)V
sipush 22101
sipush 3072
invokestatic OS/Memory.poke(II)V
sipush 22124
sipush 31744
invokestatic OS/Memory.poke(II)V
sipush 22127
sipush 4032
invokestatic OS/Memory.poke(II)V
sipush 22128
sipush 254
invokestatic OS/Memory.poke(II)V
sipush 22129
sipush 4096
ineg
invokestatic OS/Memory.poke(II)V
sipush 22130
bipush 63
invokestatic OS/Memory.poke(II)V
sipush 22131
bipush 62
invokestatic OS/Memory.poke(II)V
sipush 22132
bipush 120
invokestatic OS/Memory.poke(II)V
sipush 22133
sipush 2048
invokestatic OS/Memory.poke(II)V
sipush 22156
sipush 2048
ineg
invokestatic OS/Memory.poke(II)V
sipush 22159
sipush 3648
ineg
invokestatic OS/Memory.poke(II)V
sipush 22160
sipush 3711
invokestatic OS/Memory.poke(II)V
sipush 22161
bipush 64
ineg
invokestatic OS/Memory.poke(II)V
sipush 22162
bipush 6
invokestatic OS/Memory.poke(II)V
sipush 22163
bipush 91
invokestatic OS/Memory.poke(II)V
sipush 22164
bipush 48
invokestatic OS/Memory.poke(II)V
sipush 22165
sipush 2048
invokestatic OS/Memory.poke(II)V
sipush 22188
sipush 16384
sipush 16384
iadd
invokestatic OS/Memory.poke(II)V
sipush 22189
iconst_1
invokestatic OS/Memory.poke(II)V
sipush 22191
sipush 384
invokestatic OS/Memory.poke(II)V
sipush 22192
sipush 510
invokestatic OS/Memory.poke(II)V
sipush 22193
sipush 32256
invokestatic OS/Memory.poke(II)V
sipush 22195
bipush 121
invokestatic OS/Memory.poke(II)V
sipush 22196
bipush 56
invokestatic OS/Memory.poke(II)V
sipush 22197
sipush 2048
invokestatic OS/Memory.poke(II)V
sipush 22221
iconst_1
invokestatic OS/Memory.poke(II)V
sipush 22223
sipush 960
invokestatic OS/Memory.poke(II)V
sipush 22224
sipush 252
invokestatic OS/Memory.poke(II)V
sipush 22225
sipush 31104
invokestatic OS/Memory.poke(II)V
sipush 22227
sipush 492
invokestatic OS/Memory.poke(II)V
sipush 22228
bipush 56
invokestatic OS/Memory.poke(II)V
sipush 22255
sipush 2044
invokestatic OS/Memory.poke(II)V
sipush 22256
sipush 252
invokestatic OS/Memory.poke(II)V
sipush 22257
sipush 30720
invokestatic OS/Memory.poke(II)V
sipush 22259
sipush 428
invokestatic OS/Memory.poke(II)V
sipush 22260
bipush 56
invokestatic OS/Memory.poke(II)V
sipush 22287
sipush 2047
invokestatic OS/Memory.poke(II)V
sipush 22288
sipush 1758
invokestatic OS/Memory.poke(II)V
sipush 22289
sipush 15872
invokestatic OS/Memory.poke(II)V
sipush 22291
sipush 228
invokestatic OS/Memory.poke(II)V
sipush 22292
bipush 56
invokestatic OS/Memory.poke(II)V
sipush 22318
sipush 8192
ineg
invokestatic OS/Memory.poke(II)V
sipush 22319
sipush 24577
ineg
invokestatic OS/Memory.poke(II)V
sipush 22320
sipush 479
invokestatic OS/Memory.poke(II)V
sipush 22321
sipush 1024
ineg
invokestatic OS/Memory.poke(II)V
sipush 22322
sipush 1023
invokestatic OS/Memory.poke(II)V
sipush 22323
sipush 192
invokestatic OS/Memory.poke(II)V
sipush 22324
bipush 48
invokestatic OS/Memory.poke(II)V
sipush 22325
bipush 6
invokestatic OS/Memory.poke(II)V
sipush 22350
sipush 14336
invokestatic OS/Memory.poke(II)V
sipush 22351
sipush 16456
ineg
invokestatic OS/Memory.poke(II)V
sipush 22352
bipush 63
invokestatic OS/Memory.poke(II)V
sipush 22353
sipush 3584
invokestatic OS/Memory.poke(II)V
sipush 22354
sipush 896
invokestatic OS/Memory.poke(II)V
sipush 22355
sipush 224
invokestatic OS/Memory.poke(II)V
sipush 22356
bipush 16
invokestatic OS/Memory.poke(II)V
sipush 22357
bipush 60
invokestatic OS/Memory.poke(II)V
sipush 22382
sipush 24832
ineg
invokestatic OS/Memory.poke(II)V
sipush 22383
sipush 393
ineg
invokestatic OS/Memory.poke(II)V
sipush 22384
bipush 127
invokestatic OS/Memory.poke(II)V
sipush 22385
sipush 1792
invokestatic OS/Memory.poke(II)V
sipush 22386
sipush 3584
invokestatic OS/Memory.poke(II)V
sipush 22387
sipush 128
invokestatic OS/Memory.poke(II)V
sipush 22388
bipush 16
invokestatic OS/Memory.poke(II)V
sipush 22389
sipush 1020
invokestatic OS/Memory.poke(II)V
sipush 22414
sipush 32192
invokestatic OS/Memory.poke(II)V
sipush 22415
sipush 232
ineg
invokestatic OS/Memory.poke(II)V
sipush 22416
sipush 32673
ineg
invokestatic OS/Memory.poke(II)V
sipush 22417
sipush 1792
invokestatic OS/Memory.poke(II)V
sipush 22418
sipush 31744
invokestatic OS/Memory.poke(II)V
sipush 22419
sipush 128
invokestatic OS/Memory.poke(II)V
sipush 22420
bipush 16
invokestatic OS/Memory.poke(II)V
sipush 22421
sipush 32304
invokestatic OS/Memory.poke(II)V
sipush 22446
sipush 3952
invokestatic OS/Memory.poke(II)V
sipush 22447
bipush 50
ineg
invokestatic OS/Memory.poke(II)V
sipush 22448
sipush 32641
ineg
invokestatic OS/Memory.poke(II)V
sipush 22449
sipush 1536
invokestatic OS/Memory.poke(II)V
sipush 22450
sipush 14336
invokestatic OS/Memory.poke(II)V
sipush 22451
sipush 224
invokestatic OS/Memory.poke(II)V
sipush 22452
sipush 1024
ineg
invokestatic OS/Memory.poke(II)V
sipush 22453
sipush 29823
invokestatic OS/Memory.poke(II)V
sipush 22478
sipush 32290
ineg
invokestatic OS/Memory.poke(II)V
sipush 22479
sipush 697
ineg
invokestatic OS/Memory.poke(II)V
sipush 22480
sipush 28433
ineg
invokestatic OS/Memory.poke(II)V
sipush 22481
sipush 1920
invokestatic OS/Memory.poke(II)V
sipush 22482
sipush 4096
ineg
invokestatic OS/Memory.poke(II)V
sipush 22483
sipush 448
invokestatic OS/Memory.poke(II)V
sipush 22484
sipush 768
invokestatic OS/Memory.poke(II)V
sipush 22485
sipush 8184
ineg
invokestatic OS/Memory.poke(II)V
sipush 22510
bipush 14
invokestatic OS/Memory.poke(II)V
sipush 22511
sipush 7584
ineg
invokestatic OS/Memory.poke(II)V
sipush 22512
sipush 28545
ineg
invokestatic OS/Memory.poke(II)V
sipush 22513
sipush 896
invokestatic OS/Memory.poke(II)V
sipush 22514
sipush 28672
invokestatic OS/Memory.poke(II)V
sipush 22515
sipush 385
invokestatic OS/Memory.poke(II)V
sipush 22516
sipush 384
invokestatic OS/Memory.poke(II)V
sipush 22517
sipush 12288
invokestatic OS/Memory.poke(II)V
sipush 22542
bipush 7
invokestatic OS/Memory.poke(II)V
sipush 22543
sipush 3616
ineg
invokestatic OS/Memory.poke(II)V
sipush 22544
sipush 8255
invokestatic OS/Memory.poke(II)V
sipush 22545
sipush 768
invokestatic OS/Memory.poke(II)V
sipush 22546
sipush 4096
ineg
invokestatic OS/Memory.poke(II)V
sipush 22547
sipush 387
invokestatic OS/Memory.poke(II)V
sipush 22548
sipush 15488
invokestatic OS/Memory.poke(II)V
sipush 22549
sipush 6192
invokestatic OS/Memory.poke(II)V
sipush 22573
sipush 16384
sipush 16384
iadd
invokestatic OS/Memory.poke(II)V
sipush 22574
iconst_1
invokestatic OS/Memory.poke(II)V
sipush 22575
sipush 976
ineg
invokestatic OS/Memory.poke(II)V
sipush 22576
sipush 8065
ineg
invokestatic OS/Memory.poke(II)V
sipush 22577
sipush 384
invokestatic OS/Memory.poke(II)V
sipush 22578
sipush 24576
invokestatic OS/Memory.poke(II)V
sipush 22579
sipush 897
invokestatic OS/Memory.poke(II)V
sipush 22580
sipush 1920
ineg
invokestatic OS/Memory.poke(II)V
sipush 22581
sipush 3103
invokestatic OS/Memory.poke(II)V
sipush 22605
sipush 16384
ineg
invokestatic OS/Memory.poke(II)V
sipush 22607
sipush 15360
ineg
invokestatic OS/Memory.poke(II)V
sipush 22608
sipush 32513
ineg
invokestatic OS/Memory.poke(II)V
sipush 22609
sipush 385
invokestatic OS/Memory.poke(II)V
sipush 22610
sipush 8192
ineg
invokestatic OS/Memory.poke(II)V
sipush 22611
sipush 897
invokestatic OS/Memory.poke(II)V
sipush 22612
sipush 14464
invokestatic OS/Memory.poke(II)V
sipush 22613
sipush 1052
invokestatic OS/Memory.poke(II)V
sipush 22637
sipush 28672
invokestatic OS/Memory.poke(II)V
sipush 22638
iconst_4
invokestatic OS/Memory.poke(II)V
sipush 22639
sipush 13312
ineg
invokestatic OS/Memory.poke(II)V
sipush 22640
sipush 1151
invokestatic OS/Memory.poke(II)V
sipush 22641
sipush 192
invokestatic OS/Memory.poke(II)V
sipush 22642
sipush 16384
ineg
invokestatic OS/Memory.poke(II)V
sipush 22643
sipush 1667
invokestatic OS/Memory.poke(II)V
sipush 22644
sipush 6272
invokestatic OS/Memory.poke(II)V
sipush 22645
sipush 792
invokestatic OS/Memory.poke(II)V
sipush 22669
sipush 7168
invokestatic OS/Memory.poke(II)V
sipush 22670
bipush 6
invokestatic OS/Memory.poke(II)V
sipush 22671
sipush 7168
ineg
invokestatic OS/Memory.poke(II)V
sipush 22672
sipush 1663
invokestatic OS/Memory.poke(II)V
sipush 22673
bipush 96
invokestatic OS/Memory.poke(II)V
sipush 22674
sipush 8192
ineg
invokestatic OS/Memory.poke(II)V
sipush 22675
sipush 1167
invokestatic OS/Memory.poke(II)V
sipush 22676
sipush 6272
invokestatic OS/Memory.poke(II)V
sipush 22677
sipush 488
invokestatic OS/Memory.poke(II)V
sipush 22701
sipush 9728
invokestatic OS/Memory.poke(II)V
sipush 22702
iconst_3
invokestatic OS/Memory.poke(II)V
sipush 22703
sipush 8192
invokestatic OS/Memory.poke(II)V
sipush 22704
sipush 1791
invokestatic OS/Memory.poke(II)V
sipush 22705
sipush 480
invokestatic OS/Memory.poke(II)V
sipush 22706
sipush 16384
ineg
invokestatic OS/Memory.poke(II)V
sipush 22707
sipush 3215
invokestatic OS/Memory.poke(II)V
sipush 22708
sipush 6528
invokestatic OS/Memory.poke(II)V
sipush 22709
bipush 124
invokestatic OS/Memory.poke(II)V
sipush 22733
sipush 7936
ineg
invokestatic OS/Memory.poke(II)V
sipush 22734
sipush 193
invokestatic OS/Memory.poke(II)V
sipush 22735
sipush 14336
invokestatic OS/Memory.poke(II)V
sipush 22736
sipush 191
invokestatic OS/Memory.poke(II)V
sipush 22737
sipush 4080
invokestatic OS/Memory.poke(II)V
sipush 22738
sipush 16384
sipush 16384
iadd
invokestatic OS/Memory.poke(II)V
sipush 22739
sipush 2055
invokestatic OS/Memory.poke(II)V
sipush 22740
sipush 6400
invokestatic OS/Memory.poke(II)V
sipush 22741
bipush 28
invokestatic OS/Memory.poke(II)V
sipush 22765
sipush 2304
invokestatic OS/Memory.poke(II)V
sipush 22766
sipush 192
invokestatic OS/Memory.poke(II)V
sipush 22767
sipush 1024
ineg
invokestatic OS/Memory.poke(II)V
sipush 22768
sipush 385
invokestatic OS/Memory.poke(II)V
sipush 22769
sipush 16380
invokestatic OS/Memory.poke(II)V
sipush 22771
sipush 6151
invokestatic OS/Memory.poke(II)V
sipush 22772
sipush 12544
invokestatic OS/Memory.poke(II)V
sipush 22797
sipush 3840
invokestatic OS/Memory.poke(II)V
sipush 22799
sipush 128
ineg
invokestatic OS/Memory.poke(II)V
sipush 22800
sipush 768
invokestatic OS/Memory.poke(II)V
sipush 22801
bipush 116
ineg
invokestatic OS/Memory.poke(II)V
sipush 22802
iconst_3
invokestatic OS/Memory.poke(II)V
sipush 22803
sipush 4126
invokestatic OS/Memory.poke(II)V
sipush 22804
sipush 25344
invokestatic OS/Memory.poke(II)V
sipush 22829
sipush 30976
ineg
invokestatic OS/Memory.poke(II)V
sipush 22831
sipush 2046
invokestatic OS/Memory.poke(II)V
sipush 22832
sipush 512
invokestatic OS/Memory.poke(II)V
sipush 22833
sipush 9216
ineg
invokestatic OS/Memory.poke(II)V
sipush 22834
bipush 7
invokestatic OS/Memory.poke(II)V
sipush 22835
sipush 12414
invokestatic OS/Memory.poke(II)V
sipush 22836
sipush 14848
ineg
invokestatic OS/Memory.poke(II)V
sipush 22837
iconst_3
invokestatic OS/Memory.poke(II)V
sipush 22861
sipush 32512
ineg
invokestatic OS/Memory.poke(II)V
sipush 22862
sipush 2047
ineg
invokestatic OS/Memory.poke(II)V
sipush 22863
iconst_1
invokestatic OS/Memory.poke(II)V
sipush 22864
sipush 20992
invokestatic OS/Memory.poke(II)V
sipush 22865
sipush 11264
ineg
invokestatic OS/Memory.poke(II)V
sipush 22866
bipush 7
invokestatic OS/Memory.poke(II)V
sipush 22867
sipush 24696
invokestatic OS/Memory.poke(II)V
sipush 22868
sipush 7168
invokestatic OS/Memory.poke(II)V
sipush 22869
bipush 14
invokestatic OS/Memory.poke(II)V
sipush 22893
sipush 256
invokestatic OS/Memory.poke(II)V
sipush 22894
sipush 2047
invokestatic OS/Memory.poke(II)V
sipush 22896
sipush 29184
invokestatic OS/Memory.poke(II)V
sipush 22897
bipush 13
invokestatic OS/Memory.poke(II)V
sipush 22898
bipush 7
invokestatic OS/Memory.poke(II)V
sipush 22899
sipush 15376
ineg
invokestatic OS/Memory.poke(II)V
sipush 22900
sipush 12288
invokestatic OS/Memory.poke(II)V
sipush 22901
bipush 24
invokestatic OS/Memory.poke(II)V
sipush 22925
sipush 256
invokestatic OS/Memory.poke(II)V
sipush 22926
sipush 496
invokestatic OS/Memory.poke(II)V
sipush 22928
sipush 31232
ineg
invokestatic OS/Memory.poke(II)V
sipush 22929
sipush 32759
ineg
invokestatic OS/Memory.poke(II)V
sipush 22930
bipush 15
invokestatic OS/Memory.poke(II)V
sipush 22931
sipush 32576
ineg
invokestatic OS/Memory.poke(II)V
sipush 22932
sipush 24577
invokestatic OS/Memory.poke(II)V
sipush 22933
sipush 224
invokestatic OS/Memory.poke(II)V
sipush 22957
sipush 7424
invokestatic OS/Memory.poke(II)V
sipush 22958
sipush 1020
invokestatic OS/Memory.poke(II)V
sipush 22960
sipush 1024
invokestatic OS/Memory.poke(II)V
sipush 22961
sipush 16393
invokestatic OS/Memory.poke(II)V
sipush 22962
bipush 14
invokestatic OS/Memory.poke(II)V
sipush 22963
sipush 896
invokestatic OS/Memory.poke(II)V
sipush 22964
sipush 16381
ineg
invokestatic OS/Memory.poke(II)V
sipush 22965
sipush 960
invokestatic OS/Memory.poke(II)V
sipush 22989
sipush 7424
invokestatic OS/Memory.poke(II)V
sipush 22990
sipush 2008
invokestatic OS/Memory.poke(II)V
sipush 22992
sipush 1024
invokestatic OS/Memory.poke(II)V
sipush 22993
bipush 109
invokestatic OS/Memory.poke(II)V
sipush 22994
bipush 10
invokestatic OS/Memory.poke(II)V
sipush 22995
sipush 1792
invokestatic OS/Memory.poke(II)V
sipush 22996
sipush 32762
ineg
invokestatic OS/Memory.poke(II)V
sipush 22997
sipush 901
invokestatic OS/Memory.poke(II)V
sipush 23021
sipush 4864
invokestatic OS/Memory.poke(II)V
sipush 23022
sipush 2008
invokestatic OS/Memory.poke(II)V
sipush 23024
sipush 1024
invokestatic OS/Memory.poke(II)V
sipush 23025
bipush 76
invokestatic OS/Memory.poke(II)V
sipush 23026
bipush 10
invokestatic OS/Memory.poke(II)V
sipush 23027
sipush 3584
invokestatic OS/Memory.poke(II)V
sipush 23028
bipush 12
invokestatic OS/Memory.poke(II)V
sipush 23029
sipush 1951
invokestatic OS/Memory.poke(II)V
sipush 23053
sipush 3584
ineg
invokestatic OS/Memory.poke(II)V
sipush 23054
sipush 1806
invokestatic OS/Memory.poke(II)V
sipush 23056
sipush 7168
invokestatic OS/Memory.poke(II)V
sipush 23057
sipush 192
invokestatic OS/Memory.poke(II)V
sipush 23058
bipush 10
invokestatic OS/Memory.poke(II)V
sipush 23059
sipush 7168
invokestatic OS/Memory.poke(II)V
sipush 23060
bipush 24
invokestatic OS/Memory.poke(II)V
sipush 23061
sipush 1836
invokestatic OS/Memory.poke(II)V
sipush 23085
sipush 25088
invokestatic OS/Memory.poke(II)V
sipush 23086
sipush 1792
invokestatic OS/Memory.poke(II)V
sipush 23088
sipush 7168
invokestatic OS/Memory.poke(II)V
sipush 23089
sipush 1024
invokestatic OS/Memory.poke(II)V
sipush 23090
bipush 14
invokestatic OS/Memory.poke(II)V
sipush 23091
sipush 14336
invokestatic OS/Memory.poke(II)V
sipush 23092
bipush 112
invokestatic OS/Memory.poke(II)V
sipush 23093
sipush 1848
invokestatic OS/Memory.poke(II)V
sipush 23117
sipush 6656
invokestatic OS/Memory.poke(II)V
sipush 23118
sipush 1792
invokestatic OS/Memory.poke(II)V
sipush 23120
sipush 2048
ineg
invokestatic OS/Memory.poke(II)V
sipush 23121
sipush 4095
invokestatic OS/Memory.poke(II)V
sipush 23122
bipush 15
invokestatic OS/Memory.poke(II)V
sipush 23123
sipush 28672
invokestatic OS/Memory.poke(II)V
sipush 23124
sipush 192
invokestatic OS/Memory.poke(II)V
sipush 23125
sipush 1584
invokestatic OS/Memory.poke(II)V
sipush 23149
sipush 3584
invokestatic OS/Memory.poke(II)V
sipush 23150
sipush 1920
invokestatic OS/Memory.poke(II)V
sipush 23153
sipush 2032
invokestatic OS/Memory.poke(II)V
sipush 23154
bipush 31
invokestatic OS/Memory.poke(II)V
sipush 23155
sipush 8192
ineg
invokestatic OS/Memory.poke(II)V
sipush 23156
sipush 384
invokestatic OS/Memory.poke(II)V
sipush 23157
sipush 1072
invokestatic OS/Memory.poke(II)V
sipush 23181
sipush 1536
invokestatic OS/Memory.poke(II)V
sipush 23182
sipush 1920
invokestatic OS/Memory.poke(II)V
sipush 23185
sipush 15392
ineg
invokestatic OS/Memory.poke(II)V
sipush 23186
bipush 28
invokestatic OS/Memory.poke(II)V
sipush 23187
sipush 16384
ineg
invokestatic OS/Memory.poke(II)V
sipush 23188
sipush 769
invokestatic OS/Memory.poke(II)V
sipush 23189
sipush 1072
invokestatic OS/Memory.poke(II)V
sipush 23213
sipush 1024
invokestatic OS/Memory.poke(II)V
sipush 23214
sipush 1792
invokestatic OS/Memory.poke(II)V
sipush 23217
sipush 25568
invokestatic OS/Memory.poke(II)V
sipush 23218
bipush 28
invokestatic OS/Memory.poke(II)V
sipush 23219
sipush 16384
sipush 16384
iadd
invokestatic OS/Memory.poke(II)V
sipush 23220
sipush 1539
invokestatic OS/Memory.poke(II)V
sipush 23221
sipush 1072
invokestatic OS/Memory.poke(II)V
sipush 23245
sipush 13312
ineg
invokestatic OS/Memory.poke(II)V
sipush 23246
sipush 1792
invokestatic OS/Memory.poke(II)V
sipush 23249
sipush 960
invokestatic OS/Memory.poke(II)V
sipush 23250
bipush 24
invokestatic OS/Memory.poke(II)V
sipush 23252
sipush 7175
invokestatic OS/Memory.poke(II)V
sipush 23253
sipush 1072
invokestatic OS/Memory.poke(II)V
sipush 23277
sipush 26624
ineg
invokestatic OS/Memory.poke(II)V
sipush 23278
sipush 1920
invokestatic OS/Memory.poke(II)V
sipush 23281
sipush 1984
invokestatic OS/Memory.poke(II)V
sipush 23282
bipush 28
invokestatic OS/Memory.poke(II)V
sipush 23284
sipush 14364
invokestatic OS/Memory.poke(II)V
sipush 23285
sipush 1592
invokestatic OS/Memory.poke(II)V
sipush 23309
sipush 28672
ineg
invokestatic OS/Memory.poke(II)V
sipush 23310
sipush 1792
invokestatic OS/Memory.poke(II)V
sipush 23313
sipush 960
invokestatic OS/Memory.poke(II)V
sipush 23314
bipush 16
invokestatic OS/Memory.poke(II)V
sipush 23316
sipush 4040
ineg
invokestatic OS/Memory.poke(II)V
sipush 23317
sipush 527
invokestatic OS/Memory.poke(II)V
sipush 23341
sipush 24576
ineg
invokestatic OS/Memory.poke(II)V
sipush 23342
sipush 769
invokestatic OS/Memory.poke(II)V
sipush 23345
sipush 960
invokestatic OS/Memory.poke(II)V
sipush 23346
bipush 20
invokestatic OS/Memory.poke(II)V
sipush 23348
sipush 16288
ineg
invokestatic OS/Memory.poke(II)V
sipush 23349
sipush 519
invokestatic OS/Memory.poke(II)V
sipush 23373
sipush 8192
invokestatic OS/Memory.poke(II)V
sipush 23374
sipush 768
invokestatic OS/Memory.poke(II)V
sipush 23377
sipush 448
invokestatic OS/Memory.poke(II)V
sipush 23378
bipush 20
invokestatic OS/Memory.poke(II)V
sipush 23380
sipush 448
invokestatic OS/Memory.poke(II)V
sipush 23381
sipush 768
invokestatic OS/Memory.poke(II)V
sipush 23405
sipush 8192
invokestatic OS/Memory.poke(II)V
sipush 23406
sipush 256
invokestatic OS/Memory.poke(II)V
sipush 23409
sipush 448
invokestatic OS/Memory.poke(II)V
sipush 23410
bipush 16
invokestatic OS/Memory.poke(II)V
sipush 23412
sipush 896
invokestatic OS/Memory.poke(II)V
sipush 23413
sipush 256
invokestatic OS/Memory.poke(II)V
sipush 23437
sipush 8192
invokestatic OS/Memory.poke(II)V
sipush 23438
sipush 384
invokestatic OS/Memory.poke(II)V
sipush 23441
sipush 192
invokestatic OS/Memory.poke(II)V
sipush 23442
bipush 16
invokestatic OS/Memory.poke(II)V
sipush 23444
sipush 1792
invokestatic OS/Memory.poke(II)V
sipush 23445
sipush 448
invokestatic OS/Memory.poke(II)V
sipush 23469
sipush 16384
invokestatic OS/Memory.poke(II)V
sipush 23470
sipush 128
invokestatic OS/Memory.poke(II)V
sipush 23473
sipush 192
invokestatic OS/Memory.poke(II)V
sipush 23474
bipush 24
invokestatic OS/Memory.poke(II)V
sipush 23476
sipush 31744
invokestatic OS/Memory.poke(II)V
sipush 23477
sipush 252
invokestatic OS/Memory.poke(II)V
sipush 23501
sipush 16384
invokestatic OS/Memory.poke(II)V
sipush 23502
sipush 192
invokestatic OS/Memory.poke(II)V
sipush 23505
sipush 192
invokestatic OS/Memory.poke(II)V
sipush 23506
bipush 8
invokestatic OS/Memory.poke(II)V
sipush 23508
sipush 2048
ineg
invokestatic OS/Memory.poke(II)V
sipush 23509
bipush 63
invokestatic OS/Memory.poke(II)V
sipush 23533
sipush 16384
invokestatic OS/Memory.poke(II)V
sipush 23534
sipush 192
invokestatic OS/Memory.poke(II)V
sipush 23537
sipush 128
invokestatic OS/Memory.poke(II)V
sipush 23538
bipush 12
invokestatic OS/Memory.poke(II)V
sipush 23540
sipush 16384
ineg
invokestatic OS/Memory.poke(II)V
sipush 23541
bipush 7
invokestatic OS/Memory.poke(II)V
sipush 23565
sipush 16384
invokestatic OS/Memory.poke(II)V
sipush 23566
sipush 192
invokestatic OS/Memory.poke(II)V
sipush 23569
sipush 640
invokestatic OS/Memory.poke(II)V
sipush 23570
iconst_4
invokestatic OS/Memory.poke(II)V
sipush 23597
sipush 16384
invokestatic OS/Memory.poke(II)V
sipush 23598
sipush 960
invokestatic OS/Memory.poke(II)V
sipush 23601
sipush 896
invokestatic OS/Memory.poke(II)V
sipush 23602
iconst_4
invokestatic OS/Memory.poke(II)V
sipush 23629
sipush 16384
invokestatic OS/Memory.poke(II)V
sipush 23630
sipush 1664
invokestatic OS/Memory.poke(II)V
sipush 23633
sipush 1984
invokestatic OS/Memory.poke(II)V
sipush 23634
iconst_4
invokestatic OS/Memory.poke(II)V
sipush 23661
sipush 16384
invokestatic OS/Memory.poke(II)V
sipush 23662
sipush 1920
invokestatic OS/Memory.poke(II)V
sipush 23665
sipush 3520
invokestatic OS/Memory.poke(II)V
sipush 23666
iconst_4
invokestatic OS/Memory.poke(II)V
sipush 23693
sipush 16384
invokestatic OS/Memory.poke(II)V
sipush 23694
sipush 3456
invokestatic OS/Memory.poke(II)V
sipush 23697
sipush 5056
invokestatic OS/Memory.poke(II)V
sipush 23698
bipush 6
invokestatic OS/Memory.poke(II)V
sipush 23725
sipush 16384
invokestatic OS/Memory.poke(II)V
sipush 23726
sipush 14720
invokestatic OS/Memory.poke(II)V
sipush 23729
sipush 2016
invokestatic OS/Memory.poke(II)V
sipush 23730
bipush 6
invokestatic OS/Memory.poke(II)V
sipush 23757
sipush 24576
invokestatic OS/Memory.poke(II)V
sipush 23758
sipush 26496
invokestatic OS/Memory.poke(II)V
sipush 23761
sipush 496
invokestatic OS/Memory.poke(II)V
sipush 23762
bipush 6
invokestatic OS/Memory.poke(II)V
sipush 23789
sipush 4096
ineg
invokestatic OS/Memory.poke(II)V
sipush 23790
sipush 8320
ineg
invokestatic OS/Memory.poke(II)V
sipush 23793
bipush 120
invokestatic OS/Memory.poke(II)V
sipush 23794
bipush 14
invokestatic OS/Memory.poke(II)V
sipush 23821
sipush 512
ineg
invokestatic OS/Memory.poke(II)V
sipush 23822
sipush 24704
ineg
invokestatic OS/Memory.poke(II)V
sipush 23825
bipush 62
invokestatic OS/Memory.poke(II)V
sipush 23826
bipush 13
invokestatic OS/Memory.poke(II)V
sipush 23853
sipush 16512
ineg
invokestatic OS/Memory.poke(II)V
sipush 23854
sipush 25344
ineg
invokestatic OS/Memory.poke(II)V
sipush 23856
sipush 8192
ineg
invokestatic OS/Memory.poke(II)V
sipush 23857
bipush 11
invokestatic OS/Memory.poke(II)V
sipush 23858
bipush 25
invokestatic OS/Memory.poke(II)V
sipush 23885
sipush 20488
ineg
invokestatic OS/Memory.poke(II)V
sipush 23886
sipush 28415
ineg
invokestatic OS/Memory.poke(II)V
sipush 23888
sipush 12288
invokestatic OS/Memory.poke(II)V
sipush 23889
bipush 6
invokestatic OS/Memory.poke(II)V
sipush 23890
bipush 55
invokestatic OS/Memory.poke(II)V
sipush 23917
sipush 1871
invokestatic OS/Memory.poke(II)V
sipush 23918
sipush 3327
ineg
invokestatic OS/Memory.poke(II)V
sipush 23920
sipush 4096
invokestatic OS/Memory.poke(II)V
sipush 23921
bipush 14
invokestatic OS/Memory.poke(II)V
sipush 23922
bipush 47
invokestatic OS/Memory.poke(II)V
sipush 23948
sipush 16384
ineg
invokestatic OS/Memory.poke(II)V
sipush 23949
bipush 7
invokestatic OS/Memory.poke(II)V
sipush 23950
sipush 25088
invokestatic OS/Memory.poke(II)V
sipush 23952
sipush 26624
ineg
invokestatic OS/Memory.poke(II)V
sipush 23953
sipush 32738
ineg
invokestatic OS/Memory.poke(II)V
sipush 23954
bipush 123
invokestatic OS/Memory.poke(II)V
sipush 23980
sipush 24576
invokestatic OS/Memory.poke(II)V
sipush 23981
iconst_4
invokestatic OS/Memory.poke(II)V
sipush 23982
sipush 8960
invokestatic OS/Memory.poke(II)V
sipush 23984
sipush 18432
ineg
invokestatic OS/Memory.poke(II)V
sipush 23985
sipush 28769
ineg
invokestatic OS/Memory.poke(II)V
sipush 23986
bipush 113
invokestatic OS/Memory.poke(II)V
sipush 24012
sipush 8192
invokestatic OS/Memory.poke(II)V
sipush 24013
sipush 1542
invokestatic OS/Memory.poke(II)V
sipush 24014
sipush 256
invokestatic OS/Memory.poke(II)V
sipush 24016
sipush 2048
ineg
invokestatic OS/Memory.poke(II)V
sipush 24017
sipush 1801
ineg
invokestatic OS/Memory.poke(II)V
sipush 24018
bipush 7
invokestatic OS/Memory.poke(II)V
sipush 24044
sipush 8192
invokestatic OS/Memory.poke(II)V
sipush 24045
sipush 25729
ineg
invokestatic OS/Memory.poke(II)V
sipush 24046
sipush 449
invokestatic OS/Memory.poke(II)V
sipush 24048
sipush 2048
invokestatic OS/Memory.poke(II)V
sipush 24049
sipush 15481
invokestatic OS/Memory.poke(II)V
sipush 24076
sipush 8192
ineg
invokestatic OS/Memory.poke(II)V
sipush 24077
sipush 11833
ineg
invokestatic OS/Memory.poke(II)V
sipush 24078
bipush 127
invokestatic OS/Memory.poke(II)V
sipush 24080
sipush 2048
invokestatic OS/Memory.poke(II)V
sipush 24081
sipush 3697
invokestatic OS/Memory.poke(II)V
sipush 24108
sipush 24576
invokestatic OS/Memory.poke(II)V
sipush 24109
sipush 3646
ineg
invokestatic OS/Memory.poke(II)V
sipush 24110
iconst_1
invokestatic OS/Memory.poke(II)V
sipush 24112
sipush 16384
sipush 16384
iadd
invokestatic OS/Memory.poke(II)V
sipush 24113
sipush 1881
invokestatic OS/Memory.poke(II)V
sipush 24141
sipush 12787
invokestatic OS/Memory.poke(II)V
sipush 24144
sipush 16384
sipush 16384
iadd
invokestatic OS/Memory.poke(II)V
sipush 24145
sipush 333
invokestatic OS/Memory.poke(II)V
sipush 24173
sipush 15679
invokestatic OS/Memory.poke(II)V
sipush 24176
sipush 16384
sipush 16384
iadd
invokestatic OS/Memory.poke(II)V
sipush 24177
sipush 327
invokestatic OS/Memory.poke(II)V
sipush 24205
sipush 1821
invokestatic OS/Memory.poke(II)V
sipush 24209
sipush 451
invokestatic OS/Memory.poke(II)V
return
.end method
.method public static drawFlash()V
.limit stack 10
.limit locals 0
sipush 18574
sipush 8192
ineg
invokestatic OS/Memory.poke(II)V
sipush 18575
bipush 15
invokestatic OS/Memory.poke(II)V
sipush 18606
sipush 2048
ineg
invokestatic OS/Memory.poke(II)V
sipush 18607
sipush 24591
invokestatic OS/Memory.poke(II)V
sipush 18608
bipush 24
invokestatic OS/Memory.poke(II)V
sipush 18638
sipush 2048
ineg
invokestatic OS/Memory.poke(II)V
sipush 18639
sipush 2033
ineg
invokestatic OS/Memory.poke(II)V
sipush 18640
bipush 31
invokestatic OS/Memory.poke(II)V
sipush 18670
sipush 17408
ineg
invokestatic OS/Memory.poke(II)V
sipush 18671
sipush 2034
ineg
invokestatic OS/Memory.poke(II)V
sipush 18672
bipush 63
invokestatic OS/Memory.poke(II)V
sipush 18702
sipush 16640
ineg
invokestatic OS/Memory.poke(II)V
sipush 18703
sipush 2017
ineg
invokestatic OS/Memory.poke(II)V
sipush 18704
sipush 255
invokestatic OS/Memory.poke(II)V
sipush 18734
sipush 16448
ineg
invokestatic OS/Memory.poke(II)V
sipush 18735
iconst_1
ineg
invokestatic OS/Memory.poke(II)V
sipush 18736
sipush 2047
invokestatic OS/Memory.poke(II)V
sipush 18766
sipush 12304
ineg
invokestatic OS/Memory.poke(II)V
sipush 18767
iconst_1
ineg
invokestatic OS/Memory.poke(II)V
sipush 18768
sipush 16353
invokestatic OS/Memory.poke(II)V
sipush 18798
sipush 4112
ineg
invokestatic OS/Memory.poke(II)V
sipush 18799
iconst_1
ineg
invokestatic OS/Memory.poke(II)V
sipush 18800
sipush 16256
invokestatic OS/Memory.poke(II)V
sipush 18830
sipush 4112
ineg
invokestatic OS/Memory.poke(II)V
sipush 18831
iconst_1
ineg
invokestatic OS/Memory.poke(II)V
sipush 18832
sipush 16256
invokestatic OS/Memory.poke(II)V
sipush 18862
bipush 16
ineg
invokestatic OS/Memory.poke(II)V
sipush 18863
sipush 4095
invokestatic OS/Memory.poke(II)V
sipush 18864
sipush 7936
invokestatic OS/Memory.poke(II)V
sipush 18894
iconst_2
ineg
invokestatic OS/Memory.poke(II)V
sipush 18895
sipush 2047
invokestatic OS/Memory.poke(II)V
sipush 18896
sipush 7680
invokestatic OS/Memory.poke(II)V
sipush 18926
iconst_1
ineg
invokestatic OS/Memory.poke(II)V
sipush 18927
sipush 2047
invokestatic OS/Memory.poke(II)V
sipush 18928
sipush 3584
invokestatic OS/Memory.poke(II)V
sipush 18957
sipush 16384
sipush 16384
iadd
invokestatic OS/Memory.poke(II)V
sipush 18958
iconst_1
ineg
invokestatic OS/Memory.poke(II)V
sipush 18959
sipush 2047
invokestatic OS/Memory.poke(II)V
sipush 18960
sipush 3584
invokestatic OS/Memory.poke(II)V
sipush 18989
sipush 16384
sipush 16384
iadd
invokestatic OS/Memory.poke(II)V
sipush 18990
iconst_1
ineg
invokestatic OS/Memory.poke(II)V
sipush 18991
sipush 2047
invokestatic OS/Memory.poke(II)V
sipush 18992
sipush 3072
invokestatic OS/Memory.poke(II)V
sipush 19021
sipush 16384
sipush 16384
iadd
invokestatic OS/Memory.poke(II)V
sipush 19022
iconst_1
ineg
invokestatic OS/Memory.poke(II)V
sipush 19023
sipush 2047
invokestatic OS/Memory.poke(II)V
sipush 19024
sipush 7168
invokestatic OS/Memory.poke(II)V
sipush 19053
sipush 2048
ineg
invokestatic OS/Memory.poke(II)V
sipush 19054
iconst_1
ineg
invokestatic OS/Memory.poke(II)V
sipush 19055
sipush 2047
invokestatic OS/Memory.poke(II)V
sipush 19056
sipush 7168
invokestatic OS/Memory.poke(II)V
sipush 19085
sipush 2048
ineg
invokestatic OS/Memory.poke(II)V
sipush 19086
sipush 16385
ineg
invokestatic OS/Memory.poke(II)V
sipush 19087
sipush 2013
invokestatic OS/Memory.poke(II)V
sipush 19088
sipush 15360
invokestatic OS/Memory.poke(II)V
sipush 19117
sipush 2048
ineg
invokestatic OS/Memory.poke(II)V
sipush 19118
sipush 16383
invokestatic OS/Memory.poke(II)V
sipush 19119
sipush 28640
invokestatic OS/Memory.poke(II)V
sipush 19120
sipush 15360
invokestatic OS/Memory.poke(II)V
sipush 19149
sipush 2048
ineg
invokestatic OS/Memory.poke(II)V
sipush 19150
sipush 16383
invokestatic OS/Memory.poke(II)V
sipush 19151
sipush 8196
ineg
invokestatic OS/Memory.poke(II)V
sipush 19152
sipush 7168
invokestatic OS/Memory.poke(II)V
sipush 19181
sipush 2048
ineg
invokestatic OS/Memory.poke(II)V
sipush 19182
sipush 16383
invokestatic OS/Memory.poke(II)V
sipush 19183
sipush 24584
ineg
invokestatic OS/Memory.poke(II)V
sipush 19184
sipush 7936
invokestatic OS/Memory.poke(II)V
sipush 19213
sipush 2048
ineg
invokestatic OS/Memory.poke(II)V
sipush 19214
sipush 4095
invokestatic OS/Memory.poke(II)V
sipush 19215
sipush 24584
ineg
invokestatic OS/Memory.poke(II)V
sipush 19216
sipush 7937
invokestatic OS/Memory.poke(II)V
sipush 19245
sipush 2048
ineg
invokestatic OS/Memory.poke(II)V
sipush 19246
sipush 4095
invokestatic OS/Memory.poke(II)V
sipush 19247
sipush 24584
ineg
invokestatic OS/Memory.poke(II)V
sipush 19248
sipush 7937
invokestatic OS/Memory.poke(II)V
sipush 19277
sipush 16384
ineg
invokestatic OS/Memory.poke(II)V
sipush 19278
sipush 8191
invokestatic OS/Memory.poke(II)V
sipush 19279
sipush 24832
ineg
invokestatic OS/Memory.poke(II)V
sipush 19280
sipush 7939
invokestatic OS/Memory.poke(II)V
sipush 19309
sipush 16384
ineg
invokestatic OS/Memory.poke(II)V
sipush 19310
sipush 2047
invokestatic OS/Memory.poke(II)V
sipush 19311
sipush 25088
ineg
invokestatic OS/Memory.poke(II)V
sipush 19312
sipush 7939
invokestatic OS/Memory.poke(II)V
sipush 19341
sipush 16384
ineg
invokestatic OS/Memory.poke(II)V
sipush 19342
bipush 119
invokestatic OS/Memory.poke(II)V
sipush 19343
sipush 25600
ineg
invokestatic OS/Memory.poke(II)V
sipush 19344
sipush 4039
invokestatic OS/Memory.poke(II)V
sipush 19373
sipush 8192
ineg
invokestatic OS/Memory.poke(II)V
sipush 19374
bipush 35
invokestatic OS/Memory.poke(II)V
sipush 19375
sipush 6144
invokestatic OS/Memory.poke(II)V
sipush 19376
sipush 2046
invokestatic OS/Memory.poke(II)V
sipush 19405
sipush 2048
ineg
invokestatic OS/Memory.poke(II)V
sipush 19407
sipush 6144
invokestatic OS/Memory.poke(II)V
sipush 19408
sipush 1022
invokestatic OS/Memory.poke(II)V
sipush 19437
sipush 31744
invokestatic OS/Memory.poke(II)V
sipush 19440
sipush 1022
invokestatic OS/Memory.poke(II)V
sipush 19469
sipush 15360
invokestatic OS/Memory.poke(II)V
sipush 19472
bipush 62
invokestatic OS/Memory.poke(II)V
sipush 19501
sipush 7680
invokestatic OS/Memory.poke(II)V
sipush 19504
bipush 62
invokestatic OS/Memory.poke(II)V
sipush 19533
sipush 7936
invokestatic OS/Memory.poke(II)V
sipush 19536
sipush 2046
invokestatic OS/Memory.poke(II)V
sipush 19565
sipush 32640
invokestatic OS/Memory.poke(II)V
sipush 19568
sipush 4068
invokestatic OS/Memory.poke(II)V
sipush 19597
bipush 16
ineg
invokestatic OS/Memory.poke(II)V
sipush 19598
iconst_1
invokestatic OS/Memory.poke(II)V
sipush 19600
sipush 32736
invokestatic OS/Memory.poke(II)V
sipush 19629
bipush 16
ineg
invokestatic OS/Memory.poke(II)V
sipush 19632
sipush 128
ineg
invokestatic OS/Memory.poke(II)V
sipush 19661
bipush 16
ineg
invokestatic OS/Memory.poke(II)V
sipush 19664
sipush 128
ineg
invokestatic OS/Memory.poke(II)V
sipush 19693
sipush 16376
invokestatic OS/Memory.poke(II)V
sipush 19696
sipush 15872
invokestatic OS/Memory.poke(II)V
sipush 19725
sipush 8176
invokestatic OS/Memory.poke(II)V
sipush 19728
sipush 15616
invokestatic OS/Memory.poke(II)V
sipush 19757
sipush 8176
invokestatic OS/Memory.poke(II)V
sipush 19760
sipush 32512
invokestatic OS/Memory.poke(II)V
sipush 19789
sipush 8128
invokestatic OS/Memory.poke(II)V
sipush 19792
sipush 512
ineg
invokestatic OS/Memory.poke(II)V
sipush 19793
sipush 480
invokestatic OS/Memory.poke(II)V
sipush 19821
sipush 8128
invokestatic OS/Memory.poke(II)V
sipush 19824
sipush 1024
ineg
invokestatic OS/Memory.poke(II)V
sipush 19825
sipush 4095
invokestatic OS/Memory.poke(II)V
sipush 19853
sipush 8160
invokestatic OS/Memory.poke(II)V
sipush 19856
sipush 1024
ineg
invokestatic OS/Memory.poke(II)V
sipush 19857
sipush 4095
invokestatic OS/Memory.poke(II)V
sipush 19885
sipush 2016
invokestatic OS/Memory.poke(II)V
sipush 19888
sipush 1024
ineg
invokestatic OS/Memory.poke(II)V
sipush 19889
sipush 4095
invokestatic OS/Memory.poke(II)V
sipush 19917
sipush 8160
invokestatic OS/Memory.poke(II)V
sipush 19920
sipush 256
ineg
invokestatic OS/Memory.poke(II)V
sipush 19921
sipush 8191
invokestatic OS/Memory.poke(II)V
sipush 19949
sipush 16352
invokestatic OS/Memory.poke(II)V
sipush 19952
sipush 128
ineg
invokestatic OS/Memory.poke(II)V
sipush 19953
sipush 16383
invokestatic OS/Memory.poke(II)V
sipush 19981
sipush 32752
invokestatic OS/Memory.poke(II)V
sipush 19984
sipush 2913
ineg
invokestatic OS/Memory.poke(II)V
sipush 19985
sipush 16383
invokestatic OS/Memory.poke(II)V
sipush 20013
sipush 32760
invokestatic OS/Memory.poke(II)V
sipush 20015
sipush 16384
sipush 16384
iadd
invokestatic OS/Memory.poke(II)V
sipush 20016
sipush 12097
ineg
invokestatic OS/Memory.poke(II)V
sipush 20017
iconst_1
ineg
invokestatic OS/Memory.poke(II)V
sipush 20018
bipush 28
invokestatic OS/Memory.poke(II)V
sipush 20045
sipush 16376
invokestatic OS/Memory.poke(II)V
sipush 20048
sipush 16321
ineg
invokestatic OS/Memory.poke(II)V
sipush 20049
bipush 15
ineg
invokestatic OS/Memory.poke(II)V
sipush 20050
bipush 127
invokestatic OS/Memory.poke(II)V
sipush 20077
sipush 16376
invokestatic OS/Memory.poke(II)V
sipush 20080
sipush 16321
ineg
invokestatic OS/Memory.poke(II)V
sipush 20081
bipush 15
ineg
invokestatic OS/Memory.poke(II)V
sipush 20082
bipush 127
invokestatic OS/Memory.poke(II)V
sipush 20109
bipush 28
invokestatic OS/Memory.poke(II)V
sipush 20111
sipush 16384
sipush 16384
iadd
invokestatic OS/Memory.poke(II)V
sipush 20112
bipush 63
invokestatic OS/Memory.poke(II)V
sipush 20113
sipush 897
ineg
invokestatic OS/Memory.poke(II)V
sipush 20114
sipush 255
invokestatic OS/Memory.poke(II)V
sipush 20141
bipush 30
invokestatic OS/Memory.poke(II)V
sipush 20143
sipush 16384
sipush 16384
iadd
invokestatic OS/Memory.poke(II)V
sipush 20144
bipush 127
invokestatic OS/Memory.poke(II)V
sipush 20145
sipush 993
ineg
invokestatic OS/Memory.poke(II)V
sipush 20146
sipush 511
invokestatic OS/Memory.poke(II)V
sipush 20172
sipush 16384
sipush 16384
iadd
invokestatic OS/Memory.poke(II)V
sipush 20173
bipush 31
invokestatic OS/Memory.poke(II)V
sipush 20175
sipush 16384
sipush 16384
iadd
invokestatic OS/Memory.poke(II)V
sipush 20176
bipush 127
invokestatic OS/Memory.poke(II)V
sipush 20177
sipush 512
ineg
invokestatic OS/Memory.poke(II)V
sipush 20178
sipush 1023
invokestatic OS/Memory.poke(II)V
sipush 20204
sipush 8192
ineg
invokestatic OS/Memory.poke(II)V
sipush 20205
bipush 31
invokestatic OS/Memory.poke(II)V
sipush 20207
sipush 16384
sipush 16384
iadd
invokestatic OS/Memory.poke(II)V
sipush 20208
bipush 127
invokestatic OS/Memory.poke(II)V
sipush 20209
sipush 512
ineg
invokestatic OS/Memory.poke(II)V
sipush 20210
sipush 1023
invokestatic OS/Memory.poke(II)V
sipush 20236
sipush 8192
ineg
invokestatic OS/Memory.poke(II)V
sipush 20237
bipush 15
invokestatic OS/Memory.poke(II)V
sipush 20239
sipush 452
ineg
invokestatic OS/Memory.poke(II)V
sipush 20240
bipush 7
invokestatic OS/Memory.poke(II)V
sipush 20241
bipush 64
ineg
invokestatic OS/Memory.poke(II)V
sipush 20242
sipush 1023
invokestatic OS/Memory.poke(II)V
sipush 20268
sipush 4096
ineg
invokestatic OS/Memory.poke(II)V
sipush 20269
bipush 15
invokestatic OS/Memory.poke(II)V
sipush 20271
sipush 484
ineg
invokestatic OS/Memory.poke(II)V
sipush 20272
iconst_3
invokestatic OS/Memory.poke(II)V
sipush 20273
bipush 32
ineg
invokestatic OS/Memory.poke(II)V
sipush 20274
sipush 1023
invokestatic OS/Memory.poke(II)V
sipush 20300
sipush 2048
ineg
invokestatic OS/Memory.poke(II)V
sipush 20301
bipush 15
invokestatic OS/Memory.poke(II)V
sipush 20303
sipush 484
ineg
invokestatic OS/Memory.poke(II)V
sipush 20304
iconst_3
invokestatic OS/Memory.poke(II)V
sipush 20305
bipush 32
ineg
invokestatic OS/Memory.poke(II)V
sipush 20306
sipush 4095
invokestatic OS/Memory.poke(II)V
sipush 20332
sipush 2048
ineg
invokestatic OS/Memory.poke(II)V
sipush 20333
sipush 16383
invokestatic OS/Memory.poke(II)V
sipush 20335
sipush 3588
ineg
invokestatic OS/Memory.poke(II)V
sipush 20336
iconst_5
invokestatic OS/Memory.poke(II)V
sipush 20337
bipush 32
ineg
invokestatic OS/Memory.poke(II)V
sipush 20338
sipush 4095
invokestatic OS/Memory.poke(II)V
sipush 20364
sipush 8192
ineg
invokestatic OS/Memory.poke(II)V
sipush 20365
sipush 16383
invokestatic OS/Memory.poke(II)V
sipush 20367
sipush 1986
ineg
invokestatic OS/Memory.poke(II)V
sipush 20368
sipush 32705
ineg
invokestatic OS/Memory.poke(II)V
sipush 20369
iconst_1
ineg
invokestatic OS/Memory.poke(II)V
sipush 20370
sipush 4095
invokestatic OS/Memory.poke(II)V
sipush 20397
sipush 16382
invokestatic OS/Memory.poke(II)V
sipush 20399
sipush 30975
invokestatic OS/Memory.poke(II)V
sipush 20400
sipush 32514
ineg
invokestatic OS/Memory.poke(II)V
sipush 20401
iconst_1
ineg
invokestatic OS/Memory.poke(II)V
sipush 20402
sipush 2047
invokestatic OS/Memory.poke(II)V
sipush 20429
sipush 31864
invokestatic OS/Memory.poke(II)V
sipush 20431
sipush 769
ineg
invokestatic OS/Memory.poke(II)V
sipush 20432
sipush 8065
ineg
invokestatic OS/Memory.poke(II)V
sipush 20433
iconst_1
ineg
invokestatic OS/Memory.poke(II)V
sipush 20434
sipush 2047
invokestatic OS/Memory.poke(II)V
sipush 20461
sipush 31760
invokestatic OS/Memory.poke(II)V
sipush 20463
sipush 319
ineg
invokestatic OS/Memory.poke(II)V
sipush 20464
sipush 8129
ineg
invokestatic OS/Memory.poke(II)V
sipush 20465
iconst_1
ineg
invokestatic OS/Memory.poke(II)V
sipush 20466
sipush 1999
invokestatic OS/Memory.poke(II)V
sipush 20467
sipush 384
invokestatic OS/Memory.poke(II)V
sipush 20493
sipush 31760
invokestatic OS/Memory.poke(II)V
sipush 20495
sipush 319
ineg
invokestatic OS/Memory.poke(II)V
sipush 20496
sipush 8129
ineg
invokestatic OS/Memory.poke(II)V
sipush 20497
iconst_1
ineg
invokestatic OS/Memory.poke(II)V
sipush 20498
sipush 1999
invokestatic OS/Memory.poke(II)V
sipush 20499
sipush 384
invokestatic OS/Memory.poke(II)V
sipush 20525
sipush 30720
invokestatic OS/Memory.poke(II)V
sipush 20527
sipush 15872
invokestatic OS/Memory.poke(II)V
sipush 20528
sipush 8192
ineg
invokestatic OS/Memory.poke(II)V
sipush 20529
iconst_1
ineg
invokestatic OS/Memory.poke(II)V
sipush 20530
sipush 3999
invokestatic OS/Memory.poke(II)V
sipush 20531
sipush 1984
invokestatic OS/Memory.poke(II)V
sipush 20556
sipush 16384
sipush 16384
iadd
invokestatic OS/Memory.poke(II)V
sipush 20557
sipush 14337
invokestatic OS/Memory.poke(II)V
sipush 20559
sipush 3072
invokestatic OS/Memory.poke(II)V
sipush 20560
sipush 8192
ineg
invokestatic OS/Memory.poke(II)V
sipush 20561
iconst_1
ineg
invokestatic OS/Memory.poke(II)V
sipush 20562
sipush 15887
invokestatic OS/Memory.poke(II)V
sipush 20563
sipush 1920
invokestatic OS/Memory.poke(II)V
sipush 20588
sipush 8192
ineg
invokestatic OS/Memory.poke(II)V
sipush 20589
sipush 14343
invokestatic OS/Memory.poke(II)V
sipush 20592
sipush 16384
ineg
invokestatic OS/Memory.poke(II)V
sipush 20593
iconst_1
ineg
invokestatic OS/Memory.poke(II)V
sipush 20594
sipush 1021
ineg
invokestatic OS/Memory.poke(II)V
sipush 20595
bipush 14
invokestatic OS/Memory.poke(II)V
sipush 20620
sipush 16384
sipush 16384
iadd
invokestatic OS/Memory.poke(II)V
sipush 20621
sipush 24583
invokestatic OS/Memory.poke(II)V
sipush 20625
iconst_1
ineg
invokestatic OS/Memory.poke(II)V
sipush 20626
sipush 1017
ineg
invokestatic OS/Memory.poke(II)V
sipush 20627
bipush 31
invokestatic OS/Memory.poke(II)V
sipush 20653
sipush 14343
invokestatic OS/Memory.poke(II)V
sipush 20657
iconst_1
ineg
invokestatic OS/Memory.poke(II)V
sipush 20658
sipush 16381
ineg
invokestatic OS/Memory.poke(II)V
sipush 20659
bipush 31
invokestatic OS/Memory.poke(II)V
sipush 20685
sipush 7686
invokestatic OS/Memory.poke(II)V
sipush 20689
iconst_1
ineg
invokestatic OS/Memory.poke(II)V
sipush 20690
sipush 16381
ineg
invokestatic OS/Memory.poke(II)V
sipush 20691
bipush 31
invokestatic OS/Memory.poke(II)V
sipush 20717
sipush 7686
invokestatic OS/Memory.poke(II)V
sipush 20721
sipush 16383
invokestatic OS/Memory.poke(II)V
sipush 20722
sipush 16384
ineg
invokestatic OS/Memory.poke(II)V
sipush 20723
bipush 31
invokestatic OS/Memory.poke(II)V
sipush 20749
sipush 2046
invokestatic OS/Memory.poke(II)V
sipush 20753
sipush 16383
invokestatic OS/Memory.poke(II)V
sipush 20754
sipush 16384
ineg
invokestatic OS/Memory.poke(II)V
sipush 20755
bipush 15
invokestatic OS/Memory.poke(II)V
sipush 20781
sipush 2046
invokestatic OS/Memory.poke(II)V
sipush 20785
sipush 8191
invokestatic OS/Memory.poke(II)V
sipush 20786
sipush 16384
ineg
invokestatic OS/Memory.poke(II)V
sipush 20787
bipush 31
invokestatic OS/Memory.poke(II)V
sipush 20813
sipush 1020
invokestatic OS/Memory.poke(II)V
sipush 20817
sipush 4095
invokestatic OS/Memory.poke(II)V
sipush 20818
sipush 16384
ineg
invokestatic OS/Memory.poke(II)V
sipush 20819
bipush 31
invokestatic OS/Memory.poke(II)V
sipush 20845
sipush 1020
invokestatic OS/Memory.poke(II)V
sipush 20849
sipush 3584
invokestatic OS/Memory.poke(II)V
sipush 20850
sipush 16384
ineg
invokestatic OS/Memory.poke(II)V
sipush 20851
bipush 15
invokestatic OS/Memory.poke(II)V
sipush 20877
sipush 508
invokestatic OS/Memory.poke(II)V
sipush 20881
sipush 768
invokestatic OS/Memory.poke(II)V
sipush 20882
sipush 16384
ineg
invokestatic OS/Memory.poke(II)V
sipush 20883
bipush 15
invokestatic OS/Memory.poke(II)V
sipush 20909
sipush 508
invokestatic OS/Memory.poke(II)V
sipush 20913
sipush 768
invokestatic OS/Memory.poke(II)V
sipush 20914
sipush 16384
ineg
invokestatic OS/Memory.poke(II)V
sipush 20915
bipush 15
invokestatic OS/Memory.poke(II)V
sipush 20941
sipush 8700
invokestatic OS/Memory.poke(II)V
sipush 20945
sipush 2016
invokestatic OS/Memory.poke(II)V
sipush 20946
sipush 16384
ineg
invokestatic OS/Memory.poke(II)V
sipush 20947
bipush 15
invokestatic OS/Memory.poke(II)V
sipush 20973
sipush 14840
invokestatic OS/Memory.poke(II)V
sipush 20977
sipush 4064
invokestatic OS/Memory.poke(II)V
sipush 20978
sipush 16384
ineg
invokestatic OS/Memory.poke(II)V
sipush 20979
bipush 31
invokestatic OS/Memory.poke(II)V
sipush 21005
sipush 16376
invokestatic OS/Memory.poke(II)V
sipush 21009
sipush 12320
ineg
invokestatic OS/Memory.poke(II)V
sipush 21010
sipush 16384
ineg
invokestatic OS/Memory.poke(II)V
sipush 21011
bipush 31
invokestatic OS/Memory.poke(II)V
sipush 21037
sipush 16368
invokestatic OS/Memory.poke(II)V
sipush 21041
sipush 4128
ineg
invokestatic OS/Memory.poke(II)V
sipush 21042
sipush 4093
ineg
invokestatic OS/Memory.poke(II)V
sipush 21043
bipush 15
invokestatic OS/Memory.poke(II)V
sipush 21069
sipush 480
ineg
invokestatic OS/Memory.poke(II)V
sipush 21073
bipush 64
ineg
invokestatic OS/Memory.poke(II)V
sipush 21074
sipush 16353
ineg
invokestatic OS/Memory.poke(II)V
sipush 21075
bipush 7
invokestatic OS/Memory.poke(II)V
sipush 21101
sipush 32512
invokestatic OS/Memory.poke(II)V
sipush 21105
sipush 128
ineg
invokestatic OS/Memory.poke(II)V
sipush 21106
sipush 4081
ineg
invokestatic OS/Memory.poke(II)V
sipush 21107
iconst_3
invokestatic OS/Memory.poke(II)V
sipush 21133
sipush 32664
invokestatic OS/Memory.poke(II)V
sipush 21137
sipush 256
ineg
invokestatic OS/Memory.poke(II)V
sipush 21138
sipush 2033
ineg
invokestatic OS/Memory.poke(II)V
sipush 21139
bipush 7
invokestatic OS/Memory.poke(II)V
sipush 21165
iconst_4
ineg
invokestatic OS/Memory.poke(II)V
sipush 21169
sipush 256
ineg
invokestatic OS/Memory.poke(II)V
sipush 21170
sipush 993
ineg
invokestatic OS/Memory.poke(II)V
sipush 21171
iconst_1
invokestatic OS/Memory.poke(II)V
sipush 21197
iconst_4
ineg
invokestatic OS/Memory.poke(II)V
sipush 21198
iconst_1
invokestatic OS/Memory.poke(II)V
sipush 21201
sipush 256
ineg
invokestatic OS/Memory.poke(II)V
sipush 21202
sipush 509
ineg
invokestatic OS/Memory.poke(II)V
sipush 21203
iconst_3
invokestatic OS/Memory.poke(II)V
sipush 21229
iconst_4
ineg
invokestatic OS/Memory.poke(II)V
sipush 21230
iconst_1
invokestatic OS/Memory.poke(II)V
sipush 21233
sipush 512
ineg
invokestatic OS/Memory.poke(II)V
sipush 21234
sipush 505
ineg
invokestatic OS/Memory.poke(II)V
sipush 21235
iconst_1
invokestatic OS/Memory.poke(II)V
sipush 21261
iconst_2
ineg
invokestatic OS/Memory.poke(II)V
sipush 21262
iconst_1
invokestatic OS/Memory.poke(II)V
sipush 21265
sipush 4096
ineg
invokestatic OS/Memory.poke(II)V
sipush 21266
sipush 16143
invokestatic OS/Memory.poke(II)V
sipush 21293
bipush 52
ineg
invokestatic OS/Memory.poke(II)V
sipush 21297
sipush 16384
ineg
invokestatic OS/Memory.poke(II)V
sipush 21298
sipush 16143
invokestatic OS/Memory.poke(II)V
sipush 21325
bipush 52
ineg
invokestatic OS/Memory.poke(II)V
sipush 21329
sipush 16384
ineg
invokestatic OS/Memory.poke(II)V
sipush 21330
sipush 16143
invokestatic OS/Memory.poke(II)V
sipush 21357
bipush 64
ineg
invokestatic OS/Memory.poke(II)V
sipush 21362
sipush 16191
invokestatic OS/Memory.poke(II)V
sipush 21389
bipush 64
ineg
invokestatic OS/Memory.poke(II)V
sipush 21394
sipush 4094
invokestatic OS/Memory.poke(II)V
sipush 21421
bipush 56
ineg
invokestatic OS/Memory.poke(II)V
sipush 21426
sipush 4092
invokestatic OS/Memory.poke(II)V
sipush 21453
sipush 32748
invokestatic OS/Memory.poke(II)V
sipush 21458
sipush 4092
invokestatic OS/Memory.poke(II)V
sipush 21485
sipush 32652
invokestatic OS/Memory.poke(II)V
sipush 21490
sipush 4092
invokestatic OS/Memory.poke(II)V
sipush 21517
sipush 32648
invokestatic OS/Memory.poke(II)V
sipush 21522
sipush 4088
invokestatic OS/Memory.poke(II)V
sipush 21549
sipush 32640
invokestatic OS/Memory.poke(II)V
sipush 21553
sipush 8192
ineg
invokestatic OS/Memory.poke(II)V
sipush 21554
sipush 4091
invokestatic OS/Memory.poke(II)V
sipush 21581
sipush 32512
invokestatic OS/Memory.poke(II)V
sipush 21582
iconst_1
invokestatic OS/Memory.poke(II)V
sipush 21585
sipush 8192
ineg
invokestatic OS/Memory.poke(II)V
sipush 21586
sipush 4091
invokestatic OS/Memory.poke(II)V
sipush 21613
sipush 256
ineg
invokestatic OS/Memory.poke(II)V
sipush 21614
iconst_1
invokestatic OS/Memory.poke(II)V
sipush 21617
sipush 8192
ineg
invokestatic OS/Memory.poke(II)V
sipush 21618
sipush 4083
invokestatic OS/Memory.poke(II)V
sipush 21645
sipush 512
ineg
invokestatic OS/Memory.poke(II)V
sipush 21646
bipush 7
invokestatic OS/Memory.poke(II)V
sipush 21649
sipush 16384
ineg
invokestatic OS/Memory.poke(II)V
sipush 21650
sipush 16383
invokestatic OS/Memory.poke(II)V
sipush 21677
sipush 512
ineg
invokestatic OS/Memory.poke(II)V
sipush 21678
bipush 15
invokestatic OS/Memory.poke(II)V
sipush 21681
sipush 15424
ineg
invokestatic OS/Memory.poke(II)V
sipush 21682
sipush 16383
invokestatic OS/Memory.poke(II)V
sipush 21709
sipush 6144
invokestatic OS/Memory.poke(II)V
sipush 21710
bipush 14
invokestatic OS/Memory.poke(II)V
sipush 21713
bipush 32
ineg
invokestatic OS/Memory.poke(II)V
sipush 21714
sipush 32767
invokestatic OS/Memory.poke(II)V
sipush 21741
sipush 6144
invokestatic OS/Memory.poke(II)V
sipush 21742
bipush 14
invokestatic OS/Memory.poke(II)V
sipush 21745
bipush 32
ineg
invokestatic OS/Memory.poke(II)V
sipush 21746
sipush 32767
invokestatic OS/Memory.poke(II)V
sipush 21774
sipush 254
invokestatic OS/Memory.poke(II)V
sipush 21777
bipush 16
ineg
invokestatic OS/Memory.poke(II)V
sipush 21778
sipush 32764
invokestatic OS/Memory.poke(II)V
sipush 21806
sipush 1020
invokestatic OS/Memory.poke(II)V
sipush 21809
bipush 8
ineg
invokestatic OS/Memory.poke(II)V
sipush 21810
sipush 32767
invokestatic OS/Memory.poke(II)V
sipush 21838
sipush 1020
invokestatic OS/Memory.poke(II)V
sipush 21841
bipush 7
ineg
invokestatic OS/Memory.poke(II)V
sipush 21842
sipush 16383
invokestatic OS/Memory.poke(II)V
sipush 21870
sipush 1020
invokestatic OS/Memory.poke(II)V
sipush 21873
bipush 97
ineg
invokestatic OS/Memory.poke(II)V
sipush 21874
sipush 4095
invokestatic OS/Memory.poke(II)V
sipush 21902
sipush 2040
invokestatic OS/Memory.poke(II)V
sipush 21905
sipush 225
ineg
invokestatic OS/Memory.poke(II)V
sipush 21906
sipush 2044
invokestatic OS/Memory.poke(II)V
sipush 21934
sipush 4088
invokestatic OS/Memory.poke(II)V
sipush 21937
sipush 287
invokestatic OS/Memory.poke(II)V
sipush 21938
sipush 2044
invokestatic OS/Memory.poke(II)V
sipush 21966
sipush 16376
invokestatic OS/Memory.poke(II)V
sipush 21969
bipush 15
invokestatic OS/Memory.poke(II)V
sipush 21970
sipush 2044
invokestatic OS/Memory.poke(II)V
sipush 21998
sipush 16320
invokestatic OS/Memory.poke(II)V
sipush 22000
sipush 768
invokestatic OS/Memory.poke(II)V
sipush 22001
bipush 15
invokestatic OS/Memory.poke(II)V
sipush 22002
sipush 1020
invokestatic OS/Memory.poke(II)V
sipush 22030
sipush 32704
invokestatic OS/Memory.poke(II)V
sipush 22032
sipush 32000
ineg
invokestatic OS/Memory.poke(II)V
sipush 22033
bipush 7
invokestatic OS/Memory.poke(II)V
sipush 22034
sipush 2040
invokestatic OS/Memory.poke(II)V
sipush 22062
sipush 256
ineg
invokestatic OS/Memory.poke(II)V
sipush 22063
iconst_3
invokestatic OS/Memory.poke(II)V
sipush 22064
sipush 32000
ineg
invokestatic OS/Memory.poke(II)V
sipush 22065
bipush 7
invokestatic OS/Memory.poke(II)V
sipush 22066
sipush 1020
invokestatic OS/Memory.poke(II)V
sipush 22094
sipush 1024
ineg
invokestatic OS/Memory.poke(II)V
sipush 22095
iconst_3
invokestatic OS/Memory.poke(II)V
sipush 22096
sipush 16384
ineg
invokestatic OS/Memory.poke(II)V
sipush 22097
bipush 7
invokestatic OS/Memory.poke(II)V
sipush 22098
sipush 1022
invokestatic OS/Memory.poke(II)V
sipush 22126
sipush 4096
ineg
invokestatic OS/Memory.poke(II)V
sipush 22127
iconst_3
invokestatic OS/Memory.poke(II)V
sipush 22128
sipush 16384
ineg
invokestatic OS/Memory.poke(II)V
sipush 22129
bipush 7
invokestatic OS/Memory.poke(II)V
sipush 22130
sipush 510
invokestatic OS/Memory.poke(II)V
sipush 22158
sipush 4096
ineg
invokestatic OS/Memory.poke(II)V
sipush 22159
iconst_3
invokestatic OS/Memory.poke(II)V
sipush 22160
sipush 16384
ineg
invokestatic OS/Memory.poke(II)V
sipush 22161
bipush 7
invokestatic OS/Memory.poke(II)V
sipush 22162
sipush 510
invokestatic OS/Memory.poke(II)V
sipush 22190
sipush 4096
ineg
invokestatic OS/Memory.poke(II)V
sipush 22191
bipush 9
invokestatic OS/Memory.poke(II)V
sipush 22192
sipush 16384
ineg
invokestatic OS/Memory.poke(II)V
sipush 22193
bipush 7
invokestatic OS/Memory.poke(II)V
sipush 22194
sipush 508
invokestatic OS/Memory.poke(II)V
sipush 22222
sipush 4048
ineg
invokestatic OS/Memory.poke(II)V
sipush 22223
bipush 15
invokestatic OS/Memory.poke(II)V
sipush 22224
sipush 16384
ineg
invokestatic OS/Memory.poke(II)V
sipush 22225
iconst_1
invokestatic OS/Memory.poke(II)V
sipush 22226
bipush 120
invokestatic OS/Memory.poke(II)V
sipush 22254
sipush 4080
ineg
invokestatic OS/Memory.poke(II)V
sipush 22255
bipush 15
invokestatic OS/Memory.poke(II)V
sipush 22256
sipush 8192
ineg
invokestatic OS/Memory.poke(II)V
sipush 22286
sipush 4096
ineg
invokestatic OS/Memory.poke(II)V
sipush 22287
sipush 28735
invokestatic OS/Memory.poke(II)V
sipush 22288
sipush 4096
ineg
invokestatic OS/Memory.poke(II)V
sipush 22318
sipush 8192
ineg
invokestatic OS/Memory.poke(II)V
sipush 22319
sipush 32511
invokestatic OS/Memory.poke(II)V
sipush 22320
sipush 8192
ineg
invokestatic OS/Memory.poke(II)V
sipush 22350
sipush 8192
ineg
invokestatic OS/Memory.poke(II)V
sipush 22351
iconst_1
ineg
invokestatic OS/Memory.poke(II)V
sipush 22352
sipush 8192
ineg
invokestatic OS/Memory.poke(II)V
sipush 22382
sipush 8192
ineg
invokestatic OS/Memory.poke(II)V
sipush 22383
iconst_1
ineg
invokestatic OS/Memory.poke(II)V
sipush 22384
sipush 8192
ineg
invokestatic OS/Memory.poke(II)V
sipush 22385
iconst_1
invokestatic OS/Memory.poke(II)V
sipush 22414
sipush 16384
ineg
invokestatic OS/Memory.poke(II)V
sipush 22415
iconst_1
ineg
invokestatic OS/Memory.poke(II)V
sipush 22416
bipush 127
ineg
invokestatic OS/Memory.poke(II)V
sipush 22417
iconst_1
invokestatic OS/Memory.poke(II)V
sipush 22446
sipush 16384
ineg
invokestatic OS/Memory.poke(II)V
sipush 22447
iconst_1
ineg
invokestatic OS/Memory.poke(II)V
sipush 22448
bipush 29
ineg
invokestatic OS/Memory.poke(II)V
sipush 22449
bipush 7
invokestatic OS/Memory.poke(II)V
sipush 22478
sipush 16384
sipush 16384
iadd
invokestatic OS/Memory.poke(II)V
sipush 22479
sipush 257
ineg
invokestatic OS/Memory.poke(II)V
sipush 22480
iconst_1
ineg
invokestatic OS/Memory.poke(II)V
sipush 22481
bipush 7
invokestatic OS/Memory.poke(II)V
sipush 22510
sipush 16384
sipush 16384
iadd
invokestatic OS/Memory.poke(II)V
sipush 22511
sipush 449
ineg
invokestatic OS/Memory.poke(II)V
sipush 22512
iconst_1
ineg
invokestatic OS/Memory.poke(II)V
sipush 22513
bipush 7
invokestatic OS/Memory.poke(II)V
sipush 22543
sipush 31728
ineg
invokestatic OS/Memory.poke(II)V
sipush 22544
iconst_1
ineg
invokestatic OS/Memory.poke(II)V
sipush 22545
bipush 15
invokestatic OS/Memory.poke(II)V
sipush 22575
sipush 31728
ineg
invokestatic OS/Memory.poke(II)V
sipush 22576
iconst_1
ineg
invokestatic OS/Memory.poke(II)V
sipush 22577
bipush 15
invokestatic OS/Memory.poke(II)V
sipush 22607
sipush 32736
ineg
invokestatic OS/Memory.poke(II)V
sipush 22608
sipush 2049
ineg
invokestatic OS/Memory.poke(II)V
sipush 22609
bipush 15
invokestatic OS/Memory.poke(II)V
sipush 22639
sipush 16384
sipush 16384
iadd
invokestatic OS/Memory.poke(II)V
sipush 22640
sipush 2049
ineg
invokestatic OS/Memory.poke(II)V
sipush 22641
bipush 15
invokestatic OS/Memory.poke(II)V
sipush 22671
sipush 16384
sipush 16384
iadd
invokestatic OS/Memory.poke(II)V
sipush 22672
sipush 6241
ineg
invokestatic OS/Memory.poke(II)V
sipush 22673
bipush 15
invokestatic OS/Memory.poke(II)V
sipush 22704
sipush 32377
ineg
invokestatic OS/Memory.poke(II)V
sipush 22705
bipush 15
invokestatic OS/Memory.poke(II)V
return
.end method
